Workbook
Name __xlnm.Print_Area: #REF!
Name Add_Budget_Selection: #REF!
Name Analysis_End_Date: #REF!
Name Analysis_End_Month: #REF!
Name Analysis_Length_Months: #REF!
Name Analysis_Length_Years: #REF!
Name Analysis_Start_Date: #REF!
Name Analysis_Start_Month: #REF!
Name Category_1: #REF!
Name Category_2: #REF!
Name Category_3: #REF!
Name Category_4: #REF!
Name Category_5: #REF!
Name Category_6: #REF!
Name Category_7: #REF!
Name Const_End_Date: #REF!
Name Const_End_Month: #REF!
Name Const_Start_Date: #REF!
Name Construction_Int_Rate: #REF!
Name Construction_Length: #REF!
Name Construction_Loan_Amount: #REF!
Name Construction_Module_On?: #REF!
Name Equity_Contribution: #REF!
Name Equity_Share_LP: #REF!
Name Equity_Share_LP_Monthly: #REF!
Name Equity_Share_Sponsor: #REF!
Name Equity_Share_Sponsor_Monthly: #REF!
Name Financing_Module_On: #REF!
Name GL_Module_On?: #REF!
Name Ground_Lease_Years_Remaining: #REF!
Name Growth_Begin_Month: #REF!
Name Investment_Name: #REF!
Name Investment_Period_Months: #REF!
Name IRR_Type: #REF!
Name Jr_Funding_Month: #REF!
Name Label_SF_M2: #REF!
Name Label_Unit_Type: #REF!
Name Label_Unit_Type_Singular: #REF!
Name List_Location: OFFSET(#REF!,0,0,93-COUNTIF(#REF!,""),1)
Name List_Property_Type: OFFSET(#REF!,0,0,1,10-COUNTIF(#REF!,""))
Name Location: #REF!
Name LTC_Actual: #REF!
Name Manager_Salary_Per_Month: #N/A
Name Managersalaryper: #N/A
Name Managersalarypermonth: #N/A
Name MF_1st_Stab_Month: #REF!
Name MF_Module_On: #REF!
Name MF_Units: #REF!
Name MF_Untrended?: #REF!
Name NRA: #REF!
Name Operation_Period_Months: #REF!
Name Operations_Begin_Date: #REF!
Name Operations_Begin_Month: #REF!
Name ORI_1st_Stab_Month: #REF!
Name ORI_Module_On: #REF!
Name ORI_Untrended?: #REF!
Name Per_Unit_Type: #REF!
Name Perm_Debt_Funding: #REF!
Name PermDebt_Funding_Date: #REF!
Name PermDebt_Funding_Month: MAX(#REF!,1)

Sheet Cover Page
N3: =+Dashboard!$E$10 -> […]
N4: =+Dashboard!$E$12&", "&Dashboard!$E$13 -> […], […]
N6: =TODAY() -> 46065

Sheet Dashboard
C3: Model Dashboard
C5: Assumptions
C7: Transaction Summary | G7: Sources & Uses | L7: Operating Assumptions | Y7: Returns Summary
C9: Transaction Overview | G9: Sources | I9: $ | J9: % | L9: Broader Model General Assumptions | R9: Utility Expenses | U9: Cost / Unit | V9: Year 1 Cost | Y9: Return Summary (Gross)
C10: Investment Name | E10: […] | G10: Total Debt | I10: =+D49 -> 2795000 | J10: =+I10/$I$12 -> 0.60524036 | L10: Vacancy | P10: 0.05 | R10: Electric | U10: =+V10/$E$16 -> 0 | Y10: Scenario 1
C11: Address | E11: […] | G11: Total Equity | I11: =+I12-I10 -> 1823000 | J11: =+I11/$I$12 -> 0.39475964 | L11: Rent Increase | P11: 0.03 | R11: Electric - Vacant | U11: =+V11/$E$16 -> 0 | AA11: Unlevered | AB11: Levered
C12: City | E12: […] | G12: Total Sources | I12: =+I17 -> 4618000 | J12: =SUM(J10:J11) -> 1 | L12: Utility Expense | P12: 0.03 | R12: Water & Sewer | U12: =+V12/$E$16 -> 0 | Y12: IRR | AA12: =+'Scenario 1'!$E$122 -> 0.11402295 | AB12: =+'Scenario 1'!$E$134 -> 0.13796015
C13: State | E13: […] | L13: Move Outs Per Year | P13: =+O13/E16 -> 0 | R13: Gas | U13: =+V13/$E$16 -> 0 | Y13: MOIC | AA13: =+'Scenario 1'!$E$123 -> 1.6264055 | AB13: =+'Scenario 1'!$E$135 -> 1.80481
C14: Zipcode | E14: […] | G14: Uses | I14: $ | J14: % | L14: Other Income | P14: 0.025 | R14: Cable | U14: =+V14/$E$16 -> 0 | Y14: Profit ($m) | AA14: =+('Scenario 1'!$J$119+'Scenario 1'!$E$119)/1000000 -> 1.4685247 | AB14: =+('Scenario 1'!$J$131+'Scenario 1'!$E$131)/1000000 -> 0.96884966
C15: Property Type | E15: […] | G15: Purchase Price | I15: =+E32 -> 4300000 | J15: =+I15/$I$17 -> 0.93113902 | L15: Inflation Increase | P15: 0.03 | R15: Trash/Garbage | U15: =+V15/$E$16 -> 0
C16: Units | E16: 72 | G16: Closing and Financing Costs | I16: =+SUM(E34:E40) -> 318000 | J16: =+I16/$I$17 -> 0.068860979 | L16: Insurance Increase | P16: 0.2 | Y16: Return Summary (Gross)
C17: Buildings | E17: […] | G17: Total Uses | I17: =SUM(I15:I16) -> 4618000 | J17: =SUM(J15:J16) -> 1 | Y17: Scenario 2
C18: Year Built | E18: […] | AA18: Unlevered | AB18: Levered
C19: Initial TCCP End Date | E19: […] | G19: Deal Scenario Summary and Stats | L19: Admin Expenses | N19: Growth Rate | O19: Cost / Unit | P19: Yr. 1 Cost | R19: Operating & Maint. | U19: Cost / Unit | V19: Year 1 Cost | Y19: IRR | AA19: =+'Scenario 2'!$E$122 -> 0.1500536 | AB19: =+'Scenario 2'!$E$134 -> 0.21238056
C20: Final Year of LIHTC Restrictions | E20: […] | G20: Unit Occupancy Statistics | I20: # of Units | J20: % | L20: Bad Debt Expense | N20: 0.015 | O20: =+P20/E16 -> 0 | R20: In-House R&M (per unit) | U20: 0 | V20: =+U20*E16 -> 0 | Y20: MOIC | AA20: =+'Scenario 2'!$E$123 -> 1.8714613 | AB20: =+'Scenario 2'!$E$135 -> 2.3828351
C21: Total Rentable SF | E21: =+'Rent Roll'!N4 -> 59002 | G21: Occupied Units | I21: ='Rent Roll'!C4 -> 68 | J21: =+J23-J22 -> 0.94444444 | L21: Replacement Reserves (cost per unit) | N21: 0 | O21: 300 | P21: =+O21*E16 -> 21600 | R21: Turnover (assumed cost per move out) | U21: 700 | V21: =+U21*O13 -> 0 | Y21: Profit ($m) | AA21: =+('Scenario 2'!$J$119+'Scenario 2'!$E$119)/1000000 -> 2.3369282 | AB21: =+('Scenario 2'!$J$131+'Scenario 2'!$E$131)/1000000 -> 1.8372532
C22: SF / Unit | E22: =+E21/E16 -> 819.47222 | G22: Vacant Units | I22: ='Rent Roll'!C5 -> 4 | J22: =I22/I23 -> 0.055555556 | L22: Compliance Fee | N22: 0 | O22: 0 | P22: 0 | R22: Supplies | U22: =+V22/$E$16 -> 180 | V22: =+(V23*P13)+(V24*E16)*V25 -> 12960
C23: Total Cost / SF | E23: =+I17/E21 -> 78.268533 | G23: Total Units | I23: =+E16 -> 72 | J23: =+I23/$I$23 -> 1 | L23: COVID Late fee (years 1-2) | P23: 0 | R23: Turnover Supplies / Year | V23: 3600 | Y23: Return Summary (Gross)
C24: Total Cost / Unit | E24: =+E22*E23 -> 64138.889 | R24: Supplies / Unit / Year | V24: 150 | Y24: Scenario 3
C25: TTM Occupancy (insert month / year) | E25: […] | G25: ='Rent Roll'!$J$3 -> AMI / S8 Breakdown | I25: # of Units | J25: % | L25: Employee Work Schedule Assumptions | R25: Supplies Overage Multiplier | V25: 1.2 | AA25: Unlevered | AB25: Levered
C26: TTM NOI (insert month / year) | E26: […] | G26: ='Rent Roll'!J4 -> 40% AMI | I26: ='Rent Roll'!K4 -> 2 | J26: =+I26/$I$31 -> 0.027777778 | L26: Hours per Week | P26: 40 | R26: Appliance/Electrical | U26: 175 | V26: =+(E16/6)*U26 -> 2100 | Y26: IRR | AA26: =+'Scenario 3'!$E$122 -> 0.16185258 | AB26: =+'Scenario 3'!$E$134 -> 0.23548185
G27: ='Rent Roll'!J5 -> 50% AMI | I27: ='Rent Roll'!K5 -> 9 | J27: =+I27/$I$31 -> 0.125 | L27: Weeks per Year | P27: 52 | R27: HVAC & Plumbing | U27: =+V27/$E$16 -> 0 | V27: 0 | Y27: MOIC | AA27: =+'Scenario 3'!$E$123 -> 1.9569722 | AB27: =+'Scenario 3'!$E$135 -> 2.5845341
C28: Transaction Assumptions and Statistics | E28: Total Cost | G28: ='Rent Roll'!J6 -> 60% AMI | I28: ='Rent Roll'!K6 -> 27 | J28: =+I28/$I$31 -> 0.375 | R28: Rent Concessions | U28: 0 | V28: =+U28*$E$16 -> 0 | Y28: Profit ($m) | AA28: =+('Scenario 3'!$J$119+'Scenario 3'!$E$119)/1000000 -> 2.6399532 | AB28: =+('Scenario 3'!$J$131+'Scenario 3'!$E$131)/1000000 -> 2.1402782
C29: Asking Price | E29: 4300000 | G29: ='Rent Roll'!J7 -> Market | I29: ='Rent Roll'!K7 -> 2 | J29: =+I29/$I$31 -> 0.027777778
C30: Asking Cap Rate (Year 0) | E30: =+'Scenario 0'!E89/Dashboard!E29 -> 0.35488651 | G30: ='Rent Roll'!J8 -> S8 Voucher | I30: ='Rent Roll'!K8 -> 32 | J30: =+I30/$I$31 -> 0.44444444 | L30: Employee Work Schedule Expenses | M30: Include? | N30: Hourly | O30: Monthly | P30: Yearly | R30: Contract Expenses | V30: Total $
C31: Cost Per Unit (Asking Price) | E31: =+E29/E16 -> 59722.222 | G31: Total Units | I31: =SUM(I26:I30) -> 72 | J31: =SUM(J26:J30) -> 1 | L31: Regional Manager Salary | M31: Yes | N31: =+P31/P26/P27 -> 6.9230769 | O31: 1200 | P31: =++IF(M31="Yes",O31*12,0) -> 14400 | R31: Landscaping/Grounds Contract
C32: Purchase Price | E32: =E29 -> 4300000 | L32: Property Manager Salary | M32: Yes | N32: 27 | O32: =+P32/12 -> 4680 | P32: =+IF(M32="Yes",N32*$P$26*$P$27,0) -> 56160 | R32: Fire & Safety System
C33: Cost Per Unit (Purchase Price) | E33: =+E32/$E$16 -> 59722.222 | G33: ='Rent Roll'!$F$3 -> Unit Types | I33: # of Units | J33: % | L33: Assistant Property Manager Salary | M33: No | N33: 20 | O33: =+P33/12 -> 0 | P33: =+IF(M33="Yes",N33*$P$26*$P$27,0) -> 0 | R33: Security
C34: Closing Costs | D34: 0.02 | E34: =+$D$34*$E$32 -> 86000 | G34: ='Rent Roll'!F4 -> 1x1 | I34: ='Rent Roll'!G4 -> 6 | J34: =+I34/$I$31 -> 0.083333333 | L34: Commissions / Bonuses | M34: No | N34: 0 | O34: =+P34/12 -> 0 | P34: =+IF(M34="Yes",N34*$P$26*$P$27,0) -> 0 | R34: Pest Control
C35: Broker Fees | D35: 0 | E35: =+E32*D35 -> 0 | G35: ='Rent Roll'!F5 -> 2x1.5 | I35: ='Rent Roll'!G5 -> 6 | J35: =+I35/$I$31 -> 0.083333333 | L35: Maintenance Salary | M35: Yes | N35: 27 | O35: =+P35/12 -> 4680 | P35: =+IF(M35="Yes",N35*$P$26*$P$27,0) -> 56160 | R35: Misc. Contracts
C36: Rehabilitation Costs | D36: 1000 | E36: =+D36*E16 -> 72000 | G36: ='Rent Roll'!F6 -> 2x2 | I36: ='Rent Roll'!G6 -> 3 | J36: =+I36/$I$31 -> 0.041666667 | L36: Maintenance Assistant Salary | M36: No | N36: 0 | O36: =+P36/12 -> 0 | P36: =+IF(M36="Yes",N36*$P$26*$P$27,0) -> 0 | R36: Elevator Costs
C37: Legal Fees | E37: 35000 | G37: ='Rent Roll'!F7 -> 2x2 (TH) | I37: ='Rent Roll'!G7 -> 19 | J37: =+I37/$I$31 -> 0.26388889 | L37: Labor Increase % | N37: 0.03 | R37: Snow
C38: Developer Fees | E38: 100000 | G38: ='Rent Roll'!F8 -> 2x1.5-2x2 | I38: ='Rent Roll'!G8 -> 18 | J38: =+I38/$I$31 -> 0.25 | R38: Misc. Operating & Maint.
C39: Due Diligence Fees | E39: 25000 | G39: ='Rent Roll'!F9 -> 3x2 (TH) | I39: ='Rent Roll'!G9 -> 20 | J39: =+I39/$I$31 -> 0.27777778
C40: Taxes / Title Insurance | E40: 0 | G40: Total Units | I40: =SUM(I34:I39) -> 72 | J40: =SUM(J34:J39) -> 1 | L40: Admin Expenses | O40: Cost / Unit | P40: Yr. 1 Cost | R40: Real Estate Taxes and Insurance | V40: Total $
L41: Management Fee (% of Net Rental Income) | P41: 0.05 | R41: Market Value | V41: =+E32*U41 -> 0
C42: GP / LP Initial Equity Investment | G42: Additional Unit Statistics | L42: Legal Expense | O42: =+P42/$E$16 -> 83.333333 | P42: 6000 | R42: Less: Taxable Value | V42: =+V41*U42 -> 0
C43: GP Equity Investment | D43: 0.1 | E43: =+(I17-I10)*D43 -> 182300 | G43: Average Gross Rent | J43: ='Rent Roll'!O4 -> 775.11111 | L43: Office Expense (Per Unit) | O43: 150 | P43: =+O43*$E$16 -> 10800 | R43: RE Taxes | T43: Prop. Tax Rate (Milage) -> | V43: =+V42*U43/10 -> 0
C44: LP Equity Investment | D44: =1-D43 -> 0.9 | E44: =+(I17-I10)*D44 -> 1640700 | G44: Average Effective Rent | J44: ='Rent Roll'!P4 -> 687.125 | L44: Travel Cost | O44: =+P44/$E$16 -> 83.333333 | P44: 6000 | R44: Stormwater Fees
G45: % of Gross Rent | J45: =+J44/J43 -> 0.88648581 | L45: Audit Expense | O45: =+P45/$E$16 -> 90.277778 | P45: 6500 | R45: Less Discounts | V45: =+V43*U45 -> 0
C46: Financing Assumptions | L46: Advertising | O46: =+P46/$E$16 -> 0 | P46: 0 | R46: Total RE Taxes | U46: =+U43 -> 0 | V46: =+V43+V44-V45 -> 0
C47: Lender | E47: TBD | G47: Timeline and Exit Assumptions | L47: Training Charge | O47: =+P47/$E$16 -> 0 | P47: 0
C48: Loan to Value (w/ out addt'l costs) | E48: =+D49/I17 -> 0.60524036 | G48: Timeline Assumptions | L48: Bank Charges | O48: =+P48/$E$16 -> 0 | P48: 0 | R48: Property & Liability Insurance | U48: 450 | V48: =+U48*E16 -> 32400
C49: Loan to Value (w/ addt'l costs) | D49: =+E49*E32 -> 2795000 | E49: 0.65 | G49: Entry Date | J49: 44408 | L49: Bookkeeping | O49: =+P49/$E$16 -> 27.777778 | P49: 2000 | R49: Workmens Comp | U49: 0.02 | V49: =+SUM($P$32:$P$33,$P$35)*U49 -> 2246.4
C50: Interest Rate | E50: 0.065 | G50: Investment Period | J50: 60 | L50: Payroll Service | O50: =+P50/$E$16 -> 0 | P50: 0 | R50: Health Insurance & Other Benefits | U50: 0.03 | V50: =+SUM($P$32:$P$33,$P$35)*U50 -> 3369.6
C51: Loan Constant | E51: =E50/(1-(1/((1+(E50/12))^(30*12)))) -> 0.075848163 | G51: Exit Date | J51: =+EOMONTH(J49,J50) -> 46234 | L51: Manager Unit | O51: =+P51/$E$16 -> 0 | P51: 0 | R51: Payroll Tax | U51: 0.1 | V51: =+SUM($P$32:$P$33,$P$35)*U51 -> 11232
C52: Fully Amort / Yr | E52: =+E51*I10 -> 211995.62 | L52: Misc. Admin Expenses | O52: =+P52/$E$16 -> 0 | P52: 0 | R52: Misc Taxes, Licenses, Etc.
C53: Interest Only Loan Pmt | E53: =+$I$10*$E$50 -> 181675 | G53: Exit Assumptions
C54: Principal Portion | E54: =+E52-E53 -> 30320.615 | G54: Cap Rate at Exit | J54: 0.06
C55: Loan Term | E55: 30 | G55: Broker Commission | J55: 0.015
C56: Interest Only Period | E56: 8
C57: DSCR Check | D57: >1.25x? --> | E57: =+'Scenario 0'!$F$81/Dashboard!E52 -> 1.3767482 | G57: GP / LP Split
G58: GP Proceeds | J58: 0.25
G59: LP Proceeds | J59: =1-J58 -> 0.75

Sheet Models -->

Sheet Scenario 0
C1: Underwriting Model Scenario 0
D3: Year | E3: 2024 | F3: =+E3+1 -> 2025 | G3: =+F3+1 -> 2026 | H3: =+G3+1 -> 2027 | I3: =+H3+1 -> 2028 | J3: =+I3+1 -> 2029 | K3: =+J3+1 -> 2030 | L3: =+K3+1 -> 2031 | M3: =+L3+1 -> 2032 | ... O3: =+N3+1 -> 2034
C4: Scenario 0 (No Change to Asset)
C6: Income Statement | E6: T12 | F6: 1 | G6: =+F6+1 -> 2 | H6: =+G6+1 -> 3 | I6: =+H6+1 -> 4 | J6: =+I6+1 -> 5 | K6: =+J6+1 -> 6 | L6: =+K6+1 -> 7 | M6: =+L6+1 -> 8 | N6: =+M6+1 -> 9 | O6: =+N6+1 -> 10
A7: GPI | C7: Gross Potential Income | E7: =1561954 -> 1561954 | F7: ='Unit Mix'!N26 -> 593676 | G7: ='Unit Mix'!N49 -> 611486.28 | H7: ='Unit Mix'!N72 -> 629830.87 | I7: ='Unit Mix'!N95 -> 648725.79 | J7: =+'Unit Mix'!N118 -> 668187.57 | K7: =+'Unit Mix'!N141 -> 688233.2 | L7: =+'Unit Mix'!N164 -> 708880.19 | M7: =+'Unit Mix'!N187 -> 730146.6 | N7: =+'Unit Mix'!N210 -> 752050.99 | O7: ='Unit Mix'!N233 -> 774612.52
A8: VC | C8: Vacancy Factor | D8: =+Dashboard!$P$10 -> 0.05 | E8: 48058 | F8: =+F7*$D$8 -> 29683.8 | G8: =+G7*$D$8 -> 30574.314 | H8: =+H7*$D$8 -> 31491.543 | I8: =+I7*$D$8 -> 32436.29 | J8: =+J7*$D$8 -> 33409.378 | K8: =+K7*$D$8 -> 34411.66 | L8: =+L7*$D$8 -> 35444.01 | M8: =+M7*$D$8 -> 36507.33 | ... O8: =+O7*$D$8 -> 38730.626
C9: Net Rental Income | E9: =+E7-E8 -> 1513896 | F9: =+F7-F8 -> 563992.2 | G9: =+G7-G8 -> 580911.97 | H9: =+H7-H8 -> 598339.32 | I9: =+I7-I8 -> 616289.5 | J9: =+J7-J8 -> 634778.19 | K9: =+K7-K8 -> 653821.54 | L9: =+L7-L8 -> 673436.18 | ... O9: =+O7-O8 -> 735881.9
A11: OI | C11: Laundry and Other Income | D11: =+Dashboard!$P$14 -> 0.025 | E11: 33716 | F11: =+Dashboard!$O$14 -> 0 | G11: =+F11*(1+$D11) -> 0 | H11: =+G11*(1+$D11) -> 0 | I11: =+H11*(1+$D11) -> 0 | J11: =+I11*(1+$D11) -> 0 | K11: =+J11*(1+$D11) -> 0 | L11: =+K11*(1+$D11) -> 0 | M11: =+L11*(1+$D11) -> 0 | N11: =+M11*(1+$D11) -> 0 | O11: =+N11*(1+$D11) -> 0
C12: Total Gross Income | E12: =+SUM(E9:E11) -> 1547612 | F12: =+SUM(F9:F11) -> 563992.2 | G12: =+SUM(G9:G11) -> 580911.97 | H12: =+SUM(H9:H11) -> 598339.32 | I12: =+SUM(I9:I11) -> 616289.5 | J12: =+SUM(J9:J11) -> 634778.19 | K12: =+SUM(K9:K11) -> 653821.54 | L12: =+SUM(L9:L11) -> 673436.18 | ... O12: =+SUM(O9:O11) -> 735881.9
C13: Gross Income Growth | E13: -- | F13: =+F12/E12-1 -> -0.63557261 | G13: =+G12/F12-1 -> 0.03 | H13: =+H12/G12-1 -> 0.03 | I13: =+I12/H12-1 -> 0.03 | J13: =+J12/I12-1 -> 0.03 | K13: =+K12/J12-1 -> 0.03 | L13: =+L12/K12-1 -> 0.03 | M13: =+M12/L12-1 -> 0.03 | ... O13: =+O12/N12-1 -> 0.03
C15: Opertating Expenses
A17: BAD | C17: Bad Debt | D17: =+Dashboard!$N$20 -> 0.015 | F17: =+Dashboard!P20 -> 0 | G17: =+F17*(1+$D17) -> 0 | H17: =+G17*(1+$D17) -> 0 | I17: =+H17*(1+$D17) -> 0 | J17: =+I17*(1+$D17) -> 0 | K17: =+J17*(1+$D17) -> 0 | L17: =+K17*(1+$D17) -> 0 | M17: =+L17*(1+$D17) -> 0 | N17: =+M17*(1+$D17) -> 0 | O17: =+N17*(1+$D17) -> 0
C18: Bad Debt | E18: =+SUM(E17) -> 0 | F18: =+SUM(F17) -> 0 | G18: =+SUM(G17) -> 0 | H18: =+SUM(H17) -> 0 | I18: =+SUM(I17) -> 0 | J18: =+SUM(J17) -> 0 | K18: =+SUM(K17) -> 0 | L18: =+SUM(L17) -> 0 | ... O18: =+SUM(O17) -> 0
A20: RES | C20: Replacement Reserves | D20: =+Dashboard!$N$21 -> 0 | E20: =+F20 -> 21600 | F20: =+Dashboard!P21 -> 21600 | G20: =+F20*(1+$D20) -> 21600 | H20: =+G20*(1+$D20) -> 21600 | I20: =+H20*(1+$D20) -> 21600 | J20: =+I20*(1+$D20) -> 21600 | K20: =+J20*(1+$D20) -> 21600 | L20: =+K20*(1+$D20) -> 21600 | M20: =+L20*(1+$D20) -> 21600 | N20: =+M20*(1+$D20) -> 21600 | O20: =+N20*(1+$D20) -> 21600
A21: COM | C21: Compliance Fee | D21: =+Dashboard!$N$22 -> 0 | E21: 0 | F21: =+Dashboard!P22 -> 0 | G21: =+F21*(1+$D21) -> 0 | H21: =+G21*(1+$D21) -> 0 | I21: =+H21*(1+$D21) -> 0 | J21: =+I21*(1+$D21) -> 0 | K21: =+J21*(1+$D21) -> 0 | L21: =+K21*(1+$D21) -> 0 | M21: =+L21*(1+$D21) -> 0 | N21: =+M21*(1+$D21) -> 0 | O21: =+N21*(1+$D21) -> 0
C22: Total Replacement Reserves | E22: =SUM(E20:E21) -> 21600 | F22: =SUM(F20:F21) -> 21600 | G22: =SUM(G20:G21) -> 21600 | H22: =SUM(H20:H21) -> 21600 | I22: =SUM(I20:I21) -> 21600 | J22: =SUM(J20:J21) -> 21600 | K22: =SUM(K20:K21) -> 21600 | L22: =SUM(L20:L21) -> 21600 | ... O22: =SUM(O20:O21) -> 21600
A24: REG | C24: Regional Manager Salary | D24: =+Dashboard!$N$37 -> 0.03 | F24: =+Dashboard!P31 -> 14400 | G24: =+F24*(1+$D24) -> 14832 | H24: =+G24*(1+$D24) -> 15276.96 | I24: =+H24*(1+$D24) -> 15735.269 | J24: =+I24*(1+$D24) -> 16207.327 | K24: =+J24*(1+$D24) -> 16693.547 | L24: =+K24*(1+$D24) -> 17194.353 | M24: =+L24*(1+$D24) -> 17710.184 | N24: =+M24*(1+$D24) -> 18241.489 | O24: =+N24*(1+$D24) -> 18788.734
A25: MAN | C25: Property Manager Salary | D25: =+Dashboard!$N$37 -> 0.03 | F25: =+Dashboard!P32 -> 56160 | G25: =+F25*(1+$D25) -> 57844.8 | H25: =+G25*(1+$D25) -> 59580.144 | I25: =+H25*(1+$D25) -> 61367.548 | J25: =+I25*(1+$D25) -> 63208.575 | K25: =+J25*(1+$D25) -> 65104.832 | L25: =+K25*(1+$D25) -> 67057.977 | M25: =+L25*(1+$D25) -> 69069.716 | N25: =+M25*(1+$D25) -> 71141.808 | O25: =+N25*(1+$D25) -> 73276.062
A26: ASS | C26: Assistant Manager (over 160 units) | D26: =+Dashboard!$N$37 -> 0.03 | F26: =+Dashboard!P33 -> 0 | G26: =+F26*(1+$D26) -> 0 | H26: =+G26*(1+$D26) -> 0 | I26: =+H26*(1+$D26) -> 0 | J26: =+I26*(1+$D26) -> 0 | K26: =+J26*(1+$D26) -> 0 | L26: =+K26*(1+$D26) -> 0 | M26: =+L26*(1+$D26) -> 0 | N26: =+M26*(1+$D26) -> 0 | O26: =+N26*(1+$D26) -> 0
A27: PAY | C27: Commissions/Bonuses | D27: =+Dashboard!$N$37 -> 0.03 | F27: =+Dashboard!P34 -> 0 | G27: =+F27*(1+$D27) -> 0 | H27: =+G27*(1+$D27) -> 0 | I27: =+H27*(1+$D27) -> 0 | J27: =+I27*(1+$D27) -> 0 | K27: =+J27*(1+$D27) -> 0 | L27: =+K27*(1+$D27) -> 0 | M27: =+L27*(1+$D27) -> 0 | N27: =+M27*(1+$D27) -> 0 | O27: =+N27*(1+$D27) -> 0
A28: MAIT | C28: Maintenance Salary | D28: =+Dashboard!$N$37 -> 0.03 | F28: =+Dashboard!P35+Dashboard!P36 -> 56160 | G28: =+F28*(1+$D28) -> 57844.8 | H28: =+G28*(1+$D28) -> 59580.144 | I28: =+H28*(1+$D28) -> 61367.548 | J28: =+I28*(1+$D28) -> 63208.575 | K28: =+J28*(1+$D28) -> 65104.832 | L28: =+K28*(1+$D28) -> 67057.977 | M28: =+L28*(1+$D28) -> 69069.716 | N28: =+M28*(1+$D28) -> 71141.808 | O28: =+N28*(1+$D28) -> 73276.062
C29: Payroll | E29: =SUM(E24:E28) -> 0 | F29: =SUM(F24:F28) -> 126720 | G29: =SUM(G24:G28) -> 130521.6 | H29: =SUM(H24:H28) -> 134437.25 | I29: =SUM(I24:I28) -> 138470.37 | J29: =SUM(J24:J28) -> 142624.48 | K29: =SUM(K24:K28) -> 146903.21 | L29: =SUM(L24:L28) -> 151310.31 | ... O29: =SUM(O24:O28) -> 165340.86
A31: MGMT | C31: Management Fee | D31: =+Dashboard!$P$41 -> 0.05 | F31: =+F9*$D$31 -> 28199.61 | G31: =+G9*$D$31 -> 29045.598 | H31: =+H9*$D$31 -> 29916.966 | I31: =+I9*$D$31 -> 30814.475 | J31: =+J9*$D$31 -> 31738.909 | K31: =+K9*$D$31 -> 32691.077 | L31: =+L9*$D$31 -> 33671.809 | M31: =+M9*$D$31 -> 34681.963 | ... O31: =+O9*$D$31 -> 36794.095
A32: LEGAL | C32: Legal Expense | D32: =+Dashboard!$P$15 -> 0.03 | F32: =Dashboard!P42 -> 6000 | G32: =+F32*(1+$D32) -> 6180 | H32: =+G32*(1+$D32) -> 6365.4 | I32: =+H32*(1+$D32) -> 6556.362 | J32: =+I32*(1+$D32) -> 6753.0529 | K32: =+J32*(1+$D32) -> 6955.6444 | L32: =+K32*(1+$D32) -> 7164.3138 | M32: =+L32*(1+$D32) -> 7379.2432 | N32: =+M32*(1+$D32) -> 7600.6205 | O32: =+N32*(1+$D32) -> 7828.6391
A33: OFF | C33: Office Expense | D33: =+Dashboard!$P$15 -> 0.03 | F33: =Dashboard!P43 -> 10800 | G33: =+F33*(1+$D33) -> 11124 | H33: =+G33*(1+$D33) -> 11457.72 | I33: =+H33*(1+$D33) -> 11801.452 | J33: =+I33*(1+$D33) -> 12155.495 | K33: =+J33*(1+$D33) -> 12520.16 | L33: =+K33*(1+$D33) -> 12895.765 | M33: =+L33*(1+$D33) -> 13282.638 | N33: =+M33*(1+$D33) -> 13681.117 | O33: =+N33*(1+$D33) -> 14091.55
A34: TRAVEL | C34: Travel Cost | D34: =+Dashboard!$P$15 -> 0.03 | F34: =Dashboard!P44 -> 6000 | G34: =+F34*(1+$D34) -> 6180 | H34: =+G34*(1+$D34) -> 6365.4 | I34: =+H34*(1+$D34) -> 6556.362 | J34: =+I34*(1+$D34) -> 6753.0529 | K34: =+J34*(1+$D34) -> 6955.6444 | L34: =+K34*(1+$D34) -> 7164.3138 | M34: =+L34*(1+$D34) -> 7379.2432 | N34: =+M34*(1+$D34) -> 7600.6205 | O34: =+N34*(1+$D34) -> 7828.6391
A35: AUD | C35: Audit Expense | D35: =+Dashboard!$P$15 -> 0.03 | F35: =Dashboard!P45 -> 6500 | G35: =+F35*(1+$D35) -> 6695 | H35: =+G35*(1+$D35) -> 6895.85 | I35: =+H35*(1+$D35) -> 7102.7255 | J35: =+I35*(1+$D35) -> 7315.8073 | K35: =+J35*(1+$D35) -> 7535.2815 | L35: =+K35*(1+$D35) -> 7761.3399 | M35: =+L35*(1+$D35) -> 7994.1801 | N35: =+M35*(1+$D35) -> 8234.0055 | O35: =+N35*(1+$D35) -> 8481.0257
A36: ADV | C36: Advertising | D36: =+Dashboard!$P$15 -> 0.03 | F36: =Dashboard!P46 -> 0 | G36: =+F36*(1+$D36) -> 0 | H36: =+G36*(1+$D36) -> 0 | I36: =+H36*(1+$D36) -> 0 | J36: =+I36*(1+$D36) -> 0 | K36: =+J36*(1+$D36) -> 0 | L36: =+K36*(1+$D36) -> 0 | M36: =+L36*(1+$D36) -> 0 | N36: =+M36*(1+$D36) -> 0 | O36: =+N36*(1+$D36) -> 0
A37: TRAIN | C37: Training Charge | D37: =+Dashboard!$P$15 -> 0.03 | F37: =Dashboard!P47 -> 0 | G37: =+F37*(1+$D37) -> 0 | H37: =+G37*(1+$D37) -> 0 | I37: =+H37*(1+$D37) -> 0 | J37: =+I37*(1+$D37) -> 0 | K37: =+J37*(1+$D37) -> 0 | L37: =+K37*(1+$D37) -> 0 | M37: =+L37*(1+$D37) -> 0 | N37: =+M37*(1+$D37) -> 0 | O37: =+N37*(1+$D37) -> 0
A38: BANK | C38: Bank Charges | D38: =+Dashboard!$P$15 -> 0.03 | F38: =Dashboard!P48 -> 0 | G38: =+F38*(1+$D38) -> 0 | H38: =+G38*(1+$D38) -> 0 | I38: =+H38*(1+$D38) -> 0 | J38: =+I38*(1+$D38) -> 0 | K38: =+J38*(1+$D38) -> 0 | L38: =+K38*(1+$D38) -> 0 | M38: =+L38*(1+$D38) -> 0 | N38: =+M38*(1+$D38) -> 0 | O38: =+N38*(1+$D38) -> 0
A39: BOOK | C39: Bookkeeping | D39: =+Dashboard!$P$15 -> 0.03 | F39: =Dashboard!P49 -> 2000 | G39: =+F39*(1+$D39) -> 2060 | H39: =+G39*(1+$D39) -> 2121.8 | I39: =+H39*(1+$D39) -> 2185.454 | J39: =+I39*(1+$D39) -> 2251.0176 | K39: =+J39*(1+$D39) -> 2318.5481 | L39: =+K39*(1+$D39) -> 2388.1046 | M39: =+L39*(1+$D39) -> 2459.7477 | N39: =+M39*(1+$D39) -> 2533.5402 | O39: =+N39*(1+$D39) -> 2609.5464
A40: PAYSERV | C40: Payroll Service | D40: =+Dashboard!$P$15 -> 0.03 | F40: =Dashboard!P50 -> 0 | G40: =+F40*(1+$D40) -> 0 | H40: =+G40*(1+$D40) -> 0 | I40: =+H40*(1+$D40) -> 0 | J40: =+I40*(1+$D40) -> 0 | K40: =+J40*(1+$D40) -> 0 | L40: =+K40*(1+$D40) -> 0 | M40: =+L40*(1+$D40) -> 0 | N40: =+M40*(1+$D40) -> 0 | O40: =+N40*(1+$D40) -> 0
A41: UNIT | C41: Manager Unit | D41: =+Dashboard!$P$15 -> 0.03 | F41: =Dashboard!P51 -> 0 | G41: =+F41*(1+$D41) -> 0 | H41: =+G41*(1+$D41) -> 0 | I41: =+H41*(1+$D41) -> 0 | J41: =+I41*(1+$D41) -> 0 | K41: =+J41*(1+$D41) -> 0 | L41: =+K41*(1+$D41) -> 0 | M41: =+L41*(1+$D41) -> 0 | N41: =+M41*(1+$D41) -> 0 | O41: =+N41*(1+$D41) -> 0
A42: MISCAD | C42: Misc. Admin Expenses | D42: =+Dashboard!$P$15 -> 0.03 | E42: 0 | F42: =Dashboard!P52 -> 0 | G42: =+F42*(1+$D42) -> 0 | H42: =+G42*(1+$D42) -> 0 | I42: =+H42*(1+$D42) -> 0 | J42: =+I42*(1+$D42) -> 0 | K42: =+J42*(1+$D42) -> 0 | L42: =+K42*(1+$D42) -> 0 | M42: =+L42*(1+$D42) -> 0 | N42: =+M42*(1+$D42) -> 0 | O42: =+N42*(1+$D42) -> 0
C43: Admin Expenses | E43: =SUM(E31:E42) -> 0 | F43: =SUM(F31:F42) -> 59499.61 | G43: =SUM(G31:G42) -> 61284.598 | H43: =SUM(H31:H42) -> 63123.136 | I43: =SUM(I31:I42) -> 65016.83 | J43: =SUM(J31:J42) -> 66967.335 | K43: =SUM(K31:K42) -> 68976.355 | L43: =SUM(L31:L42) -> 71045.646 | ... O43: =SUM(O31:O42) -> 77633.496
A45: ELEC | C45: Electric | D45: =+Dashboard!$P$15 -> 0.03 | F45: =+Dashboard!V10 -> 0 | G45: =+F45*(1+$D45) -> 0 | H45: =+G45*(1+$D45) -> 0 | I45: =+H45*(1+$D45) -> 0 | J45: =+I45*(1+$D45) -> 0 | K45: =+J45*(1+$D45) -> 0 | L45: =+K45*(1+$D45) -> 0 | M45: =+L45*(1+$D45) -> 0 | N45: =+M45*(1+$D45) -> 0 | O45: =+N45*(1+$D45) -> 0
A46: VAC | C46: Electric - Vacant | D46: =+Dashboard!$P$15 -> 0.03 | F46: =+Dashboard!V11 -> 0 | G46: =+F46*(1+$D46) -> 0 | H46: =+G46*(1+$D46) -> 0 | I46: =+H46*(1+$D46) -> 0 | J46: =+I46*(1+$D46) -> 0 | K46: =+J46*(1+$D46) -> 0 | L46: =+K46*(1+$D46) -> 0 | M46: =+L46*(1+$D46) -> 0 | N46: =+M46*(1+$D46) -> 0 | O46: =+N46*(1+$D46) -> 0
A47: WS | C47: Water & Sewer | D47: =+Dashboard!$P$15 -> 0.03 | F47: =+Dashboard!V12 -> 0 | G47: =+F47*(1+$D47) -> 0 | H47: =+G47*(1+$D47) -> 0 | I47: =+H47*(1+$D47) -> 0 | J47: =+I47*(1+$D47) -> 0 | K47: =+J47*(1+$D47) -> 0 | L47: =+K47*(1+$D47) -> 0 | M47: =+L47*(1+$D47) -> 0 | N47: =+M47*(1+$D47) -> 0 | O47: =+N47*(1+$D47) -> 0
A48: GAS | C48: Gas | D48: =+Dashboard!$P$15 -> 0.03 | F48: =+Dashboard!V13 -> 0 | G48: =+F48*(1+$D48) -> 0 | H48: =+G48*(1+$D48) -> 0 | I48: =+H48*(1+$D48) -> 0 | J48: =+I48*(1+$D48) -> 0 | K48: =+J48*(1+$D48) -> 0 | L48: =+K48*(1+$D48) -> 0 | M48: =+L48*(1+$D48) -> 0 | N48: =+M48*(1+$D48) -> 0 | O48: =+N48*(1+$D48) -> 0
A49: CABLE | C49: Cable | D49: =+Dashboard!$P$15 -> 0.03 | F49: =+Dashboard!V14 -> 0 | G49: =+F49*(1+$D49) -> 0 | H49: =+G49*(1+$D49) -> 0 | I49: =+H49*(1+$D49) -> 0 | J49: =+I49*(1+$D49) -> 0 | K49: =+J49*(1+$D49) -> 0 | L49: =+K49*(1+$D49) -> 0 | M49: =+L49*(1+$D49) -> 0 | N49: =+M49*(1+$D49) -> 0 | O49: =+N49*(1+$D49) -> 0
A50: TRASH | C50: Trash/Garbage | D50: =+Dashboard!$P$15 -> 0.03 | F50: =+Dashboard!V15 -> 0 | G50: =+F50*(1+$D50) -> 0 | H50: =+G50*(1+$D50) -> 0 | I50: =+H50*(1+$D50) -> 0 | J50: =+I50*(1+$D50) -> 0 | K50: =+J50*(1+$D50) -> 0 | L50: =+K50*(1+$D50) -> 0 | M50: =+L50*(1+$D50) -> 0 | N50: =+M50*(1+$D50) -> 0 | O50: =+N50*(1+$D50) -> 0
C51: Utility Expenses | E51: =SUM(E45:E50) -> 0 | F51: =SUM(F45:F50) -> 0 | G51: =SUM(G45:G50) -> 0 | H51: =SUM(H45:H50) -> 0 | I51: =SUM(I45:I50) -> 0 | J51: =SUM(J45:J50) -> 0 | K51: =SUM(K45:K50) -> 0 | L51: =SUM(L45:L50) -> 0 | ... O51: =SUM(O45:O50) -> 0
A53: RM | C53: In-House R&M | D53: =+Dashboard!$P$15 -> 0.03 | F53: =+Dashboard!V20 -> 0 | G53: =+F53*(1+$D53) -> 0 | H53: =+G53*(1+$D53) -> 0 | I53: =+H53*(1+$D53) -> 0 | J53: =+I53*(1+$D53) -> 0 | K53: =+J53*(1+$D53) -> 0 | L53: =+K53*(1+$D53) -> 0 | M53: =+L53*(1+$D53) -> 0 | N53: =+M53*(1+$D53) -> 0 | O53: =+N53*(1+$D53) -> 0
A54: TURN | C54: Turnover | D54: =+Dashboard!$P$15 -> 0.03 | F54: =+Dashboard!V21 -> 0 | G54: =+F54*(1+$D54) -> 0 | H54: =+G54*(1+$D54) -> 0 | I54: =+H54*(1+$D54) -> 0 | J54: =+I54*(1+$D54) -> 0 | K54: =+J54*(1+$D54) -> 0 | L54: =+K54*(1+$D54) -> 0 | M54: =+L54*(1+$D54) -> 0 | N54: =+M54*(1+$D54) -> 0 | O54: =+N54*(1+$D54) -> 0
A55: SUPP | C55: Supplies | D55: =+Dashboard!$P$15 -> 0.03 | F55: =+Dashboard!V22 -> 12960 | G55: =+F55*(1+$D55) -> 13348.8 | H55: =+G55*(1+$D55) -> 13749.264 | I55: =+H55*(1+$D55) -> 14161.742 | J55: =+I55*(1+$D55) -> 14586.594 | K55: =+J55*(1+$D55) -> 15024.192 | L55: =+K55*(1+$D55) -> 15474.918 | M55: =+L55*(1+$D55) -> 15939.165 | N55: =+M55*(1+$D55) -> 16417.34 | O55: =+N55*(1+$D55) -> 16909.86
A56: APP | C56: Appliance/Electrical | D56: =+Dashboard!$P$15 -> 0.03 | F56: =+Dashboard!V26 -> 2100 | G56: =+F56*(1+$D56) -> 2163 | H56: =+G56*(1+$D56) -> 2227.89 | I56: =+H56*(1+$D56) -> 2294.7267 | J56: =+I56*(1+$D56) -> 2363.5685 | K56: =+J56*(1+$D56) -> 2434.4756 | L56: =+K56*(1+$D56) -> 2507.5098 | M56: =+L56*(1+$D56) -> 2582.7351 | N56: =+M56*(1+$D56) -> 2660.2172 | O56: =+N56*(1+$D56) -> 2740.0237
A57: HP | C57: HVAC & Plumbing | D57: =+Dashboard!$P$15 -> 0.03 | E57: 0 | F57: =+Dashboard!V27 -> 0 | G57: =+F57*(1+$D57) -> 0 | H57: =+G57*(1+$D57) -> 0 | I57: =+H57*(1+$D57) -> 0 | J57: =+I57*(1+$D57) -> 0 | K57: =+J57*(1+$D57) -> 0 | L57: =+K57*(1+$D57) -> 0 | M57: =+L57*(1+$D57) -> 0 | N57: =+M57*(1+$D57) -> 0 | O57: =+N57*(1+$D57) -> 0
A58: CONC | C58: Rent Concessions | D58: =+Dashboard!$P$15 -> 0.03 | E58: 0 | F58: =+Dashboard!V28 -> 0 | G58: =+F58*(1+$D58) -> 0 | H58: =+G58*(1+$D58) -> 0 | I58: =+H58*(1+$D58) -> 0 | J58: =+I58*(1+$D58) -> 0 | K58: =+J58*(1+$D58) -> 0 | L58: =+K58*(1+$D58) -> 0 | M58: =+L58*(1+$D58) -> 0 | N58: =+M58*(1+$D58) -> 0 | O58: =+N58*(1+$D58) -> 0
C59: Operating and Maint. | E59: =SUM(E53:E58) -> 0 | F59: =SUM(F53:F58) -> 15060 | G59: =SUM(G53:G58) -> 15511.8 | H59: =SUM(H53:H58) -> 15977.154 | I59: =SUM(I53:I58) -> 16456.469 | J59: =SUM(J53:J58) -> 16950.163 | K59: =SUM(K53:K58) -> 17458.668 | L59: =SUM(L53:L58) -> 17982.428 | ... O59: =SUM(O53:O58) -> 19649.884
A61: LAND | C61: Landscaping/Grounds Contract | D61: =+Dashboard!$P$15 -> 0.03 | F61: =+Dashboard!V31 -> 0 | G61: =+F61*(1+$D61) -> 0 | H61: =+G61*(1+$D61) -> 0 | I61: =+H61*(1+$D61) -> 0 | J61: =+I61*(1+$D61) -> 0 | K61: =+J61*(1+$D61) -> 0 | L61: =+K61*(1+$D61) -> 0 | M61: =+L61*(1+$D61) -> 0 | N61: =+M61*(1+$D61) -> 0 | O61: =+N61*(1+$D61) -> 0
A62: FIRE | C62: Fire & Safety System | D62: =+Dashboard!$P$15 -> 0.03 | F62: =+Dashboard!V32 -> 0 | G62: =+F62*(1+$D62) -> 0 | H62: =+G62*(1+$D62) -> 0 | I62: =+H62*(1+$D62) -> 0 | J62: =+I62*(1+$D62) -> 0 | K62: =+J62*(1+$D62) -> 0 | L62: =+K62*(1+$D62) -> 0 | M62: =+L62*(1+$D62) -> 0 | N62: =+M62*(1+$D62) -> 0 | O62: =+N62*(1+$D62) -> 0
A63: SEC | C63: Security | D63: =+Dashboard!$P$15 -> 0.03 | F63: =+Dashboard!V33 -> 0 | G63: =+F63*(1+$D63) -> 0 | H63: =+G63*(1+$D63) -> 0 | I63: =+H63*(1+$D63) -> 0 | J63: =+I63*(1+$D63) -> 0 | K63: =+J63*(1+$D63) -> 0 | L63: =+K63*(1+$D63) -> 0 | M63: =+L63*(1+$D63) -> 0 | N63: =+M63*(1+$D63) -> 0 | O63: =+N63*(1+$D63) -> 0
A64: PEST | C64: Pest Control | D64: =+Dashboard!$P$15 -> 0.03 | F64: =+Dashboard!V34 -> 0 | G64: =+F64*(1+$D64) -> 0 | H64: =+G64*(1+$D64) -> 0 | I64: =+H64*(1+$D64) -> 0 | J64: =+I64*(1+$D64) -> 0 | K64: =+J64*(1+$D64) -> 0 | L64: =+K64*(1+$D64) -> 0 | M64: =+L64*(1+$D64) -> 0 | N64: =+M64*(1+$D64) -> 0 | O64: =+N64*(1+$D64) -> 0
A65: CON | C65: Misc. Contracts | D65: =+Dashboard!$P$15 -> 0.03 | F65: =+Dashboard!V35 -> 0 | G65: =+F65*(1+$D65) -> 0 | H65: =+G65*(1+$D65) -> 0 | I65: =+H65*(1+$D65) -> 0 | J65: =+I65*(1+$D65) -> 0 | K65: =+J65*(1+$D65) -> 0 | L65: =+K65*(1+$D65) -> 0 | M65: =+L65*(1+$D65) -> 0 | N65: =+M65*(1+$D65) -> 0 | O65: =+N65*(1+$D65) -> 0
A66: ELEV | C66: Elevator Costs | D66: =+Dashboard!$P$15 -> 0.03 | F66: =+Dashboard!V36 -> 0 | G66: =+F66*(1+$D66) -> 0 | H66: =+G66*(1+$D66) -> 0 | I66: =+H66*(1+$D66) -> 0 | J66: =+I66*(1+$D66) -> 0 | K66: =+J66*(1+$D66) -> 0 | L66: =+K66*(1+$D66) -> 0 | M66: =+L66*(1+$D66) -> 0 | N66: =+M66*(1+$D66) -> 0 | O66: =+N66*(1+$D66) -> 0
A67: SNOW | C67: Snow | D67: =+Dashboard!$P$15 -> 0.03 | F67: =+Dashboard!V37 -> 0 | G67: =+F67*(1+$D67) -> 0 | H67: =+G67*(1+$D67) -> 0 | I67: =+H67*(1+$D67) -> 0 | J67: =+I67*(1+$D67) -> 0 | K67: =+J67*(1+$D67) -> 0 | L67: =+K67*(1+$D67) -> 0 | M67: =+L67*(1+$D67) -> 0 | N67: =+M67*(1+$D67) -> 0 | O67: =+N67*(1+$D67) -> 0
A68: MISCOP | C68: Misc. Operating & Maint. | D68: =+Dashboard!$P$15 -> 0.03 | F68: =+Dashboard!V38 -> 0 | G68: =+F68*(1+$D68) -> 0 | H68: =+G68*(1+$D68) -> 0 | I68: =+H68*(1+$D68) -> 0 | J68: =+I68*(1+$D68) -> 0 | K68: =+J68*(1+$D68) -> 0 | L68: =+K68*(1+$D68) -> 0 | M68: =+L68*(1+$D68) -> 0 | N68: =+M68*(1+$D68) -> 0 | O68: =+N68*(1+$D68) -> 0
C69: Contract Expenses | E69: =SUM(E61:E68) -> 0 | F69: =SUM(F61:F68) -> 0 | G69: =SUM(G61:G68) -> 0 | H69: =SUM(H61:H68) -> 0 | I69: =SUM(I61:I68) -> 0 | J69: =SUM(J61:J68) -> 0 | K69: =SUM(K61:K68) -> 0 | L69: =SUM(L61:L68) -> 0 | ... O69: =SUM(O61:O68) -> 0
A71: RETAX | C71: Real Estate Taxes | D71: =+Dashboard!$P$15 -> 0.03 | F71: =+Dashboard!V46 -> 0 | G71: =+F71*(1+$D71) -> 0 | H71: =+G71*(1+$D71) -> 0 | I71: =+H71*(1+$D71) -> 0 | J71: =+I71*(1+$D71) -> 0 | K71: =+J71*(1+$D71) -> 0 | L71: =+K71*(1+$D71) -> 0 | M71: =+L71*(1+$D71) -> 0 | N71: =+M71*(1+$D71) -> 0 | O71: =+N71*(1+$D71) -> 0
A72: INS | C72: Property & Liability Insurance | D72: =+Dashboard!$P$15 -> 0.03 | F72: =+Dashboard!V48 -> 32400 | G72: =+F72*(1+$D72) -> 33372 | H72: =+G72*(1+$D72) -> 34373.16 | I72: =+H72*(1+$D72) -> 35404.355 | J72: =+I72*(1+$D72) -> 36466.485 | K72: =+J72*(1+$D72) -> 37560.48 | L72: =+K72*(1+$D72) -> 38687.294 | M72: =+L72*(1+$D72) -> 39847.913 | N72: =+M72*(1+$D72) -> 41043.351 | O72: =+N72*(1+$D72) -> 42274.651
A73: WORKCOMP | C73: Workmens Comp | D73: =+Dashboard!$P$15 -> 0.03 | F73: =+Dashboard!V49 -> 2246.4 | G73: =+F73*(1+$D73) -> 2313.792 | H73: =+G73*(1+$D73) -> 2383.2058 | I73: =+H73*(1+$D73) -> 2454.7019 | J73: =+I73*(1+$D73) -> 2528.343 | K73: =+J73*(1+$D73) -> 2604.1933 | L73: =+K73*(1+$D73) -> 2682.3191 | M73: =+L73*(1+$D73) -> 2762.7887 | N73: =+M73*(1+$D73) -> 2845.6723 | O73: =+N73*(1+$D73) -> 2931.0425
A74: HEALTH | C74: Health Insurance & Other Benefits | D74: =+Dashboard!$P$15 -> 0.03 | F74: =+Dashboard!V50 -> 3369.6 | G74: =+F74*(1+$D74) -> 3470.688 | H74: =+G74*(1+$D74) -> 3574.8086 | I74: =+H74*(1+$D74) -> 3682.0529 | J74: =+I74*(1+$D74) -> 3792.5145 | K74: =+J74*(1+$D74) -> 3906.2899 | L74: =+K74*(1+$D74) -> 4023.4786 | M74: =+L74*(1+$D74) -> 4144.183 | N74: =+M74*(1+$D74) -> 4268.5085 | O74: =+N74*(1+$D74) -> 4396.5637
A75: PTAX | C75: Payroll Tax | D75: =+Dashboard!$P$15 -> 0.03 | F75: =+Dashboard!V51 -> 11232 | G75: =+F75*(1+$D75) -> 11568.96 | H75: =+G75*(1+$D75) -> 11916.029 | I75: =+H75*(1+$D75) -> 12273.51 | J75: =+I75*(1+$D75) -> 12641.715 | K75: =+J75*(1+$D75) -> 13020.966 | L75: =+K75*(1+$D75) -> 13411.595 | M75: =+L75*(1+$D75) -> 13813.943 | N75: =+M75*(1+$D75) -> 14228.362 | O75: =+N75*(1+$D75) -> 14655.212
A76: MISCTAX | C76: Misc Taxes, Licenses, Etc. | D76: =+Dashboard!$P$15 -> 0.03 | F76: =+Dashboard!V52 -> 0 | G76: =+F76*(1+$D76) -> 0 | H76: =+G76*(1+$D76) -> 0 | I76: =+H76*(1+$D76) -> 0 | J76: =+I76*(1+$D76) -> 0 | K76: =+J76*(1+$D76) -> 0 | L76: =+K76*(1+$D76) -> 0 | M76: =+L76*(1+$D76) -> 0 | N76: =+M76*(1+$D76) -> 0 | O76: =+N76*(1+$D76) -> 0
C77: Total Taxes and Insurance Expenses | E77: =SUM(E71:E76) -> 0 | F77: =SUM(F71:F76) -> 49248 | G77: =SUM(G71:G76) -> 50725.44 | H77: =SUM(H71:H76) -> 52247.203 | I77: =SUM(I71:I76) -> 53814.619 | J77: =SUM(J71:J76) -> 55429.058 | K77: =SUM(K71:K76) -> 57091.93 | L77: =SUM(L71:L76) -> 58804.687 | ... O77: =SUM(O71:O76) -> 64257.47
C79: Total Operating Expenses | E79: =+SUM(E18,E22,E29,E43,E51,E59,E69,E77,) -> 21600 | F79: =+SUM(F18,F22,F29,F43,F51,F59,F69,F77,) -> 272127.61 | G79: =+SUM(G18,G22,G29,G43,G51,G59,G69,G77,) -> 279643.44 | H79: =+SUM(H18,H22,H29,H43,H51,H59,H69,H77,) -> 287384.74 | I79: =+SUM(I18,I22,I29,I43,I51,I59,I69,I77,) -> 295358.28 | J79: =+SUM(J18,J22,J29,J43,J51,J59,J69,J77,) -> 303571.03 | K79: =+SUM(K18,K22,K29,K43,K51,K59,K69,K77,) -> 312030.16 | L79: =+SUM(L18,L22,L29,L43,L51,L59,L69,L77,) -> 320743.07 | ... O79: =+SUM(O18,O22,O29,O43,O51,O59,O69,O77,) -> 348481.71
C81: Net Operating Income | E81: =+E12-E79 -> 1526012 | F81: =+F12-F79 -> 291864.59 | G81: =+G12-G79 -> 301268.53 | H81: =+H12-H79 -> 310954.58 | I81: =+I12-I79 -> 320931.22 | J81: =+J12-J79 -> 331207.16 | K81: =+K12-K79 -> 341791.37 | L81: =+L12-L79 -> 352693.11 | ... O81: =+O12-O79 -> 387400.19
C82: NOI Margin | E82: =+IFERROR(E81/E12,"--") -> 0.98604301 | F82: =+F81/F12 -> 0.51749756 | G82: =+G81/G12 -> 0.51861305 | H82: =+H81/H12 -> 0.51969605 | I82: =+I81/I12 -> 0.5207475 | J82: =+J81/J12 -> 0.52176833 | K82: =+K81/K12 -> 0.52275943 | L82: =+L81/L12 -> 0.52372166 | M82: =+M81/M12 -> 0.52465586 | ... O82: =+O81/O12 -> 0.52644343
C84: Capital Expenditures
C85: Other CapEx
C86: Capital Reserve
C87: Total Capital Expenditures | E87: =+SUM(E85:E86) -> 0 | F87: =+SUM(F85:F86) -> 0 | G87: =+SUM(G85:G86) -> 0 | H87: =+SUM(H85:H86) -> 0 | I87: =+SUM(I85:I86) -> 0 | J87: =+SUM(J85:J86) -> 0 | K87: =+SUM(K85:K86) -> 0 | L87: =+SUM(L85:L86) -> 0 | ... O87: =+SUM(O85:O86) -> 0
C89: Cash Flow from Operations (Adj. NOI) | E89: =+E81-E87 -> 1526012 | F89: =+F81-F87 -> 291864.59 | G89: =+G81-G87 -> 301268.53 | H89: =+H81-H87 -> 310954.58 | I89: =+I81-I87 -> 320931.22 | J89: =+J81-J87 -> 331207.16 | K89: =+K81-K87 -> 341791.37 | L89: =+L81-L87 -> 352693.11 | ... O89: =+O81-O87 -> 387400.19
C91: Interest Expense Debt Service | E91: -- | F91: =+Dashboard!$I$10*Dashboard!$E$50 -> 181675 | G91: =+F91 -> 181675 | H91: =+G91 -> 181675 | I91: =+H91 -> 181675 | J91: =+I91 -> 181675 | K91: =+J91 -> 181675 | L91: =+K91 -> 181675 | M91: =+L91 -> 181675 | N91: =+M91 -> 181675 | O91: =+N91 -> 181675
C92: Principal Repayment | E92: -- | F92: =IF(F$6<=Dashboard!$E$56,0,-PPMT(Dashboard!$E$50,'Scenario 0'!F3-'Scenario 0'!$E3,Dashboard!$E$55,Dashboard!$D$49)) -> 0 | G92: =IF(G$6<=Dashboard!$E$56,0,-PPMT(Dashboard!$E$50,'Scenario 0'!G3-'Scenario 0'!$E3,Dashboard!$E$55,Dashboard!$D$49)) -> 0 | H92: =IF(H$6<=Dashboard!$E$56,0,-PPMT(Dashboard!$E$50,'Scenario 0'!H3-'Scenario 0'!$E3,Dashboard!$E$55,Dashboard!$D$49)) -> 0 | I92: =IF(I$6<=Dashboard!$E$56,0,-PPMT(Dashboard!$E$50,'Scenario 0'!I3-'Scenario 0'!$E3,Dashboard!$E$55,Dashboard!$D$49)) -> 0 | J92: =IF(J$6<=Dashboard!$E$56,0,-PPMT(Dashboard!$E$50,'Scenario 0'!J3-'Scenario 0'!$E3,Dashboard!$E$55,Dashboard!$D$49)) -> 0 | K92: =IF(K$6<=Dashboard!$E$56,0,-PPMT(Dashboard!$E$50,'Scenario 0'!K3-'Scenario 0'!$E3,Dashboard!$E$55,Dashboard!$D$49)) -> 0 | L92: =IF(L$6<=Dashboard!$E$56,0,-PPMT(Dashboard!$E$50,'Scenario 0'!L3-'Scenario 0'!$E3,Dashboard!$E$55,Dashboard!$D$49)) -> 0 | M92: =IF(M$6<=Dashboard!$E$56,0,-PPMT(Dashboard!$E$50,'Scenario 0'!M3-'Scenario 0'!$E3,Dashboard!$E$55,Dashboard!$D$49)) -> 0 | ... O92: =IF(O$6<=Dashboard!$E$56,0,-PPMT(Dashboard!$E$50,'Scenario 0'!O3-'Scenario 0'!$E3,Dashboard!$E$55,Dashboard!$D$49)) -> 57034.929
C93: Cash Flow After Financing (CF to Equity Investors) | E93: -- | F93: =+F89-F91 -> 110189.59 | G93: =+G89-G91 -> 119593.53 | H93: =+H89-H91 -> 129279.58 | I93: =+I89-I91 -> 139256.22 | J93: =+J89-J91 -> 149532.16 | K93: =+K89-K91 -> 160116.37 | L93: =+L89-L91 -> 171018.11 | M93: =+M89-M91 -> 182246.91 | N93: =+N89-N91-N92 -> 140258.64 | O93: =+O89-O91-O92 -> 148690.26
C95: Ending Debt Balance | F95: =+Dashboard!$D$49-SUM('Scenario 0'!$F$92:F92) -> 2795000 | G95: =+Dashboard!$D$49-SUM('Scenario 0'!$F$92:G92) -> 2795000 | H95: =+Dashboard!$D$49-SUM('Scenario 0'!$F$92:H92) -> 2795000 | I95: =+Dashboard!$D$49-SUM('Scenario 0'!$F$92:I92) -> 2795000 | J95: =+Dashboard!$D$49-SUM('Scenario 0'!$F$92:J92) -> 2795000 | K95: =+Dashboard!$D$49-SUM('Scenario 0'!$F$92:K92) -> 2795000 | L95: =+Dashboard!$D$49-SUM('Scenario 0'!$F$92:L92) -> 2795000 | M95: =+Dashboard!$D$49-SUM('Scenario 0'!$F$92:M92) -> 2795000 | ... O95: =+Dashboard!$D$49-SUM('Scenario 0'!$F$92:O92) -> 2684411.1
C97: DSCR (NOI) | F97: =+IFERROR(F81/F91,"") -> 1.6065204 | G97: =+IFERROR(G81/G91,"") -> 1.6582828 | H97: =+IFERROR(H81/H91,"") -> 1.7115981 | I97: =+IFERROR(I81/I91,"") -> 1.7665128 | J97: =+IFERROR(J81/J91,"") -> 1.823075 | K97: =+IFERROR(K81/K91,"") -> 1.8813341 | L97: =+IFERROR(L81/L91,"") -> 1.9413409 | M97: =+IFERROR(M81/M91,"") -> 2.003148 | ... O97: =+IFERROR(O81/O91,"") -> 2.1323803
C98: DSCR (CFO) | F98: =+IFERROR(F89/F91,"") -> 1.6065204 | G98: =+IFERROR(G89/G91,"") -> 1.6582828 | H98: =+IFERROR(H89/H91,"") -> 1.7115981 | I98: =+IFERROR(I89/I91,"") -> 1.7665128 | J98: =+IFERROR(J89/J91,"") -> 1.823075 | K98: =+IFERROR(K89/K91,"") -> 1.8813341 | L98: =+IFERROR(L89/L91,"") -> 1.9413409 | M98: =+IFERROR(M89/M91,"") -> 2.003148 | ... O98: =+IFERROR(O89/O91,"") -> 2.1323803
C99: Debt Yield (CFO) | F99: =+F89/Dashboard!$I$10 -> 0.10442382 | G99: =+G89/Dashboard!$I$10 -> 0.10778838 | H99: =+H89/Dashboard!$I$10 -> 0.11125388 | I99: =+I89/Dashboard!$I$10 -> 0.11482333 | J99: =+J89/Dashboard!$I$10 -> 0.11849988 | K99: =+K89/Dashboard!$I$10 -> 0.12228672 | L99: =+L89/Dashboard!$I$10 -> 0.12618716 | M99: =+M89/Dashboard!$I$10 -> 0.13020462 | ... O99: =+O89/Dashboard!$I$10 -> 0.13860472
C100: Break-Even Ratio | F100: =+SUM(F97,F79)/F12 -> 0.48250528 | G100: =+SUM(G97,G79)/G12 -> 0.4813898 | H100: =+SUM(H97,H79)/H12 -> 0.48030681 | I100: =+SUM(I97,I79)/I12 -> 0.47925536 | J100: =+SUM(J97,J79)/J12 -> 0.47823454 | K100: =+SUM(K97,K79)/K12 -> 0.47724345 | L100: =+SUM(L97,L79)/L12 -> 0.47628122 | M100: =+SUM(M97,M79)/M12 -> 0.47534703 | ... O100: =+SUM(O97,O79)/O12 -> 0.47355947
C102: Cap Rate (Purchase Price) | F102: =+F81/Dashboard!$E$32 -> 0.067875486 | G102: =+G81/Dashboard!$E$32 -> 0.070062448 | H102: =+H81/Dashboard!$E$32 -> 0.072315019 | I102: =+I81/Dashboard!$E$32 -> 0.074635168 | J102: =+J81/Dashboard!$E$32 -> 0.07702492 | K102: =+K81/Dashboard!$E$32 -> 0.079486366 | L102: =+L81/Dashboard!$E$32 -> 0.082021654 | M102: =+M81/Dashboard!$E$32 -> 0.084633002 | ... O102: =+O81/Dashboard!$E$32 -> 0.090093068
C103: Operating Cash Flow Before Taxes | F103: =+F81-F91-F92 -> 110189.59 | G103: =+G81-G91-G92 -> 119593.53 | H103: =+H81-H91-H92 -> 129279.58 | I103: =+I81-I91-I92 -> 139256.22 | J103: =+J81-J91-J92 -> 149532.16 | K103: =+K81-K91-K92 -> 160116.37 | L103: =+L81-L91-L92 -> 171018.11 | M103: =+M81-M91-M92 -> 182246.91 | ... O103: =+O81-O91-O92 -> 148690.26
C104: Cash on Cash Return | F104: =+F103/Dashboard!$I$11 -> 0.060444098 | G104: =+G103/Dashboard!$I$11 -> 0.065602593 | H104: =+H103/Dashboard!$I$11 -> 0.070915844 | I104: =+I103/Dashboard!$I$11 -> 0.076388492 | J104: =+J103/Dashboard!$I$11 -> 0.08202532 | K104: =+K103/Dashboard!$I$11 -> 0.087831252 | L104: =+L103/Dashboard!$I$11 -> 0.093811362 | M104: =+M103/Dashboard!$I$11 -> 0.099970876 | ... O104: =+O103/Dashboard!$I$11 -> 0.081563501
C105: General Partner Cash Return | D105: =+Dashboard!J58 -> 0.25 | F105: =+F103*$D$105 -> 27547.397 | G105: =+G103*$D$105 -> 29898.382 | H105: =+H103*$D$105 -> 32319.896 | I105: =+I103*$D$105 -> 34814.055 | J105: =+J103*$D$105 -> 37383.039 | K105: =+K103*$D$105 -> 40029.093 | L105: =+L103*$D$105 -> 42754.528 | M105: =+M103*$D$105 -> 45561.727 | ... O105: =+O103*$D$105 -> 37172.566
C106: Total Limited Partner Cash Return | D106: =+Dashboard!J59 -> 0.75 | F106: =+F103*$D$106 -> 82642.192 | G106: =+G103*$D$106 -> 89695.146 | H106: =+H103*$D$106 -> 96959.688 | I106: =+I103*$D$106 -> 104442.17 | J106: =+J103*$D$106 -> 112149.12 | K106: =+K103*$D$106 -> 120087.28 | L106: =+L103*$D$106 -> 128263.59 | M106: =+M103*$D$106 -> 136685.18 | ... O106: =+O103*$D$106 -> 111517.7
C107: Cash on Cash LP Return | F107: =+F106/Dashboard!$I$11 -> 0.045333073 | G107: =+G106/Dashboard!$I$11 -> 0.049201945 | H107: =+H106/Dashboard!$I$11 -> 0.053186883 | I107: =+I106/Dashboard!$I$11 -> 0.057291369 | J107: =+J106/Dashboard!$I$11 -> 0.06151899 | K107: =+K106/Dashboard!$I$11 -> 0.065873439 | L107: =+L106/Dashboard!$I$11 -> 0.070358522 | M107: =+M106/Dashboard!$I$11 -> 0.074978157 | ... O107: =+O106/Dashboard!$I$11 -> 0.061172626
C109: Return Metrics
C111: 5 Year Hold IRR | E111: Year 0 | F111: 1 | G111: 2 | H111: 3 | I111: 4 | J111: 5
C113: Exit Cap Rate Assumption | D113: =+Dashboard!$J$54 -> 0.06
C115: Project Cash Flows (Unleveraged IRR):
C116: (+) Proceeds from Sale of Property: | F116: 0 | G116: 0 | H116: 0 | I116: 0 | J116: =+J$81/D$113 -> 5520119.3
C117: (-) Selling Costs: | D117: =+Dashboard!$J$55 -> 0.015 | F117: 0 | G117: 0 | H117: 0 | I117: 0 | J117: =-J$116*D$117 -> -82801.789
C118: (+) Adjusted NOI (Cash Flows to All Investors): | F118: =+F$89 -> 291864.59 | G118: =+G$89 -> 301268.53 | H118: =+H$89 -> 310954.58 | I118: =+I$89 -> 320931.22 | J118: =+J$89 -> 331207.16
C119: (-) Property Acquisition Price: | E119: =-Dashboard!$E$32 -> -4300000 | F119: 0 | G119: 0 | H119: 0 | I119: 0 | J119: 0
C120: Total Project Cash Flows (Unleveraged IRR): | E120: =SUM(E116:E119) -> -4300000 | F120: =SUM(F116:F119) -> 291864.59 | G120: =SUM(G116:G119) -> 301268.53 | H120: =SUM(H116:H119) -> 310954.58 | I120: =SUM(I116:I119) -> 320931.22 | J120: =SUM(J116:J119) -> 5768524.7
F121: =+F120-F116 -> 291864.59 | G121: =+G120-G116 -> 301268.53 | H121: =+H120-H116 -> 310954.58 | I121: =+I120-I116 -> 320931.22 | J121: =+J120-J116 -> 248405.37
C123: Unlevered IRR: | E123: =+IRR(E120:J120) -> 0.11402295
C124: Unlevered Cash-on-Cash Multiple: | E124: =+SUM(F116:J118)/-SUM(E119:J119) -> 1.6264055
C126: Cash Flow to Equity Investors (Leveraged IRR):
...

Sheet Scenario 1
C1: Underwriting Model Scenario 1
D3: Year | E3: =+'Scenario 0'!E3 -> 2024 | F3: =+'Scenario 0'!F3 -> 2025 | G3: =+'Scenario 0'!G3 -> 2026 | H3: =+'Scenario 0'!H3 -> 2027 | I3: =+'Scenario 0'!I3 -> 2028 | J3: =+'Scenario 0'!J3 -> 2029 | K3: =+'Scenario 0'!K3 -> 2030 | L3: =+'Scenario 0'!L3 -> 2031 | ... O3: =+'Scenario 0'!O3 -> 2034
C4: ='Unit Mix'!$P$3 -> Scenario 1 ( Max Current Vouchers)
C6: Income Statement | E6: =+'Scenario 0'!E6 -> T12 | F6: =+'Scenario 0'!F6 -> 1 | G6: =+'Scenario 0'!G6 -> 2 | H6: =+'Scenario 0'!H6 -> 3 | I6: =+'Scenario 0'!I6 -> 4 | J6: =+'Scenario 0'!J6 -> 5 | K6: =+'Scenario 0'!K6 -> 6 | L6: =+'Scenario 0'!L6 -> 7 | ... O6: =+'Scenario 0'!O6 -> 10
C7: Gross Potential Income | E7: =+'Scenario 0'!$E$7 -> 1561954 | F7: =+'Unit Mix'!U26 -> 593676 | G7: =+'Unit Mix'!U49 -> 611486.28 | H7: =+'Unit Mix'!U72 -> 629830.87 | I7: =+'Unit Mix'!U95 -> 648725.79 | J7: =+'Unit Mix'!U118 -> 668187.57 | K7: =+'Unit Mix'!U141 -> 688233.2 | L7: =+'Unit Mix'!U164 -> 708880.19 | M7: =+'Unit Mix'!U187 -> 730146.6 | N7: =+'Unit Mix'!U210 -> 752050.99 | O7: =+'Unit Mix'!U233 -> 774612.52
C8: Vacancy Factor | D8: =+Dashboard!$P$10 -> 0.05 | E8: =+'Scenario 0'!$E$8 -> 48058 | F8: =+F7*$D$8 -> 29683.8 | G8: =+G7*$D$8 -> 30574.314 | H8: =+H7*$D$8 -> 31491.543 | I8: =+I7*$D$8 -> 32436.29 | J8: =+J7*$D$8 -> 33409.378 | K8: =+K7*$D$8 -> 34411.66 | L8: =+L7*$D$8 -> 35444.01 | M8: =+M7*$D$8 -> 36507.33 | ... O8: =+O7*$D$8 -> 38730.626
C9: Net Rental Income | E9: =+E7-E8 -> 1513896 | F9: =+F7-F8 -> 563992.2 | G9: =+G7-G8 -> 580911.97 | H9: =+H7-H8 -> 598339.32 | I9: =+I7-I8 -> 616289.5 | J9: =+J7-J8 -> 634778.19 | K9: =+K7-K8 -> 653821.54 | L9: =+L7-L8 -> 673436.18 | ... O9: =+O7-O8 -> 735881.9
C11: Laundry and Other Income | D11: =+Dashboard!$P$14 -> 0.025 | E11: =+'Scenario 0'!$E$11 -> 33716 | F11: =+Dashboard!$O$14 -> 0 | G11: =+F11*(1+$D11) -> 0 | H11: =+G11*(1+$D11) -> 0 | I11: =+H11*(1+$D11) -> 0 | J11: =+I11*(1+$D11) -> 0 | K11: =+J11*(1+$D11) -> 0 | L11: =+K11*(1+$D11) -> 0 | M11: =+L11*(1+$D11) -> 0 | N11: =+M11*(1+$D11) -> 0 | O11: =+N11*(1+$D11) -> 0
C12: Total Gross Income | E12: =+SUM(E9:E11) -> 1547612 | F12: =+SUM(F9:F11) -> 563992.2 | G12: =+SUM(G9:G11) -> 580911.97 | H12: =+SUM(H9:H11) -> 598339.32 | I12: =+SUM(I9:I11) -> 616289.5 | J12: =+SUM(J9:J11) -> 634778.19 | K12: =+SUM(K9:K11) -> 653821.54 | L12: =+SUM(L9:L11) -> 673436.18 | ... O12: =+SUM(O9:O11) -> 735881.9
C13: Gross Income Growth | E13: -- | F13: =+F12/E12-1 -> -0.63557261 | G13: =+G12/F12-1 -> 0.03 | H13: =+H12/G12-1 -> 0.03 | I13: =+I12/H12-1 -> 0.03 | J13: =+J12/I12-1 -> 0.03 | K13: =+K12/J12-1 -> 0.03 | L13: =+L12/K12-1 -> 0.03 | M13: =+M12/L12-1 -> 0.03 | ... O13: =+O12/N12-1 -> 0.03
C15: Opertating Expenses
A17: BAD
C18: Bad Debt | E18: =+'Scenario 0'!E18 -> 0 | F18: =+'Scenario 0'!F18 -> 0 | G18: =+'Scenario 0'!G18 -> 0 | H18: =+'Scenario 0'!H18 -> 0 | I18: =+'Scenario 0'!I18 -> 0 | J18: =+'Scenario 0'!J18 -> 0 | K18: =+'Scenario 0'!K18 -> 0 | L18: =+'Scenario 0'!L18 -> 0 | ... O18: =+'Scenario 0'!O18 -> 0
A20: RES
A21: COM
C22: Total Replacement Reserves | E22: =+'Scenario 0'!E22 -> 21600 | F22: =+'Scenario 0'!F22 -> 21600 | G22: =+'Scenario 0'!G22 -> 21600 | H22: =+'Scenario 0'!H22 -> 21600 | I22: =+'Scenario 0'!I22 -> 21600 | J22: =+'Scenario 0'!J22 -> 21600 | K22: =+'Scenario 0'!K22 -> 21600 | L22: =+'Scenario 0'!L22 -> 21600 | ... O22: =+'Scenario 0'!O22 -> 21600
A24: MAN
A25: ASS
A26: PAY
A27: MAIT
C28: Payroll | E28: =+'Scenario 0'!E29 -> 0 | F28: =+'Scenario 0'!F29 -> 126720 | G28: =+'Scenario 0'!G29 -> 130521.6 | H28: =+'Scenario 0'!H29 -> 134437.25 | I28: =+'Scenario 0'!I29 -> 138470.37 | J28: =+'Scenario 0'!J29 -> 142624.48 | K28: =+'Scenario 0'!K29 -> 146903.21 | L28: =+'Scenario 0'!L29 -> 151310.31 | ... O28: =+'Scenario 0'!O29 -> 165340.86
A30: MGMT
A31: LEGAL
A32: OFF
A33: TRAVEL
A34: AUD
A35: ADV
A36: TRAIN
A37: BANK
A38: BOOK
A39: PAYSERV
A40: UNIT
A41: MISCAD
C42: Admin Expenses | E42: =+'Scenario 0'!E43 -> 0 | F42: =+'Scenario 0'!F43 -> 59499.61 | G42: =+'Scenario 0'!G43 -> 61284.598 | H42: =+'Scenario 0'!H43 -> 63123.136 | I42: =+'Scenario 0'!I43 -> 65016.83 | J42: =+'Scenario 0'!J43 -> 66967.335 | K42: =+'Scenario 0'!K43 -> 68976.355 | L42: =+'Scenario 0'!L43 -> 71045.646 | ... O42: =+'Scenario 0'!O43 -> 77633.496
A44: ELEC
A45: VAC
A46: WS
A47: GAS
A48: CABLE
A49: TRASH
C50: Utility Expenses | E50: =+'Scenario 0'!E51 -> 0 | F50: =+'Scenario 0'!F51 -> 0 | G50: =+'Scenario 0'!G51 -> 0 | H50: =+'Scenario 0'!H51 -> 0 | I50: =+'Scenario 0'!I51 -> 0 | J50: =+'Scenario 0'!J51 -> 0 | K50: =+'Scenario 0'!K51 -> 0 | L50: =+'Scenario 0'!L51 -> 0 | ... O50: =+'Scenario 0'!O51 -> 0
A52: RM
A53: TURN
A54: SUPP
A55: APP
A56: HP
A57: CONC
C58: Operating and Maint. | E58: =+'Scenario 0'!E59 -> 0 | F58: =+'Scenario 0'!F59 -> 15060 | G58: =+'Scenario 0'!G59 -> 15511.8 | H58: =+'Scenario 0'!H59 -> 15977.154 | I58: =+'Scenario 0'!I59 -> 16456.469 | J58: =+'Scenario 0'!J59 -> 16950.163 | K58: =+'Scenario 0'!K59 -> 17458.668 | L58: =+'Scenario 0'!L59 -> 17982.428 | ... O58: =+'Scenario 0'!O59 -> 19649.884
A60: LAND
A61: FIRE
A62: SEC
A63: PEST
A64: CON
A65: ELEV
A66: SNOW
A67: MISCOP
C68: Contract Expenses | E68: =+'Scenario 0'!E69 -> 0 | F68: =+'Scenario 0'!F69 -> 0 | G68: =+'Scenario 0'!G69 -> 0 | H68: =+'Scenario 0'!H69 -> 0 | I68: =+'Scenario 0'!I69 -> 0 | J68: =+'Scenario 0'!J69 -> 0 | K68: =+'Scenario 0'!K69 -> 0 | L68: =+'Scenario 0'!L69 -> 0 | ... O68: =+'Scenario 0'!O69 -> 0
A70: RETAX
A71: INS
A72: WORKCOMP
A73: HEALTH
A74: PTAX
A75: MISCTAX
C76: Total Taxes and Insurance Expenses | E76: =+'Scenario 0'!E77 -> 0 | F76: =+'Scenario 0'!F77 -> 49248 | G76: =+'Scenario 0'!G77 -> 50725.44 | H76: =+'Scenario 0'!H77 -> 52247.203 | I76: =+'Scenario 0'!I77 -> 53814.619 | J76: =+'Scenario 0'!J77 -> 55429.058 | K76: =+'Scenario 0'!K77 -> 57091.93 | L76: =+'Scenario 0'!L77 -> 58804.687 | ... O76: =+'Scenario 0'!O77 -> 64257.47
C78: Total Operating Expenses | E78: =+SUM(E18,E22,E28,E42,E50,E58,E68,E76,) -> 21600 | F78: =+SUM(F18,F22,F28,F42,F50,F58,F68,F76,) -> 272127.61 | G78: =+SUM(G18,G22,G28,G42,G50,G58,G68,G76,) -> 279643.44 | H78: =+SUM(H18,H22,H28,H42,H50,H58,H68,H76,) -> 287384.74 | I78: =+SUM(I18,I22,I28,I42,I50,I58,I68,I76,) -> 295358.28 | J78: =+SUM(J18,J22,J28,J42,J50,J58,J68,J76,) -> 303571.03 | K78: =+SUM(K18,K22,K28,K42,K50,K58,K68,K76,) -> 312030.16 | L78: =+SUM(L18,L22,L28,L42,L50,L58,L68,L76,) -> 320743.07 | ... O78: =+SUM(O18,O22,O28,O42,O50,O58,O68,O76,) -> 348481.71
C80: Net Operating Income | E80: =+E12-E78 -> 1526012 | F80: =+F12-F78 -> 291864.59 | G80: =+G12-G78 -> 301268.53 | H80: =+H12-H78 -> 310954.58 | I80: =+I12-I78 -> 320931.22 | J80: =+J12-J78 -> 331207.16 | K80: =+K12-K78 -> 341791.37 | L80: =+L12-L78 -> 352693.11 | ... O80: =+O12-O78 -> 387400.19
C81: NOI Margin | E81: =+IFERROR(E80/E12,"--") -> 0.98604301 | F81: =+F80/F12 -> 0.51749756 | G81: =+G80/G12 -> 0.51861305 | H81: =+H80/H12 -> 0.51969605 | I81: =+I80/I12 -> 0.5207475 | J81: =+J80/J12 -> 0.52176833 | K81: =+K80/K12 -> 0.52275943 | L81: =+L80/L12 -> 0.52372166 | M81: =+M80/M12 -> 0.52465586 | ... O81: =+O80/O12 -> 0.52644343
C83: Capital Expenditures
C84: Other CapEx
C85: Capital Reserve
C86: Total Capital Expenditures | E86: =+SUM(E84:E85) -> 0 | F86: =+SUM(F84:F85) -> 0 | G86: =+SUM(G84:G85) -> 0 | H86: =+SUM(H84:H85) -> 0 | I86: =+SUM(I84:I85) -> 0 | J86: =+SUM(J84:J85) -> 0 | K86: =+SUM(K84:K85) -> 0 | L86: =+SUM(L84:L85) -> 0 | ... O86: =+SUM(O84:O85) -> 0
C88: Cash Flow from Operations (Adj. NOI) | E88: =+E80-E86 -> 1526012 | F88: =+F80-F86 -> 291864.59 | G88: =+G80-G86 -> 301268.53 | H88: =+H80-H86 -> 310954.58 | I88: =+I80-I86 -> 320931.22 | J88: =+J80-J86 -> 331207.16 | K88: =+K80-K86 -> 341791.37 | L88: =+L80-L86 -> 352693.11 | ... O88: =+O80-O86 -> 387400.19
C90: Debt Service | E90: -- | F90: =+Dashboard!$I$10*Dashboard!$E$50 -> 181675 | G90: =+F90 -> 181675 | H90: =+G90 -> 181675 | I90: =+H90 -> 181675 | J90: =+I90 -> 181675 | K90: =+J90 -> 181675 | L90: =+K90 -> 181675 | M90: =+L90 -> 181675 | N90: =+M90 -> 181675 | O90: =+N90 -> 181675
C91: Principal Repayment | E91: -- | F91: =IF(F$6<=Dashboard!$E$56,0,-PPMT(Dashboard!$E$50,'Scenario 1'!F3-'Scenario 1'!$E3,Dashboard!$E$55,Dashboard!$D$49)) -> 0 | G91: =IF(G$6<=Dashboard!$E$56,0,-PPMT(Dashboard!$E$50,'Scenario 1'!G3-'Scenario 1'!$E3,Dashboard!$E$55,Dashboard!$D$49)) -> 0 | H91: =IF(H$6<=Dashboard!$E$56,0,-PPMT(Dashboard!$E$50,'Scenario 1'!H3-'Scenario 1'!$E3,Dashboard!$E$55,Dashboard!$D$49)) -> 0 | I91: =IF(I$6<=Dashboard!$E$56,0,-PPMT(Dashboard!$E$50,'Scenario 1'!I3-'Scenario 1'!$E3,Dashboard!$E$55,Dashboard!$D$49)) -> 0 | J91: =IF(J$6<=Dashboard!$E$56,0,-PPMT(Dashboard!$E$50,'Scenario 1'!J3-'Scenario 1'!$E3,Dashboard!$E$55,Dashboard!$D$49)) -> 0 | K91: =IF(K$6<=Dashboard!$E$56,0,-PPMT(Dashboard!$E$50,'Scenario 1'!K3-'Scenario 1'!$E3,Dashboard!$E$55,Dashboard!$D$49)) -> 0 | L91: =IF(L$6<=Dashboard!$E$56,0,-PPMT(Dashboard!$E$50,'Scenario 1'!L3-'Scenario 1'!$E3,Dashboard!$E$55,Dashboard!$D$49)) -> 0 | M91: =IF(M$6<=Dashboard!$E$56,0,-PPMT(Dashboard!$E$50,'Scenario 1'!M3-'Scenario 1'!$E3,Dashboard!$E$55,Dashboard!$D$49)) -> 0 | ... O91: =IF(O$6<=Dashboard!$E$56,0,-PPMT(Dashboard!$E$50,'Scenario 1'!O3-'Scenario 1'!$E3,Dashboard!$E$55,Dashboard!$D$49)) -> 57034.929
C92: Cash Flow After Financing (CF to Equity Investors) | E92: -- | F92: =+F88-F90 -> 110189.59 | G92: =+G88-G90 -> 119593.53 | H92: =+H88-H90 -> 129279.58 | I92: =+I88-I90 -> 139256.22 | J92: =+J88-J90 -> 149532.16 | K92: =+K88-K90 -> 160116.37 | L92: =+L88-L90 -> 171018.11 | M92: =+M88-M90 -> 182246.91 | ... O92: =+O88-O90 -> 205725.19
C94: Ending Debt Balance | F94: =+Dashboard!$D$49-SUM('Scenario 1'!$F$91:F91) -> 2795000 | G94: =+Dashboard!$D$49-SUM('Scenario 1'!$F$91:G91) -> 2795000 | H94: =+Dashboard!$D$49-SUM('Scenario 1'!$F$91:H91) -> 2795000 | I94: =+Dashboard!$D$49-SUM('Scenario 1'!$F$91:I91) -> 2795000 | J94: =+Dashboard!$D$49-SUM('Scenario 1'!$F$91:J91) -> 2795000 | K94: =+Dashboard!$D$49-SUM('Scenario 1'!$F$91:K91) -> 2795000 | L94: =+Dashboard!$D$49-SUM('Scenario 1'!$F$91:L91) -> 2795000 | M94: =+Dashboard!$D$49-SUM('Scenario 1'!$F$91:M91) -> 2795000 | ... O94: =+Dashboard!$D$49-SUM('Scenario 1'!$F$91:O91) -> 2684411.1
C96: DSCR (NOI) | F96: =+IFERROR(F80/F90,"") -> 1.6065204 | G96: =+IFERROR(G80/G90,"") -> 1.6582828 | H96: =+IFERROR(H80/H90,"") -> 1.7115981 | I96: =+IFERROR(I80/I90,"") -> 1.7665128 | J96: =+IFERROR(J80/J90,"") -> 1.823075 | K96: =+IFERROR(K80/K90,"") -> 1.8813341 | L96: =+IFERROR(L80/L90,"") -> 1.9413409 | M96: =+IFERROR(M80/M90,"") -> 2.003148 | ... O96: =+IFERROR(O80/O90,"") -> 2.1323803
C97: DSCR (CFO) | F97: =+IFERROR(F88/F90,"") -> 1.6065204 | G97: =+IFERROR(G88/G90,"") -> 1.6582828 | H97: =+IFERROR(H88/H90,"") -> 1.7115981 | I97: =+IFERROR(I88/I90,"") -> 1.7665128 | J97: =+IFERROR(J88/J90,"") -> 1.823075 | K97: =+IFERROR(K88/K90,"") -> 1.8813341 | L97: =+IFERROR(L88/L90,"") -> 1.9413409 | M97: =+IFERROR(M88/M90,"") -> 2.003148 | ... O97: =+IFERROR(O88/O90,"") -> 2.1323803
C98: Debt Yield (CFO) | F98: =+F88/Dashboard!$I$10 -> 0.10442382 | G98: =+G88/Dashboard!$I$10 -> 0.10778838 | H98: =+H88/Dashboard!$I$10 -> 0.11125388 | I98: =+I88/Dashboard!$I$10 -> 0.11482333 | J98: =+J88/Dashboard!$I$10 -> 0.11849988 | K98: =+K88/Dashboard!$I$10 -> 0.12228672 | L98: =+L88/Dashboard!$I$10 -> 0.12618716 | M98: =+M88/Dashboard!$I$10 -> 0.13020462 | ... O98: =+O88/Dashboard!$I$10 -> 0.13860472
C99: Break-Even Ratio | F99: =+SUM(F96,F78)/F12 -> 0.48250528 | G99: =+SUM(G96,G78)/G12 -> 0.4813898 | H99: =+SUM(H96,H78)/H12 -> 0.48030681 | I99: =+SUM(I96,I78)/I12 -> 0.47925536 | J99: =+SUM(J96,J78)/J12 -> 0.47823454 | K99: =+SUM(K96,K78)/K12 -> 0.47724345 | L99: =+SUM(L96,L78)/L12 -> 0.47628122 | M99: =+SUM(M96,M78)/M12 -> 0.47534703 | ... O99: =+SUM(O96,O78)/O12 -> 0.47355947
C101: Cap Rate (Purchase Price) | F101: =+F80/Dashboard!$E$32 -> 0.067875486 | G101: =+G80/Dashboard!$E$32 -> 0.070062448 | H101: =+H80/Dashboard!$E$32 -> 0.072315019 | I101: =+I80/Dashboard!$E$32 -> 0.074635168 | J101: =+J80/Dashboard!$E$32 -> 0.07702492 | K101: =+K80/Dashboard!$E$32 -> 0.079486366 | L101: =+L80/Dashboard!$E$32 -> 0.082021654 | M101: =+M80/Dashboard!$E$32 -> 0.084633002 | ... O101: =+O80/Dashboard!$E$32 -> 0.090093068
C102: Operating Cash Flow Before Taxes | F102: =+F80-F90-F91 -> 110189.59 | G102: =+G80-G90-G91 -> 119593.53 | H102: =+H80-H90-H91 -> 129279.58 | I102: =+I80-I90-I91 -> 139256.22 | J102: =+J80-J90-J91 -> 149532.16 | K102: =+K80-K90-K91 -> 160116.37 | L102: =+L80-L90-L91 -> 171018.11 | M102: =+M80-M90-M91 -> 182246.91 | ... O102: =+O80-O90-O91 -> 148690.26
C103: Cash on Cash Return | F103: =+F102/Dashboard!$I$11 -> 0.060444098 | G103: =+G102/Dashboard!$I$11 -> 0.065602593 | H103: =+H102/Dashboard!$I$11 -> 0.070915844 | I103: =+I102/Dashboard!$I$11 -> 0.076388492 | J103: =+J102/Dashboard!$I$11 -> 0.08202532 | K103: =+K102/Dashboard!$I$11 -> 0.087831252 | L103: =+L102/Dashboard!$I$11 -> 0.093811362 | M103: =+M102/Dashboard!$I$11 -> 0.099970876 | ... O103: =+O102/Dashboard!$I$11 -> 0.081563501
C104: General Partner Cash Return | D104: =+Dashboard!J58 -> 0.25 | F104: =+F102*$D$104 -> 27547.397 | G104: =+G102*$D$104 -> 29898.382 | H104: =+H102*$D$104 -> 32319.896 | I104: =+I102*$D$104 -> 34814.055 | J104: =+J102*$D$104 -> 37383.039 | K104: =+K102*$D$104 -> 40029.093 | L104: =+L102*$D$104 -> 42754.528 | M104: =+M102*$D$104 -> 45561.727 | ... O104: =+O102*$D$104 -> 37172.566
C105: Total Limited Partner Cash Return | D105: =+Dashboard!J59 -> 0.75 | F105: =+F102*$D$105 -> 82642.192 | G105: =+G102*$D$105 -> 89695.146 | H105: =+H102*$D$105 -> 96959.688 | I105: =+I102*$D$105 -> 104442.17 | J105: =+J102*$D$105 -> 112149.12 | K105: =+K102*$D$105 -> 120087.28 | L105: =+L102*$D$105 -> 128263.59 | M105: =+M102*$D$105 -> 136685.18 | ... O105: =+O102*$D$105 -> 111517.7
C106: Cash on Cash LP Return | F106: =+F105/Dashboard!$I$11 -> 0.045333073 | G106: =+G105/Dashboard!$I$11 -> 0.049201945 | H106: =+H105/Dashboard!$I$11 -> 0.053186883 | I106: =+I105/Dashboard!$I$11 -> 0.057291369 | J106: =+J105/Dashboard!$I$11 -> 0.06151899 | K106: =+K105/Dashboard!$I$11 -> 0.065873439 | L106: =+L105/Dashboard!$I$11 -> 0.070358522 | M106: =+M105/Dashboard!$I$11 -> 0.074978157 | ... O106: =+O105/Dashboard!$I$11 -> 0.061172626
C108: Return Metrics
C110: 5 Year Hold IRR | E110: =+'Scenario 0'!E111 -> Year 0 | F110: =+'Scenario 0'!F111 -> 1 | G110: =+'Scenario 0'!G111 -> 2 | H110: =+'Scenario 0'!H111 -> 3 | I110: =+'Scenario 0'!I111 -> 4 | J110: =+'Scenario 0'!J111 -> 5
C112: Exit Cap Rate Assumption | D112: =+Dashboard!$J$54 -> 0.06
C114: Project Cash Flows (Unleveraged IRR):
C115: (+) Proceeds from Sale of Property: | F115: 0 | G115: 0 | H115: 0 | I115: 0 | J115: =+J$80/D$112 -> 5520119.3
C116: (-) Selling Costs: | D116: =+Dashboard!$J$55 -> 0.015 | F116: 0 | G116: 0 | H116: 0 | I116: 0 | J116: =-J$115*D$116 -> -82801.789
C117: (+) Adjusted NOI (Cash Flows to All Investors): | F117: =+F$88 -> 291864.59 | G117: =+G$88 -> 301268.53 | H117: =+H$88 -> 310954.58 | I117: =+I$88 -> 320931.22 | J117: =+J$88 -> 331207.16
C118: (-) Property Acquisition Price: | E118: =-Dashboard!$E$32 -> -4300000 | F118: 0 | G118: 0 | H118: 0 | I118: 0 | J118: 0
C119: Total Project Cash Flows (Unleveraged IRR): | E119: =SUM(E115:E118) -> -4300000 | F119: =SUM(F115:F118) -> 291864.59 | G119: =SUM(G115:G118) -> 301268.53 | H119: =SUM(H115:H118) -> 310954.58 | I119: =SUM(I115:I118) -> 320931.22 | J119: =SUM(J115:J118) -> 5768524.7
F120: =+F119-F115 -> 291864.59 | G120: =+G119-G115 -> 301268.53 | H120: =+H119-H115 -> 310954.58 | I120: =+I119-I115 -> 320931.22 | J120: =+J119-J115 -> 248405.37
C122: Unlevered IRR: | E122: =+IRR(E119:J119) -> 0.11402295
C123: Unlevered Cash-on-Cash Multiple: | E123: =+SUM(F115:J117)/-SUM(E118:J118) -> 1.6264055
C125: Cash Flow to Equity Investors (Leveraged IRR):
C126: (+) Proceeds from Sale of Property: | F126: 0 | G126: 0 | H126: 0 | I126: 0 | J126: =+J$80/D$112 -> 5520119.3
...

Sheet Scenario 2
C1: Underwriting Model Scenario 2
D3: Year | E3: =+'Scenario 0'!E3 -> 2024 | F3: =+'Scenario 0'!F3 -> 2025 | G3: =+'Scenario 0'!G3 -> 2026 | H3: =+'Scenario 0'!H3 -> 2027 | I3: =+'Scenario 0'!I3 -> 2028 | J3: =+'Scenario 0'!J3 -> 2029 | K3: =+'Scenario 0'!K3 -> 2030 | L3: =+'Scenario 0'!L3 -> 2031 | ... O3: =+'Scenario 0'!O3 -> 2034
C4: ='Unit Mix'!$W$3 -> Scenario 2 (Max Net LIHTC)
C6: Income Statement | E6: =+'Scenario 0'!E6 -> T12 | F6: =+'Scenario 0'!F6 -> 1 | G6: =+'Scenario 0'!G6 -> 2 | H6: =+'Scenario 0'!H6 -> 3 | I6: =+'Scenario 0'!I6 -> 4 | J6: =+'Scenario 0'!J6 -> 5 | K6: =+'Scenario 0'!K6 -> 6 | L6: =+'Scenario 0'!L6 -> 7 | ... O6: =+'Scenario 0'!O6 -> 10
C7: Gross Potential Income | E7: =+'Scenario 0'!$E$7 -> 1561954 | F7: =+'Unit Mix'!AB26 -> 640308 | G7: =+'Unit Mix'!AB49 -> 659517.24 | H7: =+'Unit Mix'!AB72 -> 679302.76 | I7: =+'Unit Mix'!AB95 -> 699681.84 | J7: =+'Unit Mix'!AB118 -> 720672.3 | K7: =+'Unit Mix'!AB141 -> 742292.46 | L7: =+'Unit Mix'!AB164 -> 764561.24 | M7: =+'Unit Mix'!AB187 -> 787498.08 | N7: =+'Unit Mix'!AB210 -> 811123.02 | O7: =+'Unit Mix'!AB233 -> 835456.71
C8: Vacancy Factor | D8: =+Dashboard!$P$10 -> 0.05 | E8: =+'Scenario 0'!$E$8 -> 48058 | F8: =+F7*$D$8 -> 32015.4 | G8: =+G7*$D$8 -> 32975.862 | H8: =+H7*$D$8 -> 33965.138 | I8: =+I7*$D$8 -> 34984.092 | J8: =+J7*$D$8 -> 36033.615 | K8: =+K7*$D$8 -> 37114.623 | L8: =+L7*$D$8 -> 38228.062 | M8: =+M7*$D$8 -> 39374.904 | ... O8: =+O7*$D$8 -> 41772.835
C9: Net Rental Income | E9: =+E7-E8 -> 1513896 | F9: =+F7-F8 -> 608292.6 | G9: =+G7-G8 -> 626541.38 | H9: =+H7-H8 -> 645337.62 | I9: =+I7-I8 -> 664697.75 | J9: =+J7-J8 -> 684638.68 | K9: =+K7-K8 -> 705177.84 | L9: =+L7-L8 -> 726333.18 | ... O9: =+O7-O8 -> 793683.87
C11: Laundry and Other Income | D11: =+Dashboard!$P$14 -> 0.025 | E11: =+'Scenario 0'!$E$11 -> 33716 | F11: =+Dashboard!$O$14 -> 0 | G11: =+F11*(1+$D11) -> 0 | H11: =+G11*(1+$D11) -> 0 | I11: =+H11*(1+$D11) -> 0 | J11: =+I11*(1+$D11) -> 0 | K11: =+J11*(1+$D11) -> 0 | L11: =+K11*(1+$D11) -> 0 | M11: =+L11*(1+$D11) -> 0 | N11: =+M11*(1+$D11) -> 0 | O11: =+N11*(1+$D11) -> 0
C12: Total Gross Income | E12: =+SUM(E9:E11) -> 1547612 | F12: =+SUM(F9:F11) -> 608292.6 | G12: =+SUM(G9:G11) -> 626541.38 | H12: =+SUM(H9:H11) -> 645337.62 | I12: =+SUM(I9:I11) -> 664697.75 | J12: =+SUM(J9:J11) -> 684638.68 | K12: =+SUM(K9:K11) -> 705177.84 | L12: =+SUM(L9:L11) -> 726333.18 | ... O12: =+SUM(O9:O11) -> 793683.87
C13: Gross Income Growth | E13: -- | F13: =+F12/E12-1 -> -0.60694761 | G13: =+G12/F12-1 -> 0.03 | H13: =+H12/G12-1 -> 0.03 | I13: =+I12/H12-1 -> 0.03 | J13: =+J12/I12-1 -> 0.03 | K13: =+K12/J12-1 -> 0.03 | L13: =+L12/K12-1 -> 0.03 | M13: =+M12/L12-1 -> 0.03 | ... O13: =+O12/N12-1 -> 0.03
C15: Opertating Expenses
A17: BAD
C18: Bad Debt | E18: =+'Scenario 0'!E18 -> 0 | F18: =+'Scenario 0'!F18 -> 0 | G18: =+'Scenario 0'!G18 -> 0 | H18: =+'Scenario 0'!H18 -> 0 | I18: =+'Scenario 0'!I18 -> 0 | J18: =+'Scenario 0'!J18 -> 0 | K18: =+'Scenario 0'!K18 -> 0 | L18: =+'Scenario 0'!L18 -> 0 | ... O18: =+'Scenario 0'!O18 -> 0
A20: RES
A21: COM
C22: Total Replacement Reserves | E22: =+'Scenario 0'!E22 -> 21600 | F22: =+'Scenario 0'!F22 -> 21600 | G22: =+'Scenario 0'!G22 -> 21600 | H22: =+'Scenario 0'!H22 -> 21600 | I22: =+'Scenario 0'!I22 -> 21600 | J22: =+'Scenario 0'!J22 -> 21600 | K22: =+'Scenario 0'!K22 -> 21600 | L22: =+'Scenario 0'!L22 -> 21600 | ... O22: =+'Scenario 0'!O22 -> 21600
A24: MAN
A25: ASS
A26: PAY
A27: MAIT
C28: Payroll | E28: =+'Scenario 0'!E29 -> 0 | F28: =+'Scenario 0'!F29 -> 126720 | G28: =+'Scenario 0'!G29 -> 130521.6 | H28: =+'Scenario 0'!H29 -> 134437.25 | I28: =+'Scenario 0'!I29 -> 138470.37 | J28: =+'Scenario 0'!J29 -> 142624.48 | K28: =+'Scenario 0'!K29 -> 146903.21 | L28: =+'Scenario 0'!L29 -> 151310.31 | ... O28: =+'Scenario 0'!O29 -> 165340.86
A30: MGMT
A31: LEGAL
A32: OFF
A33: TRAVEL
A34: AUD
A35: ADV
A36: TRAIN
A37: BANK
A38: BOOK
A39: PAYSERV
A40: UNIT
A41: MISCAD
C42: Admin Expenses | E42: =+'Scenario 0'!E43 -> 0 | F42: =+'Scenario 0'!F43 -> 59499.61 | G42: =+'Scenario 0'!G43 -> 61284.598 | H42: =+'Scenario 0'!H43 -> 63123.136 | I42: =+'Scenario 0'!I43 -> 65016.83 | J42: =+'Scenario 0'!J43 -> 66967.335 | K42: =+'Scenario 0'!K43 -> 68976.355 | L42: =+'Scenario 0'!L43 -> 71045.646 | ... O42: =+'Scenario 0'!O43 -> 77633.496
A44: ELEC
A45: VAC
A46: WS
A47: GAS
A48: CABLE
A49: TRASH
C50: Utility Expenses | E50: =+'Scenario 0'!E51 -> 0 | F50: =+'Scenario 0'!F51 -> 0 | G50: =+'Scenario 0'!G51 -> 0 | H50: =+'Scenario 0'!H51 -> 0 | I50: =+'Scenario 0'!I51 -> 0 | J50: =+'Scenario 0'!J51 -> 0 | K50: =+'Scenario 0'!K51 -> 0 | L50: =+'Scenario 0'!L51 -> 0 | ... O50: =+'Scenario 0'!O51 -> 0
A52: RM
A53: TURN
A54: SUPP
A55: APP
A56: HP
A57: CONC
C58: Operating and Maint. | E58: =+'Scenario 0'!E59 -> 0 | F58: =+'Scenario 0'!F59 -> 15060 | G58: =+'Scenario 0'!G59 -> 15511.8 | H58: =+'Scenario 0'!H59 -> 15977.154 | I58: =+'Scenario 0'!I59 -> 16456.469 | J58: =+'Scenario 0'!J59 -> 16950.163 | K58: =+'Scenario 0'!K59 -> 17458.668 | L58: =+'Scenario 0'!L59 -> 17982.428 | ... O58: =+'Scenario 0'!O59 -> 19649.884
A60: LAND
A61: FIRE
A62: SEC
A63: PEST
A64: CON
A65: ELEV
A66: SNOW
A67: MISCOP
C68: Contract Expenses | E68: =+'Scenario 0'!E69 -> 0 | F68: =+'Scenario 0'!F69 -> 0 | G68: =+'Scenario 0'!G69 -> 0 | H68: =+'Scenario 0'!H69 -> 0 | I68: =+'Scenario 0'!I69 -> 0 | J68: =+'Scenario 0'!J69 -> 0 | K68: =+'Scenario 0'!K69 -> 0 | L68: =+'Scenario 0'!L69 -> 0 | ... O68: =+'Scenario 0'!O69 -> 0
A70: RETAX
A71: INS
A72: WORKCOMP
A73: HEALTH
A74: PTAX
A75: MISCTAX
C76: Total Taxes and Insurance Expenses | E76: =+'Scenario 0'!E77 -> 0 | F76: =+'Scenario 0'!F77 -> 49248 | G76: =+'Scenario 0'!G77 -> 50725.44 | H76: =+'Scenario 0'!H77 -> 52247.203 | I76: =+'Scenario 0'!I77 -> 53814.619 | J76: =+'Scenario 0'!J77 -> 55429.058 | K76: =+'Scenario 0'!K77 -> 57091.93 | L76: =+'Scenario 0'!L77 -> 58804.687 | ... O76: =+'Scenario 0'!O77 -> 64257.47
C78: Total Operating Expenses | E78: =+SUM(E18,E22,E28,E42,E50,E58,E68,E76,) -> 21600 | F78: =+SUM(F18,F22,F28,F42,F50,F58,F68,F76,) -> 272127.61 | G78: =+SUM(G18,G22,G28,G42,G50,G58,G68,G76,) -> 279643.44 | H78: =+SUM(H18,H22,H28,H42,H50,H58,H68,H76,) -> 287384.74 | I78: =+SUM(I18,I22,I28,I42,I50,I58,I68,I76,) -> 295358.28 | J78: =+SUM(J18,J22,J28,J42,J50,J58,J68,J76,) -> 303571.03 | K78: =+SUM(K18,K22,K28,K42,K50,K58,K68,K76,) -> 312030.16 | L78: =+SUM(L18,L22,L28,L42,L50,L58,L68,L76,) -> 320743.07 | ... O78: =+SUM(O18,O22,O28,O42,O50,O58,O68,O76,) -> 348481.71
C80: Net Operating Income | E80: =+E12-E78 -> 1526012 | F80: =+F12-F78 -> 336164.99 | G80: =+G12-G78 -> 346897.94 | H80: =+H12-H78 -> 357952.88 | I80: =+I12-I78 -> 369339.46 | J80: =+J12-J78 -> 381067.65 | K80: =+K12-K78 -> 393147.68 | L80: =+L12-L78 -> 405590.11 | ... O80: =+O12-O78 -> 445202.17
C81: NOI Margin | E81: =+IFERROR(E80/E12,"--") -> 0.98604301 | F81: =+F80/F12 -> 0.55263699 | G81: =+G80/G12 -> 0.55367124 | H81: =+H80/H12 -> 0.55467536 | I81: =+I80/I12 -> 0.55565024 | J81: =+J80/J12 -> 0.55659673 | K81: =+K80/K12 -> 0.55751564 | L81: =+L80/L12 -> 0.5584078 | M81: =+M80/M12 -> 0.55927396 | ... O81: =+O80/O12 -> 0.56093135
C83: Capital Expenditures
C84: Other CapEx
C85: Capital Reserve
C86: Total Capital Expenditures | E86: =+SUM(E84:E85) -> 0 | F86: =+SUM(F84:F85) -> 0 | G86: =+SUM(G84:G85) -> 0 | H86: =+SUM(H84:H85) -> 0 | I86: =+SUM(I84:I85) -> 0 | J86: =+SUM(J84:J85) -> 0 | K86: =+SUM(K84:K85) -> 0 | L86: =+SUM(L84:L85) -> 0 | ... O86: =+SUM(O84:O85) -> 0
C88: Cash Flow from Operations (Adj. NOI) | E88: =+E80-E86 -> 1526012 | F88: =+F80-F86 -> 336164.99 | G88: =+G80-G86 -> 346897.94 | H88: =+H80-H86 -> 357952.88 | I88: =+I80-I86 -> 369339.46 | J88: =+J80-J86 -> 381067.65 | K88: =+K80-K86 -> 393147.68 | L88: =+L80-L86 -> 405590.11 | ... O88: =+O80-O86 -> 445202.17
C90: Debt Service | E90: -- | F90: =+Dashboard!$I$10*Dashboard!$E$50 -> 181675 | G90: =+F90 -> 181675 | H90: =+G90 -> 181675 | I90: =+H90 -> 181675 | J90: =+I90 -> 181675 | K90: =+J90 -> 181675 | L90: =+K90 -> 181675 | M90: =+L90 -> 181675 | N90: =+M90 -> 181675 | O90: =+N90 -> 181675
C91: Principal Repayment | E91: -- | F91: =IF(F$6<=Dashboard!$E$56,0,-PPMT(Dashboard!$E$50,'Scenario 2'!F3-'Scenario 2'!$E3,Dashboard!$E$55,Dashboard!$D$49)) -> 0 | G91: =IF(G$6<=Dashboard!$E$56,0,-PPMT(Dashboard!$E$50,'Scenario 2'!G3-'Scenario 2'!$E3,Dashboard!$E$55,Dashboard!$D$49)) -> 0 | H91: =IF(H$6<=Dashboard!$E$56,0,-PPMT(Dashboard!$E$50,'Scenario 2'!H3-'Scenario 2'!$E3,Dashboard!$E$55,Dashboard!$D$49)) -> 0 | I91: =IF(I$6<=Dashboard!$E$56,0,-PPMT(Dashboard!$E$50,'Scenario 2'!I3-'Scenario 2'!$E3,Dashboard!$E$55,Dashboard!$D$49)) -> 0 | J91: =IF(J$6<=Dashboard!$E$56,0,-PPMT(Dashboard!$E$50,'Scenario 2'!J3-'Scenario 2'!$E3,Dashboard!$E$55,Dashboard!$D$49)) -> 0 | K91: =IF(K$6<=Dashboard!$E$56,0,-PPMT(Dashboard!$E$50,'Scenario 2'!K3-'Scenario 2'!$E3,Dashboard!$E$55,Dashboard!$D$49)) -> 0 | L91: =IF(L$6<=Dashboard!$E$56,0,-PPMT(Dashboard!$E$50,'Scenario 2'!L3-'Scenario 2'!$E3,Dashboard!$E$55,Dashboard!$D$49)) -> 0 | M91: =IF(M$6<=Dashboard!$E$56,0,-PPMT(Dashboard!$E$50,'Scenario 2'!M3-'Scenario 2'!$E3,Dashboard!$E$55,Dashboard!$D$49)) -> 0 | ... O91: =IF(O$6<=Dashboard!$E$56,0,-PPMT(Dashboard!$E$50,'Scenario 2'!O3-'Scenario 2'!$E3,Dashboard!$E$55,Dashboard!$D$49)) -> 57034.929
C92: Cash Flow After Financing (CF to Equity Investors) | E92: -- | F92: =+F88-F90 -> 154489.99 | G92: =+G88-G90 -> 165222.94 | H92: =+H88-H90 -> 176277.88 | I92: =+I88-I90 -> 187664.46 | J92: =+J88-J90 -> 199392.65 | K92: =+K88-K90 -> 211472.68 | L92: =+L88-L90 -> 223915.11 | M92: =+M88-M90 -> 236730.81 | ... O92: =+O88-O90 -> 263527.17
C94: Ending Debt Balance | F94: =+Dashboard!$D$49-SUM('Scenario 2'!$F$91:F91) -> 2795000 | G94: =+Dashboard!$D$49-SUM('Scenario 2'!$F$91:G91) -> 2795000 | H94: =+Dashboard!$D$49-SUM('Scenario 2'!$F$91:H91) -> 2795000 | I94: =+Dashboard!$D$49-SUM('Scenario 2'!$F$91:I91) -> 2795000 | J94: =+Dashboard!$D$49-SUM('Scenario 2'!$F$91:J91) -> 2795000 | K94: =+Dashboard!$D$49-SUM('Scenario 2'!$F$91:K91) -> 2795000 | L94: =+Dashboard!$D$49-SUM('Scenario 2'!$F$91:L91) -> 2795000 | M94: =+Dashboard!$D$49-SUM('Scenario 2'!$F$91:M91) -> 2795000 | ... O94: =+Dashboard!$D$49-SUM('Scenario 2'!$F$91:O91) -> 2684411.1
C96: DSCR (NOI) | F96: =+IFERROR(F80/F90,"") -> 1.8503646 | G96: =+IFERROR(G80/G90,"") -> 1.9094424 | H96: =+IFERROR(H80/H90,"") -> 1.9702924 | I96: =+IFERROR(I80/I90,"") -> 2.032968 | J96: =+IFERROR(J80/J90,"") -> 2.0975239 | K96: =+IFERROR(K80/K90,"") -> 2.1640164 | L96: =+IFERROR(L80/L90,"") -> 2.2325037 | M96: =+IFERROR(M80/M90,"") -> 2.3030456 | ... O96: =+IFERROR(O80/O90,"") -> 2.4505417
C97: DSCR (CFO) | F97: =+IFERROR(F88/F90,"") -> 1.8503646 | G97: =+IFERROR(G88/G90,"") -> 1.9094424 | H97: =+IFERROR(H88/H90,"") -> 1.9702924 | I97: =+IFERROR(I88/I90,"") -> 2.032968 | J97: =+IFERROR(J88/J90,"") -> 2.0975239 | K97: =+IFERROR(K88/K90,"") -> 2.1640164 | L97: =+IFERROR(L88/L90,"") -> 2.2325037 | M97: =+IFERROR(M88/M90,"") -> 2.3030456 | ... O97: =+IFERROR(O88/O90,"") -> 2.4505417
C98: Debt Yield (CFO) | F98: =+F88/Dashboard!$I$10 -> 0.1202737 | G98: =+G88/Dashboard!$I$10 -> 0.12411375 | H98: =+H88/Dashboard!$I$10 -> 0.12806901 | I98: =+I88/Dashboard!$I$10 -> 0.13214292 | J98: =+J88/Dashboard!$I$10 -> 0.13633905 | K98: =+K88/Dashboard!$I$10 -> 0.14066107 | L98: =+L88/Dashboard!$I$10 -> 0.14511274 | M98: =+M88/Dashboard!$I$10 -> 0.14969796 | ... O98: =+O88/Dashboard!$I$10 -> 0.15928521
C99: Break-Even Ratio | F99: =+SUM(F96,F78)/F12 -> 0.44736605 | G99: =+SUM(G96,G78)/G12 -> 0.44633181 | H99: =+SUM(H96,H78)/H12 -> 0.44532769 | I99: =+SUM(I96,I78)/I12 -> 0.44435282 | J99: =+SUM(J96,J78)/J12 -> 0.44340634 | K99: =+SUM(K96,K78)/K12 -> 0.44248743 | L99: =+SUM(L96,L78)/L12 -> 0.44159528 | M99: =+SUM(M96,M78)/M12 -> 0.44072911 | ... O99: =+SUM(O96,O78)/O12 -> 0.43907174
C101: Cap Rate (Purchase Price) | F101: =+F80/Dashboard!$E$32 -> 0.078177905 | G101: =+G80/Dashboard!$E$32 -> 0.080673939 | H101: =+H80/Dashboard!$E$32 -> 0.083244855 | I101: =+I80/Dashboard!$E$32 -> 0.085892899 | J101: =+J80/Dashboard!$E$32 -> 0.088620383 | K101: =+K80/Dashboard!$E$32 -> 0.091429692 | L101: =+L80/Dashboard!$E$32 -> 0.094323281 | M101: =+M80/Dashboard!$E$32 -> 0.097303677 | ... O101: =+O80/Dashboard!$E$32 -> 0.10353539
C102: Operating Cash Flow Before Taxes | F102: =+F80-F90-F91 -> 154489.99 | G102: =+G80-G90-G91 -> 165222.94 | H102: =+H80-H90-H91 -> 176277.88 | I102: =+I80-I90-I91 -> 187664.46 | J102: =+J80-J90-J91 -> 199392.65 | K102: =+K80-K90-K91 -> 211472.68 | L102: =+L80-L90-L91 -> 223915.11 | M102: =+M80-M90-M91 -> 236730.81 | ... O102: =+O80-O90-O91 -> 206492.24
C103: Cash on Cash Return | F103: =+F102/Dashboard!$I$11 -> 0.08474492 | G103: =+G102/Dashboard!$I$11 -> 0.090632441 | H103: =+H102/Dashboard!$I$11 -> 0.096696587 | I103: =+I102/Dashboard!$I$11 -> 0.10294266 | J103: =+J102/Dashboard!$I$11 -> 0.10937611 | K103: =+K102/Dashboard!$I$11 -> 0.11600257 | L103: =+L102/Dashboard!$I$11 -> 0.12282782 | M103: =+M102/Dashboard!$I$11 -> 0.12985782 | ... O103: =+O102/Dashboard!$I$11 -> 0.11327056
C104: General Partner Cash Return | D104: =+Dashboard!J58 -> 0.25 | F104: =+F102*$D$104 -> 38622.497 | G104: =+G102*$D$104 -> 41305.735 | H104: =+H102*$D$104 -> 44069.469 | I104: =+I102*$D$104 -> 46916.116 | J104: =+J102*$D$104 -> 49848.162 | K104: =+K102*$D$104 -> 52868.169 | L104: =+L102*$D$104 -> 55978.777 | M104: =+M102*$D$104 -> 59182.703 | ... O104: =+O102*$D$104 -> 51623.059
C105: Total Limited Partner Cash Return | D105: =+Dashboard!J59 -> 0.75 | F105: =+F102*$D$105 -> 115867.49 | G105: =+G102*$D$105 -> 123917.2 | H105: =+H102*$D$105 -> 132208.41 | I105: =+I102*$D$105 -> 140748.35 | J105: =+J102*$D$105 -> 149544.49 | K105: =+K102*$D$105 -> 158604.51 | L105: =+L102*$D$105 -> 167936.33 | M105: =+M102*$D$105 -> 177548.11 | ... O105: =+O102*$D$105 -> 154869.18
C106: Cash on Cash LP Return | F106: =+F105/Dashboard!$I$11 -> 0.06355869 | G106: =+G105/Dashboard!$I$11 -> 0.067974331 | H106: =+H105/Dashboard!$I$11 -> 0.07252244 | I106: =+I105/Dashboard!$I$11 -> 0.077206993 | J106: =+J105/Dashboard!$I$11 -> 0.082032082 | K106: =+K105/Dashboard!$I$11 -> 0.087001924 | L106: =+L105/Dashboard!$I$11 -> 0.092120862 | M106: =+M105/Dashboard!$I$11 -> 0.097393367 | ... O106: =+O105/Dashboard!$I$11 -> 0.084952922
C108: Return Metrics
C110: 5 Year Hold IRR | E110: =+'Scenario 0'!E111 -> Year 0 | F110: =+'Scenario 0'!F111 -> 1 | G110: =+'Scenario 0'!G111 -> 2 | H110: =+'Scenario 0'!H111 -> 3 | I110: =+'Scenario 0'!I111 -> 4 | J110: =+'Scenario 0'!J111 -> 5
C112: Exit Cap Rate Assumption | D112: =+Dashboard!$J$54 -> 0.06
C114: Project Cash Flows (Unleveraged IRR):
C115: (+) Proceeds from Sale of Property: | F115: 0 | G115: 0 | H115: 0 | I115: 0 | J115: =+J$80/D$112 -> 6351127.5
C116: (-) Selling Costs: | D116: =+Dashboard!$J$55 -> 0.015 | F116: 0 | G116: 0 | H116: 0 | I116: 0 | J116: =-J$115*D$116 -> -95266.912
C117: (+) Adjusted NOI (Cash Flows to All Investors): | F117: =+F$88 -> 336164.99 | G117: =+G$88 -> 346897.94 | H117: =+H$88 -> 357952.88 | I117: =+I$88 -> 369339.46 | J117: =+J$88 -> 381067.65
C118: (-) Property Acquisition Price: | E118: =-Dashboard!$E$32 -> -4300000 | F118: 0 | G118: 0 | H118: 0 | I118: 0 | J118: 0
C119: Total Project Cash Flows (Unleveraged IRR): | E119: =SUM(E115:E118) -> -4300000 | F119: =SUM(F115:F118) -> 336164.99 | G119: =SUM(G115:G118) -> 346897.94 | H119: =SUM(H115:H118) -> 357952.88 | I119: =SUM(I115:I118) -> 369339.46 | J119: =SUM(J115:J118) -> 6636928.2
F120: =+F119-F115 -> 336164.99 | G120: =+G119-G115 -> 346897.94 | H120: =+H119-H115 -> 357952.88 | I120: =+I119-I115 -> 369339.46 | J120: =+J119-J115 -> 285800.74
C122: Unlevered IRR: | E122: =+IRR(E119:J119) -> 0.1500536
C123: Unlevered Cash-on-Cash Multiple: | E123: =+SUM(F115:J117)/-SUM(E118:J118) -> 1.8714613
C125: Cash Flow to Equity Investors (Leveraged IRR):
C126: (+) Proceeds from Sale of Property: | F126: 0 | G126: 0 | H126: 0 | I126: 0 | J126: =+J$80/D$112 -> 6351127.5
...

Sheet Scenario 3
C1: Underwriting Model Scenario 3
D3: Year | E3: =+'Scenario 0'!E3 -> 2024 | F3: =+'Scenario 0'!F3 -> 2025 | G3: =+'Scenario 0'!G3 -> 2026 | H3: =+'Scenario 0'!H3 -> 2027 | I3: =+'Scenario 0'!I3 -> 2028 | J3: =+'Scenario 0'!J3 -> 2029 | K3: =+'Scenario 0'!K3 -> 2030 | L3: =+'Scenario 0'!L3 -> 2031 | ... O3: =+'Scenario 0'!O3 -> 2034
C4: =+'Unit Mix'!AD3 -> Scenario 3 ( Max Current Vouchers + NET LIHTC)
C6: Income Statement | E6: =+'Scenario 0'!E6 -> T12 | F6: =+'Scenario 0'!F6 -> 1 | G6: =+'Scenario 0'!G6 -> 2 | H6: =+'Scenario 0'!H6 -> 3 | I6: =+'Scenario 0'!I6 -> 4 | J6: =+'Scenario 0'!J6 -> 5 | K6: =+'Scenario 0'!K6 -> 6 | L6: =+'Scenario 0'!L6 -> 7 | ... O6: =+'Scenario 0'!O6 -> 10
C7: Gross Potential Income | E7: =+'Scenario 0'!$E$7 -> 1561954 | F7: =+'Unit Mix'!AI26 -> 656580 | G7: =+'Unit Mix'!AI49 -> 676277.4 | H7: =+'Unit Mix'!AI72 -> 696565.72 | I7: =+'Unit Mix'!AI95 -> 717462.69 | J7: =+'Unit Mix'!AI118 -> 738986.57 | K7: =+'Unit Mix'!AI141 -> 761156.17 | L7: =+'Unit Mix'!AI164 -> 783990.86 | M7: =+'Unit Mix'!AI187 -> 807510.58 | N7: =+'Unit Mix'!AI210 -> 831735.9 | O7: =+'Unit Mix'!AI233 -> 856687.98
C8: Vacancy Factor | D8: =+Dashboard!$P$10 -> 0.05 | E8: =+'Scenario 0'!$E$8 -> 48058 | F8: =+F7*$D$8 -> 32829 | G8: =+G7*$D$8 -> 33813.87 | H8: =+H7*$D$8 -> 34828.286 | I8: =+I7*$D$8 -> 35873.135 | J8: =+J7*$D$8 -> 36949.329 | K8: =+K7*$D$8 -> 38057.809 | L8: =+L7*$D$8 -> 39199.543 | M8: =+M7*$D$8 -> 40375.529 | ... O8: =+O7*$D$8 -> 42834.399
C9: Net Rental Income | E9: =+E7-E8 -> 1513896 | F9: =+F7-F8 -> 623751 | G9: =+G7-G8 -> 642463.53 | H9: =+H7-H8 -> 661737.44 | I9: =+I7-I8 -> 681589.56 | J9: =+J7-J8 -> 702037.25 | K9: =+K7-K8 -> 723098.36 | L9: =+L7-L8 -> 744791.31 | ... O9: =+O7-O8 -> 813853.58
C11: Laundry and Other Income | D11: =+Dashboard!$P$14 -> 0.025 | E11: =+'Scenario 0'!$E$11 -> 33716 | F11: =+Dashboard!$O$14 -> 0 | G11: =+F11*(1+$D11) -> 0 | H11: =+G11*(1+$D11) -> 0 | I11: =+H11*(1+$D11) -> 0 | J11: =+I11*(1+$D11) -> 0 | K11: =+J11*(1+$D11) -> 0 | L11: =+K11*(1+$D11) -> 0 | M11: =+L11*(1+$D11) -> 0 | N11: =+M11*(1+$D11) -> 0 | O11: =+N11*(1+$D11) -> 0
C12: Total Gross Income | E12: =+SUM(E9:E11) -> 1547612 | F12: =+SUM(F9:F11) -> 623751 | G12: =+SUM(G9:G11) -> 642463.53 | H12: =+SUM(H9:H11) -> 661737.44 | I12: =+SUM(I9:I11) -> 681589.56 | J12: =+SUM(J9:J11) -> 702037.25 | K12: =+SUM(K9:K11) -> 723098.36 | L12: =+SUM(L9:L11) -> 744791.31 | ... O12: =+SUM(O9:O11) -> 813853.58
C13: Gross Income Growth | E13: -- | F13: =+F12/E12-1 -> -0.59695906 | G13: =+G12/F12-1 -> 0.03 | H13: =+H12/G12-1 -> 0.03 | I13: =+I12/H12-1 -> 0.03 | J13: =+J12/I12-1 -> 0.03 | K13: =+K12/J12-1 -> 0.03 | L13: =+L12/K12-1 -> 0.03 | M13: =+M12/L12-1 -> 0.03 | ... O13: =+O12/N12-1 -> 0.03
C15: Opertating Expenses
A17: BAD
C18: Bad Debt | E18: =+'Scenario 0'!E18 -> 0 | F18: =+'Scenario 0'!F18 -> 0 | G18: =+'Scenario 0'!G18 -> 0 | H18: =+'Scenario 0'!H18 -> 0 | I18: =+'Scenario 0'!I18 -> 0 | J18: =+'Scenario 0'!J18 -> 0 | K18: =+'Scenario 0'!K18 -> 0 | L18: =+'Scenario 0'!L18 -> 0 | ... O18: =+'Scenario 0'!O18 -> 0
A20: RES
A21: COM
C22: Total Replacement Reserves | E22: =+'Scenario 0'!E22 -> 21600 | F22: =+'Scenario 0'!F22 -> 21600 | G22: =+'Scenario 0'!G22 -> 21600 | H22: =+'Scenario 0'!H22 -> 21600 | I22: =+'Scenario 0'!I22 -> 21600 | J22: =+'Scenario 0'!J22 -> 21600 | K22: =+'Scenario 0'!K22 -> 21600 | L22: =+'Scenario 0'!L22 -> 21600 | ... O22: =+'Scenario 0'!O22 -> 21600
A24: MAN
A25: ASS
A26: PAY
A27: MAIT
C28: Payroll | E28: =+'Scenario 0'!E29 -> 0 | F28: =+'Scenario 0'!F29 -> 126720 | G28: =+'Scenario 0'!G29 -> 130521.6 | H28: =+'Scenario 0'!H29 -> 134437.25 | I28: =+'Scenario 0'!I29 -> 138470.37 | J28: =+'Scenario 0'!J29 -> 142624.48 | K28: =+'Scenario 0'!K29 -> 146903.21 | L28: =+'Scenario 0'!L29 -> 151310.31 | ... O28: =+'Scenario 0'!O29 -> 165340.86
A30: MGMT
A31: LEGAL
A32: OFF
A33: TRAVEL
A34: AUD
A35: ADV
A36: TRAIN
A37: BANK
A38: BOOK
A39: PAYSERV
A40: UNIT
A41: MISCAD
C42: Admin Expenses | E42: =+'Scenario 0'!E43 -> 0 | F42: =+'Scenario 0'!F43 -> 59499.61 | G42: =+'Scenario 0'!G43 -> 61284.598 | H42: =+'Scenario 0'!H43 -> 63123.136 | I42: =+'Scenario 0'!I43 -> 65016.83 | J42: =+'Scenario 0'!J43 -> 66967.335 | K42: =+'Scenario 0'!K43 -> 68976.355 | L42: =+'Scenario 0'!L43 -> 71045.646 | ... O42: =+'Scenario 0'!O43 -> 77633.496
A44: ELEC
A45: VAC
A46: WS
A47: GAS
A48: CABLE
A49: TRASH
C50: Utility Expenses | E50: =+'Scenario 0'!E51 -> 0 | F50: =+'Scenario 0'!F51 -> 0 | G50: =+'Scenario 0'!G51 -> 0 | H50: =+'Scenario 0'!H51 -> 0 | I50: =+'Scenario 0'!I51 -> 0 | J50: =+'Scenario 0'!J51 -> 0 | K50: =+'Scenario 0'!K51 -> 0 | L50: =+'Scenario 0'!L51 -> 0 | ... O50: =+'Scenario 0'!O51 -> 0
A52: RM
A53: TURN
A54: SUPP
A55: APP
A56: HP
A57: CONC
C58: Operating and Maint. | E58: =+'Scenario 0'!E59 -> 0 | F58: =+'Scenario 0'!F59 -> 15060 | G58: =+'Scenario 0'!G59 -> 15511.8 | H58: =+'Scenario 0'!H59 -> 15977.154 | I58: =+'Scenario 0'!I59 -> 16456.469 | J58: =+'Scenario 0'!J59 -> 16950.163 | K58: =+'Scenario 0'!K59 -> 17458.668 | L58: =+'Scenario 0'!L59 -> 17982.428 | ... O58: =+'Scenario 0'!O59 -> 19649.884
A60: LAND
A61: FIRE
A62: SEC
A63: PEST
A64: CON
A65: ELEV
A66: SNOW
A67: MISCOP
C68: Contract Expenses | E68: =+'Scenario 0'!E69 -> 0 | F68: =+'Scenario 0'!F69 -> 0 | G68: =+'Scenario 0'!G69 -> 0 | H68: =+'Scenario 0'!H69 -> 0 | I68: =+'Scenario 0'!I69 -> 0 | J68: =+'Scenario 0'!J69 -> 0 | K68: =+'Scenario 0'!K69 -> 0 | L68: =+'Scenario 0'!L69 -> 0 | ... O68: =+'Scenario 0'!O69 -> 0
A70: RETAX
A71: INS
A72: WORKCOMP
A73: HEALTH
A74: PTAX
A75: MISCTAX
C76: Total Taxes and Insurance Expenses | E76: =+'Scenario 0'!E77 -> 0 | F76: =+'Scenario 0'!F77 -> 49248 | G76: =+'Scenario 0'!G77 -> 50725.44 | H76: =+'Scenario 0'!H77 -> 52247.203 | I76: =+'Scenario 0'!I77 -> 53814.619 | J76: =+'Scenario 0'!J77 -> 55429.058 | K76: =+'Scenario 0'!K77 -> 57091.93 | L76: =+'Scenario 0'!L77 -> 58804.687 | ... O76: =+'Scenario 0'!O77 -> 64257.47
C78: Total Operating Expenses | E78: =+SUM(E18,E22,E28,E42,E50,E58,E68,E76,) -> 21600 | F78: =+SUM(F18,F22,F28,F42,F50,F58,F68,F76,) -> 272127.61 | G78: =+SUM(G18,G22,G28,G42,G50,G58,G68,G76,) -> 279643.44 | H78: =+SUM(H18,H22,H28,H42,H50,H58,H68,H76,) -> 287384.74 | I78: =+SUM(I18,I22,I28,I42,I50,I58,I68,I76,) -> 295358.28 | J78: =+SUM(J18,J22,J28,J42,J50,J58,J68,J76,) -> 303571.03 | K78: =+SUM(K18,K22,K28,K42,K50,K58,K68,K76,) -> 312030.16 | L78: =+SUM(L18,L22,L28,L42,L50,L58,L68,L76,) -> 320743.07 | ... O78: =+SUM(O18,O22,O28,O42,O50,O58,O68,O76,) -> 348481.71
C80: Net Operating Income | E80: =+E12-E78 -> 1526012 | F80: =+F12-F78 -> 351623.39 | G80: =+G12-G78 -> 362820.09 | H80: =+H12-H78 -> 374352.69 | I80: =+I12-I78 -> 386231.28 | J80: =+J12-J78 -> 398466.21 | K80: =+K12-K78 -> 411068.2 | L80: =+L12-L78 -> 424048.25 | ... O80: =+O12-O78 -> 465371.87
C81: NOI Margin | E81: =+IFERROR(E80/E12,"--") -> 0.98604301 | F81: =+F80/F12 -> 0.56372397 | G81: =+G80/G12 -> 0.56473259 | H81: =+H80/H12 -> 0.56571183 | I81: =+I80/I12 -> 0.56666255 | J81: =+J80/J12 -> 0.56758557 | K81: =+K80/K12 -> 0.56848172 | L81: =+L80/L12 -> 0.56935176 | M81: =+M80/M12 -> 0.57019646 | ... O81: =+O80/O12 -> 0.57181277
C83: Capital Expenditures
C84: Other CapEx
C85: Capital Reserve
C86: Total Capital Expenditures | E86: =+SUM(E84:E85) -> 0 | F86: =+SUM(F84:F85) -> 0 | G86: =+SUM(G84:G85) -> 0 | H86: =+SUM(H84:H85) -> 0 | I86: =+SUM(I84:I85) -> 0 | J86: =+SUM(J84:J85) -> 0 | K86: =+SUM(K84:K85) -> 0 | L86: =+SUM(L84:L85) -> 0 | ... O86: =+SUM(O84:O85) -> 0
C88: Cash Flow from Operations (Adj. NOI) | E88: =+E80-E86 -> 1526012 | F88: =+F80-F86 -> 351623.39 | G88: =+G80-G86 -> 362820.09 | H88: =+H80-H86 -> 374352.69 | I88: =+I80-I86 -> 386231.28 | J88: =+J80-J86 -> 398466.21 | K88: =+K80-K86 -> 411068.2 | L88: =+L80-L86 -> 424048.25 | ... O88: =+O80-O86 -> 465371.87
C90: Debt Service | E90: -- | F90: =+Dashboard!$I$10*Dashboard!$E$50 -> 181675 | G90: =+F90 -> 181675 | H90: =+G90 -> 181675 | I90: =+H90 -> 181675 | J90: =+I90 -> 181675 | K90: =+J90 -> 181675 | L90: =+K90 -> 181675 | M90: =+L90 -> 181675 | N90: =+M90 -> 181675 | O90: =+N90 -> 181675
C91: Principal Repayment | E91: -- | F91: =IF(F$6<=Dashboard!$E$56,0,-PPMT(Dashboard!$E$50,'Scenario 3'!F3-'Scenario 3'!$E3,Dashboard!$E$55,Dashboard!$D$49)) -> 0 | G91: =IF(G$6<=Dashboard!$E$56,0,-PPMT(Dashboard!$E$50,'Scenario 3'!G3-'Scenario 3'!$E3,Dashboard!$E$55,Dashboard!$D$49)) -> 0 | H91: =IF(H$6<=Dashboard!$E$56,0,-PPMT(Dashboard!$E$50,'Scenario 3'!H3-'Scenario 3'!$E3,Dashboard!$E$55,Dashboard!$D$49)) -> 0 | I91: =IF(I$6<=Dashboard!$E$56,0,-PPMT(Dashboard!$E$50,'Scenario 3'!I3-'Scenario 3'!$E3,Dashboard!$E$55,Dashboard!$D$49)) -> 0 | J91: =IF(J$6<=Dashboard!$E$56,0,-PPMT(Dashboard!$E$50,'Scenario 3'!J3-'Scenario 3'!$E3,Dashboard!$E$55,Dashboard!$D$49)) -> 0 | K91: =IF(K$6<=Dashboard!$E$56,0,-PPMT(Dashboard!$E$50,'Scenario 3'!K3-'Scenario 3'!$E3,Dashboard!$E$55,Dashboard!$D$49)) -> 0 | L91: =IF(L$6<=Dashboard!$E$56,0,-PPMT(Dashboard!$E$50,'Scenario 3'!L3-'Scenario 3'!$E3,Dashboard!$E$55,Dashboard!$D$49)) -> 0 | M91: =IF(M$6<=Dashboard!$E$56,0,-PPMT(Dashboard!$E$50,'Scenario 3'!M3-'Scenario 3'!$E3,Dashboard!$E$55,Dashboard!$D$49)) -> 0 | ... O91: =IF(O$6<=Dashboard!$E$56,0,-PPMT(Dashboard!$E$50,'Scenario 3'!O3-'Scenario 3'!$E3,Dashboard!$E$55,Dashboard!$D$49)) -> 57034.929
C92: Cash Flow After Financing (CF to Equity Investors) | E92: -- | F92: =+F88-F90 -> 169948.39 | G92: =+G88-G90 -> 181145.09 | H92: =+H88-H90 -> 192677.69 | I92: =+I88-I90 -> 204556.28 | J92: =+J88-J90 -> 216791.21 | K92: =+K88-K90 -> 229393.2 | L92: =+L88-L90 -> 242373.25 | M92: =+M88-M90 -> 255742.69 | ... O92: =+O88-O90 -> 283696.87
C94: Ending Debt Balance | F94: =+Dashboard!$D$49-SUM('Scenario 3'!$F$91:F91) -> 2795000 | G94: =+Dashboard!$D$49-SUM('Scenario 3'!$F$91:G91) -> 2795000 | H94: =+Dashboard!$D$49-SUM('Scenario 3'!$F$91:H91) -> 2795000 | I94: =+Dashboard!$D$49-SUM('Scenario 3'!$F$91:I91) -> 2795000 | J94: =+Dashboard!$D$49-SUM('Scenario 3'!$F$91:J91) -> 2795000 | K94: =+Dashboard!$D$49-SUM('Scenario 3'!$F$91:K91) -> 2795000 | L94: =+Dashboard!$D$49-SUM('Scenario 3'!$F$91:L91) -> 2795000 | M94: =+Dashboard!$D$49-SUM('Scenario 3'!$F$91:M91) -> 2795000 | ... O94: =+Dashboard!$D$49-SUM('Scenario 3'!$F$91:O91) -> 2684411.1
C96: DSCR (NOI) | F96: =+IFERROR(F80/F90,"") -> 1.9354528 | G96: =+IFERROR(G80/G90,"") -> 1.9970832 | H96: =+IFERROR(H80/H90,"") -> 2.0605625 | I96: =+IFERROR(I80/I90,"") -> 2.1259462 | J96: =+IFERROR(J80/J90,"") -> 2.1932914 | K96: =+IFERROR(K80/K90,"") -> 2.2626569 | L96: =+IFERROR(L80/L90,"") -> 2.3341035 | M96: =+IFERROR(M80/M90,"") -> 2.4076934 | ... O96: =+IFERROR(O80/O90,"") -> 2.5615625
C97: DSCR (CFO) | F97: =+IFERROR(F88/F90,"") -> 1.9354528 | G97: =+IFERROR(G88/G90,"") -> 1.9970832 | H97: =+IFERROR(H88/H90,"") -> 2.0605625 | I97: =+IFERROR(I88/I90,"") -> 2.1259462 | J97: =+IFERROR(J88/J90,"") -> 2.1932914 | K97: =+IFERROR(K88/K90,"") -> 2.2626569 | L97: =+IFERROR(L88/L90,"") -> 2.3341035 | M97: =+IFERROR(M88/M90,"") -> 2.4076934 | ... O97: =+IFERROR(O88/O90,"") -> 2.5615625
C98: Debt Yield (CFO) | F98: =+F88/Dashboard!$I$10 -> 0.12580443 | G98: =+G88/Dashboard!$I$10 -> 0.12981041 | H98: =+H88/Dashboard!$I$10 -> 0.13393656 | I98: =+I88/Dashboard!$I$10 -> 0.1381865 | J98: =+J88/Dashboard!$I$10 -> 0.14256394 | K98: =+K88/Dashboard!$I$10 -> 0.1470727 | L98: =+L88/Dashboard!$I$10 -> 0.15171672 | M98: =+M88/Dashboard!$I$10 -> 0.15650007 | ... O98: =+O88/Dashboard!$I$10 -> 0.16650156
C99: Break-Even Ratio | F99: =+SUM(F96,F78)/F12 -> 0.43627913 | G99: =+SUM(G96,G78)/G12 -> 0.43527052 | H99: =+SUM(H96,H78)/H12 -> 0.43429129 | I99: =+SUM(I96,I78)/I12 -> 0.43334057 | J99: =+SUM(J96,J78)/J12 -> 0.43241755 | K99: =+SUM(K96,K78)/K12 -> 0.43152141 | L99: =+SUM(L96,L78)/L12 -> 0.43065137 | M99: =+SUM(M96,M78)/M12 -> 0.42980668 | ... O99: =+SUM(O96,O78)/O12 -> 0.42819038
C101: Cap Rate (Purchase Price) | F101: =+F80/Dashboard!$E$32 -> 0.081772881 | G101: =+G80/Dashboard!$E$32 -> 0.084376766 | H101: =+H80/Dashboard!$E$32 -> 0.087058766 | I101: =+I80/Dashboard!$E$32 -> 0.089821227 | J101: =+J80/Dashboard!$E$32 -> 0.092666561 | K101: =+K80/Dashboard!$E$32 -> 0.095597256 | L101: =+L80/Dashboard!$E$32 -> 0.098615871 | M101: =+M80/Dashboard!$E$32 -> 0.10172504 | ... O101: =+O80/Dashboard!$E$32 -> 0.10822602
C102: Operating Cash Flow Before Taxes | F102: =+F80-F90-F91 -> 169948.39 | G102: =+G80-G90-G91 -> 181145.09 | H102: =+H80-H90-H91 -> 192677.69 | I102: =+I80-I90-I91 -> 204556.28 | J102: =+J80-J90-J91 -> 216791.21 | K102: =+K80-K90-K91 -> 229393.2 | L102: =+L80-L90-L91 -> 242373.25 | M102: =+M80-M90-M91 -> 255742.69 | ... O102: =+O80-O90-O91 -> 226661.94
C103: Cash on Cash Return | F103: =+F102/Dashboard!$I$11 -> 0.093224569 | G103: =+G102/Dashboard!$I$11 -> 0.099366479 | H103: =+H102/Dashboard!$I$11 -> 0.10569265 | I103: =+I102/Dashboard!$I$11 -> 0.1122086 | J103: =+J102/Dashboard!$I$11 -> 0.11892003 | K103: =+K102/Dashboard!$I$11 -> 0.1258328 | L103: =+L102/Dashboard!$I$11 -> 0.13295296 | M103: =+M102/Dashboard!$I$11 -> 0.14028672 | ... O103: =+O102/Dashboard!$I$11 -> 0.12433458
C104: General Partner Cash Return | D104: =+Dashboard!J58 -> 0.25 | F104: =+F102*$D$104 -> 42487.098 | G104: =+G102*$D$104 -> 45286.273 | H104: =+H102*$D$104 -> 48169.424 | I104: =+I102*$D$104 -> 51139.069 | J104: =+J102*$D$104 -> 54197.803 | K104: =+K102*$D$104 -> 57348.3 | L104: =+L102*$D$104 -> 60593.311 | M104: =+M102*$D$104 -> 63935.673 | ... O104: =+O102*$D$104 -> 56665.485
C105: Total Limited Partner Cash Return | D105: =+Dashboard!J59 -> 0.75 | F105: =+F102*$D$105 -> 127461.29 | G105: =+G102*$D$105 -> 135858.82 | H105: =+H102*$D$105 -> 144508.27 | I105: =+I102*$D$105 -> 153417.21 | J105: =+J102*$D$105 -> 162593.41 | K105: =+K102*$D$105 -> 172044.9 | L105: =+L102*$D$105 -> 181779.93 | M105: =+M102*$D$105 -> 191807.02 | ... O105: =+O102*$D$105 -> 169996.46
C106: Cash on Cash LP Return | F106: =+F105/Dashboard!$I$11 -> 0.069918427 | G106: =+G105/Dashboard!$I$11 -> 0.074524859 | H106: =+H105/Dashboard!$I$11 -> 0.079269485 | I106: =+I105/Dashboard!$I$11 -> 0.084156449 | J106: =+J105/Dashboard!$I$11 -> 0.089190022 | K106: =+K105/Dashboard!$I$11 -> 0.094374602 | L106: =+L105/Dashboard!$I$11 -> 0.09971472 | M106: =+M105/Dashboard!$I$11 -> 0.10521504 | ... O106: =+O105/Dashboard!$I$11 -> 0.093250936
C108: Return Metrics
C110: 5 Year Hold IRR | E110: =+'Scenario 0'!E111 -> Year 0 | F110: =+'Scenario 0'!F111 -> 1 | G110: =+'Scenario 0'!G111 -> 2 | H110: =+'Scenario 0'!H111 -> 3 | I110: =+'Scenario 0'!I111 -> 4 | J110: =+'Scenario 0'!J111 -> 5
C112: Exit Cap Rate Assumption | D112: =+Dashboard!$J$54 -> 0.06
C114: Project Cash Flows (Unleveraged IRR):
C115: (+) Proceeds from Sale of Property: | F115: 0 | G115: 0 | H115: 0 | I115: 0 | J115: =+J$80/D$112 -> 6641103.6
C116: (-) Selling Costs: | D116: =+Dashboard!$J$55 -> 0.015 | F116: 0 | G116: 0 | H116: 0 | I116: 0 | J116: =-J$115*D$116 -> -99616.553
C117: (+) Adjusted NOI (Cash Flows to All Investors): | F117: =+F$88 -> 351623.39 | G117: =+G$88 -> 362820.09 | H117: =+H$88 -> 374352.69 | I117: =+I$88 -> 386231.28 | J117: =+J$88 -> 398466.21
C118: (-) Property Acquisition Price: | E118: =-Dashboard!$E$32 -> -4300000 | F118: 0 | G118: 0 | H118: 0 | I118: 0 | J118: 0
C119: Total Project Cash Flows (Unleveraged IRR): | E119: =SUM(E115:E118) -> -4300000 | F119: =SUM(F115:F118) -> 351623.39 | G119: =SUM(G115:G118) -> 362820.09 | H119: =SUM(H115:H118) -> 374352.69 | I119: =SUM(I115:I118) -> 386231.28 | J119: =SUM(J115:J118) -> 6939953.2
F120: =+F119-F115 -> 351623.39 | G120: =+G119-G115 -> 362820.09 | H120: =+H119-H115 -> 374352.69 | I120: =+I119-I115 -> 386231.28 | J120: =+J119-J115 -> 298849.66
C122: Unlevered IRR: | E122: =+IRR(E119:J119) -> 0.16185258
C123: Unlevered Cash-on-Cash Multiple: | E123: =+SUM(F115:J117)/-SUM(E118:J118) -> 1.9569722
C125: Cash Flow to Equity Investors (Leveraged IRR):
C126: (+) Proceeds from Sale of Property: | F126: 0 | G126: 0 | H126: 0 | I126: 0 | J126: =+J$80/D$112 -> 6641103.6
...

Sheet Rent Roll Calcs -->

Sheet Unit Mix
B3: Scenario 0 (No Change to Asset) | P3: Scenario 1 ( Max Current Vouchers) | W3: Scenario 2 (Max Net LIHTC) | AD3: Scenario 3 ( Max Current Vouchers + NET LIHTC)
B5: Year 1 | P5: =+$B5 -> Year 1 | W5: =+$B5 -> Year 1 | AD5: =+$B5 -> Year 1
B6: Unit Type | C6: AMI / S8 | D6: # of Units | E6: Avg. SF | F6: Avg. Utilities | G6: Avg. Max LITHC | H6: Net LIHTC | I6: Avg. Max FMR | J6: Net FMR | K6: CoStar Rent | L6: Gross Rent | M6: Avg. Current Rent | N6: Yrly. Gross Income (Net Rent) | P6: Unit Type | Q6: AMI / S8 | R6: # of Units | S6: Avg. SF | T6: Avg. Utilities | U6: Max Current Vouchers | W6: Unit Type | X6: AMI / S8 | Y6: # of Units | Z6: Avg. SF | AA6: Avg. Utilities | AB6: Max NET LIHTC | AD6: Unit Type | AE6: AMI / S8 | AF6: # of Units | AG6: Avg. SF | AH6: Avg. Utilities | AI6: Max Current Vouchers + NET LIHTC
B7: ='Rent Roll'!C13 -> 1x1 | C7: ='Rent Roll'!D13 -> 50% AMI | D7: ='Rent Roll'!E13 -> 2 | E7: ='Rent Roll'!F13 -> 701 | F7: ='Rent Roll'!K13 -> 65 | G7: ='Rent Roll'!M13 -> 651 | H7: =+G7-F7 -> 586 | I7: ='Rent Roll'!O13 -> 683 | J7: =I7-F7 -> 618 | K7: ='Rent Roll'!G13 -> 0 | L7: ='Rent Roll'!L13 -> 592 | M7: ='Rent Roll'!J13 -> 527 | N7: =((M7*D7)*12) -> 12648 | P7: =B7 -> 1x1 | Q7: =C7 -> 50% AMI | R7: =D7 -> 2 | S7: =E7 -> 701 | T7: =F7 -> 65 | U7: =((M7*R7)*12) -> 12648 | W7: =B7 -> 1x1 | X7: =C7 -> 50% AMI | Y7: =D7 -> 2 | Z7: =E7 -> 701 | AA7: =F7 -> 65 | AB7: =((H7*Y7)*12) -> 14064 | AD7: =B7 -> 1x1 | AE7: =C7 -> 50% AMI | AF7: =D7 -> 2 | AG7: =E7 -> 701 | AH7: =F7 -> 65 | AI7: =+MAX(U7,AB7) -> 14064
B8: ='Rent Roll'!C14 -> 1x1 | C8: ='Rent Roll'!D14 -> 60% AMI | D8: ='Rent Roll'!E14 -> 0 | E8: ='Rent Roll'!F14 -> 701 | F8: ='Rent Roll'!K14 -> 65 | G8: ='Rent Roll'!M14 -> 781 | H8: =+G8-F8 -> 716 | I8: ='Rent Roll'!O14 -> 683 | J8: =I8-F8 -> 618 | K8: ='Rent Roll'!G14 -> 0 | L8: ='Rent Roll'!L14 -> 65 | M8: ='Rent Roll'!J14 -> 0 | N8: =((M8*D8)*12) -> 0 | P8: =B8 -> 1x1 | Q8: =C8 -> 60% AMI | R8: =D8 -> 0 | S8: =E8 -> 701 | T8: =F8 -> 65 | U8: =((M8*R8)*12) -> 0 | W8: =B8 -> 1x1 | X8: =C8 -> 60% AMI | Y8: =D8 -> 0 | Z8: =E8 -> 701 | AA8: =F8 -> 65 | AB8: =((H8*Y8)*12) -> 0 | AD8: =B8 -> 1x1 | AE8: =C8 -> 60% AMI | AF8: =D8 -> 0 | AG8: =E8 -> 701 | AH8: =F8 -> 65 | AI8: =+MAX(U8,AB8) -> 0
B9: ='Rent Roll'!C15 -> 1x1 | C9: ='Rent Roll'!D15 -> Market | D9: ='Rent Roll'!E15 -> 1 | E9: ='Rent Roll'!F15 -> 701 | F9: ='Rent Roll'!K15 -> 0 | G9: ='Rent Roll'!M15 -> 0 | H9: =+G9-F9 -> 0 | I9: ='Rent Roll'!O15 -> 683 | J9: =I9-F9 -> 683 | K9: ='Rent Roll'!G15 -> 0 | L9: ='Rent Roll'!L15 -> 593 | M9: ='Rent Roll'!J15 -> 593 | N9: =((M9*D9)*12) -> 7116 | P9: =B9 -> 1x1 | Q9: =C9 -> Market | R9: =D9 -> 1 | S9: =E9 -> 701 | T9: =F9 -> 0 | U9: =((M9*R9)*12) -> 7116 | W9: =B9 -> 1x1 | X9: =C9 -> Market | Y9: =D9 -> 1 | Z9: =E9 -> 701 | AA9: =F9 -> 0 | AB9: =((H9*Y9)*12) -> 0 | AD9: =B9 -> 1x1 | AE9: =C9 -> Market | AF9: =D9 -> 1 | AG9: =E9 -> 701 | AH9: =F9 -> 0 | AI9: =+MAX(U9,AB9) -> 7116
B10: ='Rent Roll'!C16 -> 1x1 | C10: ='Rent Roll'!D16 -> S8 Voucher | D10: ='Rent Roll'!E16 -> 3 | E10: ='Rent Roll'!F16 -> 701 | F10: ='Rent Roll'!K16 -> 65 | G10: ='Rent Roll'!M16 -> 781 | H10: =+G10-F10 -> 716 | I10: ='Rent Roll'!O16 -> 683 | J10: =I10-F10 -> 618 | K10: ='Rent Roll'!G16 -> 0 | L10: ='Rent Roll'!L16 -> 588 | M10: ='Rent Roll'!J16 -> 523 | N10: =((M10*D10)*12) -> 18828 | P10: =B10 -> 1x1 | Q10: =C10 -> S8 Voucher | R10: =D10 -> 3 | S10: =E10 -> 701 | T10: =F10 -> 65 | U10: =((M10*R10)*12) -> 18828 | W10: =B10 -> 1x1 | X10: =C10 -> S8 Voucher | Y10: =D10 -> 3 | Z10: =E10 -> 701 | AA10: =F10 -> 65 | AB10: =((H10*Y10)*12) -> 25776 | AD10: =B10 -> 1x1 | AE10: =C10 -> S8 Voucher | AF10: =D10 -> 3 | AG10: =E10 -> 701 | AH10: =F10 -> 65 | AI10: =+MAX(U10,AB10) -> 25776
B11: ='Rent Roll'!C17 -> 2x1.5 | C11: ='Rent Roll'!D17 -> 40% AMI | D11: ='Rent Roll'!E17 -> 1 | E11: ='Rent Roll'!F17 -> 940 | F11: ='Rent Roll'!K17 -> 86 | G11: ='Rent Roll'!M17 -> 539 | H11: =+G11-F11 -> 453 | I11: ='Rent Roll'!O17 -> 778 | J11: =I11-F11 -> 692 | K11: ='Rent Roll'!G17 -> 0 | L11: ='Rent Roll'!L17 -> 551 | M11: ='Rent Roll'!J17 -> 465 | N11: =((M11*D11)*12) -> 5580 | P11: =B11 -> 2x1.5 | Q11: =C11 -> 40% AMI | R11: =D11 -> 1 | S11: =E11 -> 940 | T11: =F11 -> 86 | U11: =((M11*R11)*12) -> 5580 | W11: =B11 -> 2x1.5 | X11: =C11 -> 40% AMI | Y11: =D11 -> 1 | Z11: =E11 -> 940 | AA11: =F11 -> 86 | AB11: =((H11*Y11)*12) -> 5436 | AD11: =B11 -> 2x1.5 | AE11: =C11 -> 40% AMI | AF11: =D11 -> 1 | AG11: =E11 -> 940 | AH11: =F11 -> 86 | AI11: =+MAX(U11,AB11) -> 5580
B12: ='Rent Roll'!C18 -> 2x1.5 | C12: ='Rent Roll'!D18 -> 50% AMI | D12: ='Rent Roll'!E18 -> 3 | E12: ='Rent Roll'!F18 -> 990 | F12: ='Rent Roll'!K18 -> 86 | G12: ='Rent Roll'!M18 -> 695 | H12: =+G12-F12 -> 609 | I12: ='Rent Roll'!O18 -> 778 | J12: =I12-F12 -> 692 | K12: ='Rent Roll'!G18 -> 0 | L12: ='Rent Roll'!L18 -> 666 | M12: ='Rent Roll'!J18 -> 580 | N12: =((M12*D12)*12) -> 20880 | P12: =B12 -> 2x1.5 | Q12: =C12 -> 50% AMI | R12: =D12 -> 3 | S12: =E12 -> 990 | T12: =F12 -> 86 | U12: =((M12*R12)*12) -> 20880 | W12: =B12 -> 2x1.5 | X12: =C12 -> 50% AMI | Y12: =D12 -> 3 | Z12: =E12 -> 990 | AA12: =F12 -> 86 | AB12: =((H12*Y12)*12) -> 21924 | AD12: =B12 -> 2x1.5 | AE12: =C12 -> 50% AMI | AF12: =D12 -> 3 | AG12: =E12 -> 990 | AH12: =F12 -> 86 | AI12: =+MAX(U12,AB12) -> 21924
B13: ='Rent Roll'!C19 -> 2x1.5 | C13: ='Rent Roll'!D19 -> 60% AMI | D13: ='Rent Roll'!E19 -> 2 | E13: ='Rent Roll'!F19 -> 980 | F13: ='Rent Roll'!K19 -> 86 | G13: ='Rent Roll'!M19 -> 851 | H13: =+G13-F13 -> 765 | I13: ='Rent Roll'!O19 -> 778 | J13: =I13-F13 -> 692 | K13: ='Rent Roll'!G19 -> 0 | L13: ='Rent Roll'!L19 -> 728 | M13: ='Rent Roll'!J19 -> 642 | N13: =((M13*D13)*12) -> 15408 | P13: =B13 -> 2x1.5 | Q13: =C13 -> 60% AMI | R13: =D13 -> 2 | S13: =E13 -> 980 | T13: =F13 -> 86 | U13: =((M13*R13)*12) -> 15408 | W13: =B13 -> 2x1.5 | X13: =C13 -> 60% AMI | Y13: =D13 -> 2 | Z13: =E13 -> 980 | AA13: =F13 -> 86 | AB13: =((H13*Y13)*12) -> 18360 | AD13: =B13 -> 2x1.5 | AE13: =C13 -> 60% AMI | AF13: =D13 -> 2 | AG13: =E13 -> 980 | AH13: =F13 -> 86 | AI13: =+MAX(U13,AB13) -> 18360
B14: ='Rent Roll'!C20 -> 2x2 | C14: ='Rent Roll'!D20 -> 50% AMI | D14: ='Rent Roll'!E20 -> 1 | E14: ='Rent Roll'!F20 -> 968 | F14: ='Rent Roll'!K20 -> 86 | G14: ='Rent Roll'!M20 -> 695 | H14: =+G14-F14 -> 609 | I14: ='Rent Roll'!O20 -> 778 | J14: =I14-F14 -> 692 | K14: ='Rent Roll'!G20 -> 0 | L14: ='Rent Roll'!L20 -> 696 | M14: ='Rent Roll'!J20 -> 610 | N14: =((M14*D14)*12) -> 7320 | P14: =B14 -> 2x2 | Q14: =C14 -> 50% AMI | R14: =D14 -> 1 | S14: =E14 -> 968 | T14: =F14 -> 86 | U14: =((M14*R14)*12) -> 7320 | W14: =B14 -> 2x2 | X14: =C14 -> 50% AMI | Y14: =D14 -> 1 | Z14: =E14 -> 968 | AA14: =F14 -> 86 | AB14: =((H14*Y14)*12) -> 7308 | AD14: =B14 -> 2x2 | AE14: =C14 -> 50% AMI | AF14: =D14 -> 1 | AG14: =E14 -> 968 | AH14: =F14 -> 86 | AI14: =+MAX(U14,AB14) -> 7320
B15: ='Rent Roll'!C21 -> 2x2 | C15: ='Rent Roll'!D21 -> 60% AMI | D15: ='Rent Roll'!E21 -> 2 | E15: ='Rent Roll'!F21 -> 968 | F15: ='Rent Roll'!K21 -> 86 | G15: ='Rent Roll'!M21 -> 851 | H15: =+G15-F15 -> 765 | I15: ='Rent Roll'!O21 -> 778 | J15: =I15-F15 -> 692 | K15: ='Rent Roll'!G21 -> 0 | L15: ='Rent Roll'!L21 -> 721 | M15: ='Rent Roll'!J21 -> 635 | N15: =((M15*D15)*12) -> 15240 | P15: =B15 -> 2x2 | Q15: =C15 -> 60% AMI | R15: =D15 -> 2 | S15: =E15 -> 968 | T15: =F15 -> 86 | U15: =((M15*R15)*12) -> 15240 | W15: =B15 -> 2x2 | X15: =C15 -> 60% AMI | Y15: =D15 -> 2 | Z15: =E15 -> 968 | AA15: =F15 -> 86 | AB15: =((H15*Y15)*12) -> 18360 | AD15: =B15 -> 2x2 | AE15: =C15 -> 60% AMI | AF15: =D15 -> 2 | AG15: =E15 -> 968 | AH15: =F15 -> 86 | AI15: =+MAX(U15,AB15) -> 18360
B16: ='Rent Roll'!C22 -> 2x2 | C16: ='Rent Roll'!D22 -> Market | D16: ='Rent Roll'!E22 -> 0 | E16: ='Rent Roll'!F22 -> 968 | F16: ='Rent Roll'!K22 -> 0 | G16: ='Rent Roll'!M22 -> 0 | H16: =+G16-F16 -> 0 | I16: ='Rent Roll'!O22 -> 778 | J16: =I16-F16 -> 778 | K16: ='Rent Roll'!G22 -> 0 | L16: ='Rent Roll'!L22 -> 0 | M16: ='Rent Roll'!J22 -> 0 | N16: =((M16*D16)*12) -> 0 | P16: =B16 -> 2x2 | Q16: =C16 -> Market | R16: =D16 -> 0 | S16: =E16 -> 968 | T16: =F16 -> 0 | U16: =((M16*R16)*12) -> 0 | W16: =B16 -> 2x2 | X16: =C16 -> Market | Y16: =D16 -> 0 | Z16: =E16 -> 968 | AA16: =F16 -> 0 | AB16: =((H16*Y16)*12) -> 0 | AD16: =B16 -> 2x2 | AE16: =C16 -> Market | AF16: =D16 -> 0 | AG16: =E16 -> 968 | AH16: =F16 -> 0 | AI16: =+MAX(U16,AB16) -> 0
B17: ='Rent Roll'!C23 -> 2x2 (TH) | C17: ='Rent Roll'!D23 -> 40% AMI | D17: ='Rent Roll'!E23 -> 1 | E17: ='Rent Roll'!F23 -> 1058 | F17: ='Rent Roll'!K23 -> 86 | G17: ='Rent Roll'!M23 -> 539 | H17: =+G17-F17 -> 453 | I17: ='Rent Roll'!O23 -> 778 | J17: =I17-F17 -> 692 | K17: ='Rent Roll'!G23 -> 0 | L17: ='Rent Roll'!L23 -> 536 | M17: ='Rent Roll'!J23 -> 450 | N17: =((M17*D17)*12) -> 5400 | P17: =B17 -> 2x2 (TH) | Q17: =C17 -> 40% AMI | R17: =D17 -> 1 | S17: =E17 -> 1058 | T17: =F17 -> 86 | U17: =((M17*R17)*12) -> 5400 | W17: =B17 -> 2x2 (TH) | X17: =C17 -> 40% AMI | Y17: =D17 -> 1 | Z17: =E17 -> 1058 | AA17: =F17 -> 86 | AB17: =((H17*Y17)*12) -> 5436 | AD17: =B17 -> 2x2 (TH) | AE17: =C17 -> 40% AMI | AF17: =D17 -> 1 | AG17: =E17 -> 1058 | AH17: =F17 -> 86 | AI17: =+MAX(U17,AB17) -> 5436
B18: ='Rent Roll'!C24 -> 2x2 (TH) | C18: ='Rent Roll'!D24 -> 50% AMI | D18: ='Rent Roll'!E24 -> 1 | E18: ='Rent Roll'!F24 -> 1058 | F18: ='Rent Roll'!K24 -> 86 | G18: ='Rent Roll'!M24 -> 695 | H18: =+G18-F18 -> 609 | I18: ='Rent Roll'!O24 -> 778 | J18: =I18-F18 -> 692 | K18: ='Rent Roll'!G24 -> 0 | L18: ='Rent Roll'!L24 -> 146 | M18: ='Rent Roll'!J24 -> 60 | N18: =((M18*D18)*12) -> 720 | P18: =B18 -> 2x2 (TH) | Q18: =C18 -> 50% AMI | R18: =D18 -> 1 | S18: =E18 -> 1058 | T18: =F18 -> 86 | U18: =((M18*R18)*12) -> 720 | W18: =B18 -> 2x2 (TH) | X18: =C18 -> 50% AMI | Y18: =D18 -> 1 | Z18: =E18 -> 1058 | AA18: =F18 -> 86 | AB18: =((H18*Y18)*12) -> 7308 | AD18: =B18 -> 2x2 (TH) | AE18: =C18 -> 50% AMI | AF18: =D18 -> 1 | AG18: =E18 -> 1058 | AH18: =F18 -> 86 | AI18: =+MAX(U18,AB18) -> 7308
... B25: ='Rent Roll'!C31 -> 3x2 (TH) | C25: ='Rent Roll'!D31 -> S8 Voucher | D25: ='Rent Roll'!E31 -> 11 | E25: ='Rent Roll'!F31 -> 1296 | F25: ='Rent Roll'!K31 -> 107 | G25: ='Rent Roll'!M31 -> 976 | H25: =+G25-F25 -> 869 | I25: ='Rent Roll'!O31 -> 1023 | J25: =I25-F25 -> 916 | K25: ='Rent Roll'!G31 -> 0 | L25: ='Rent Roll'!L31 -> 935 | M25: ='Rent Roll'!J31 -> 828 | N25: =((M25*D25)*12) -> 109296 | P25: =B25 -> 3x2 (TH) | Q25: =C25 -> S8 Voucher | R25: =D25 -> 11 | S25: =E25 -> 1296 | T25: =F25 -> 107 | U25: =((M25*R25)*12) -> 109296 | W25: =B25 -> 3x2 (TH) | X25: =C25 -> S8 Voucher | Y25: =D25 -> 11 | Z25: =E25 -> 1296 | AA25: =F25 -> 107 | AB25: =((H25*Y25)*12) -> 114708 | AD25: =B25 -> 3x2 (TH) | AE25: =C25 -> S8 Voucher | AF25: =D25 -> 11 | AG25: =E25 -> 1296 | AH25: =F25 -> 107 | AI25: =+MAX(U25,AB25) -> 114708
B26: Total (Pre-Vacancy) | D26: =SUM(D7:D25) -> 72 | E26: =+SUMPRODUCT(E7:E25,$D7:$D25) -> 59002 | F26: =+SUMPRODUCT(F7:F25,$D7:$D25) -> 6335 | G26: =+SUMPRODUCT(G7:G25,$D7:$D25) -> 59694 | H26: =+SUMPRODUCT(H7:H25,$D7:$D25) -> 53359 | I26: =+SUMPRODUCT(I7:I25,$D7:$D25) -> 60346 | J26: =+SUMPRODUCT(J7:J25,$D7:$D25) -> 54011 | K26: =+SUMPRODUCT(K7:K25,$D7:$D25) -> 0 | L26: =+SUMPRODUCT(L7:L25,$D7:$D25) -> 55808 | M26: =+SUMPRODUCT(M7:M25,$D7:$D25) -> 49473 | N26: =SUM(N7:N25) -> 593676 | P26: Total (Pre-Vacancy) | R26: =SUM(R7:R25) -> 72 | S26: =+SUMPRODUCT(S7:S25,$R7:$R25) -> 59002 | T26: =+SUMPRODUCT(T7:T25,$R7:$R25) -> 6335 | U26: =SUM(U7:U25) -> 593676 | W26: Total (Pre-Vacancy) | Y26: =SUM(Y7:Y25) -> 72 | Z26: =+SUMPRODUCT(Z7:Z25,$Y7:$Y25) -> 59002 | AA26: =+SUMPRODUCT(AA7:AA25,$Y7:$Y25) -> 6335 | AB26: =SUM(AB7:AB25) -> 640308 | AD26: Total (Pre-Vacancy) | AF26: =SUM(AF7:AF25) -> 72 | AG26: =+SUMPRODUCT(AG7:AG25,$AF7:$AF25) -> 59002 | AH26: =+SUMPRODUCT(AH7:AH25,$AF7:$AF25) -> 6335 | AI26: =SUM(AI7:AI25) -> 656580
B28: Year 2 | P28: =+$B28 -> Year 2 | W28: =+$B28 -> Year 2 | AD28: =+$B28 -> Year 2
B29: Unit Type | C29: AMI / S8 | D29: # of Units | E29: Avg. SF | F29: Avg. Utilities | G29: Avg. Max LITHC | H29: Net LIHTC | I29: Avg. Max FMR | J29: Net FMR | K29: =+K6 -> CoStar Rent | L29: Gross Rent | M29: Avg. Current Rent | N29: Yrly. Gross Income (Net Rent) | P29: Unit Type | Q29: AMI / S8 | R29: # of Units | S29: Avg. SF | T29: Avg. Utilities | U29: Max Current Vouchers | W29: Unit Type | X29: AMI / S8 | Y29: # of Units | Z29: Avg. SF | AA29: Avg. Utilities | AB29: Max NET LIHTC | AD29: Unit Type | AE29: AMI / S8 | AF29: # of Units | AG29: Avg. SF | AH29: Avg. Utilities | AI29: Max Current Vouchers + NET LIHTC
B30: =B7 -> 1x1 | C30: =C7 -> 50% AMI | D30: =$D7 -> 2 | E30: =E7 -> 701 | F30: =F7*(1+Dashboard!$P$12) -> 66.95 | G30: =G7*(1+Dashboard!$P$11) -> 670.53 | H30: =+G30-F30 -> 603.58 | I30: =I7*(1+Dashboard!$P$11) -> 703.49 | J30: =I30-F30 -> 636.54 | K30: =K7*(1+Dashboard!$P$11) -> 0 | L30: =M30+F30 -> 609.76 | M30: =M7*(1+Dashboard!$P$11) -> 542.81 | N30: =((M30*D30)*12) -> 13027.44 | P30: =B30 -> 1x1 | Q30: =C30 -> 50% AMI | R30: =D30 -> 2 | S30: =E30 -> 701 | T30: =F30 -> 66.95 | U30: =((M30*R30)*12) -> 13027.44 | W30: =B30 -> 1x1 | X30: =C30 -> 50% AMI | Y30: =D30 -> 2 | Z30: =E30 -> 701 | AA30: =F30 -> 66.95 | AB30: =((H30*Y30)*12) -> 14485.92 | AD30: =B30 -> 1x1 | AE30: =C30 -> 50% AMI | AF30: =D30 -> 2 | AG30: =E30 -> 701 | AH30: =F30 -> 66.95 | AI30: =+MAX(U30,AB30) -> 14485.92
B31: =B8 -> 1x1 | C31: =C8 -> 60% AMI | D31: =$D8 -> 0 | E31: =E8 -> 701 | F31: =F8*(1+Dashboard!$P$12) -> 66.95 | G31: =G8*(1+Dashboard!$P$11) -> 804.43 | H31: =+G31-F31 -> 737.48 | I31: =I8*(1+Dashboard!$P$11) -> 703.49 | J31: =I31-F31 -> 636.54 | K31: =K8*(1+Dashboard!$P$11) -> 0 | L31: =M31+F31 -> 66.95 | M31: =M8*(1+Dashboard!$P$11) -> 0 | N31: =((M31*D31)*12) -> 0 | P31: =B31 -> 1x1 | Q31: =C31 -> 60% AMI | R31: =D31 -> 0 | S31: =E31 -> 701 | T31: =F31 -> 66.95 | U31: =((M31*R31)*12) -> 0 | W31: =B31 -> 1x1 | X31: =C31 -> 60% AMI | Y31: =D31 -> 0 | Z31: =E31 -> 701 | AA31: =F31 -> 66.95 | AB31: =((H31*Y31)*12) -> 0 | AD31: =B31 -> 1x1 | AE31: =C31 -> 60% AMI | AF31: =D31 -> 0 | AG31: =E31 -> 701 | AH31: =F31 -> 66.95 | AI31: =+MAX(U31,AB31) -> 0
B32: =B9 -> 1x1 | C32: =C9 -> Market | D32: =$D9 -> 1 | E32: =E9 -> 701 | F32: =F9*(1+Dashboard!$P$12) -> 0 | G32: =G9*(1+Dashboard!$P$11) -> 0 | H32: =+G32-F32 -> 0 | I32: =I9*(1+Dashboard!$P$11) -> 703.49 | J32: =I32-F32 -> 703.49 | K32: =K9*(1+Dashboard!$P$11) -> 0 | L32: =M32+F32 -> 610.79 | M32: =M9*(1+Dashboard!$P$11) -> 610.79 | N32: =((M32*D32)*12) -> 7329.48 | P32: =B32 -> 1x1 | Q32: =C32 -> Market | R32: =D32 -> 1 | S32: =E32 -> 701 | T32: =F32 -> 0 | U32: =((M32*R32)*12) -> 7329.48 | W32: =B32 -> 1x1 | X32: =C32 -> Market | Y32: =D32 -> 1 | Z32: =E32 -> 701 | AA32: =F32 -> 0 | AB32: =((H32*Y32)*12) -> 0 | AD32: =B32 -> 1x1 | AE32: =C32 -> Market | AF32: =D32 -> 1 | AG32: =E32 -> 701 | AH32: =F32 -> 0 | AI32: =+MAX(U32,AB32) -> 7329.48
B33: =B10 -> 1x1 | C33: =C10 -> S8 Voucher | D33: =$D10 -> 3 | E33: =E10 -> 701 | F33: =F10*(1+Dashboard!$P$12) -> 66.95 | G33: =G10*(1+Dashboard!$P$11) -> 804.43 | H33: =+G33-F33 -> 737.48 | I33: =I10*(1+Dashboard!$P$11) -> 703.49 | J33: =I33-F33 -> 636.54 | K33: =K10*(1+Dashboard!$P$11) -> 0 | L33: =M33+F33 -> 605.64 | M33: =M10*(1+Dashboard!$P$11) -> 538.69 | N33: =((M33*D33)*12) -> 19392.84 | P33: =B33 -> 1x1 | Q33: =C33 -> S8 Voucher | R33: =D33 -> 3 | S33: =E33 -> 701 | T33: =F33 -> 66.95 | U33: =((M33*R33)*12) -> 19392.84 | W33: =B33 -> 1x1 | X33: =C33 -> S8 Voucher | Y33: =D33 -> 3 | Z33: =E33 -> 701 | AA33: =F33 -> 66.95 | AB33: =((H33*Y33)*12) -> 26549.28 | AD33: =B33 -> 1x1 | AE33: =C33 -> S8 Voucher | AF33: =D33 -> 3 | AG33: =E33 -> 701 | AH33: =F33 -> 66.95 | AI33: =+MAX(U33,AB33) -> 26549.28
B34: =B11 -> 2x1.5 | C34: =C11 -> 40% AMI | D34: =$D11 -> 1 | E34: =E11 -> 940 | F34: =F11*(1+Dashboard!$P$12) -> 88.58 | G34: =G11*(1+Dashboard!$P$11) -> 555.17 | H34: =+G34-F34 -> 466.59 | I34: =I11*(1+Dashboard!$P$11) -> 801.34 | J34: =I34-F34 -> 712.76 | K34: =K11*(1+Dashboard!$P$11) -> 0 | L34: =M34+F34 -> 567.53 | M34: =M11*(1+Dashboard!$P$11) -> 478.95 | N34: =((M34*D34)*12) -> 5747.4 | P34: =B34 -> 2x1.5 | Q34: =C34 -> 40% AMI | R34: =D34 -> 1 | S34: =E34 -> 940 | T34: =F34 -> 88.58 | U34: =((M34*R34)*12) -> 5747.4 | W34: =B34 -> 2x1.5 | X34: =C34 -> 40% AMI | Y34: =D34 -> 1 | Z34: =E34 -> 940 | AA34: =F34 -> 88.58 | AB34: =((H34*Y34)*12) -> 5599.08 | AD34: =B34 -> 2x1.5 | AE34: =C34 -> 40% AMI | AF34: =D34 -> 1 | AG34: =E34 -> 940 | AH34: =F34 -> 88.58 | AI34: =+MAX(U34,AB34) -> 5747.4
B35: =B12 -> 2x1.5 | C35: =C12 -> 50% AMI | D35: =$D12 -> 3 | E35: =E12 -> 990 | F35: =F12*(1+Dashboard!$P$12) -> 88.58 | G35: =G12*(1+Dashboard!$P$11) -> 715.85 | H35: =+G35-F35 -> 627.27 | I35: =I12*(1+Dashboard!$P$11) -> 801.34 | J35: =I35-F35 -> 712.76 | K35: =K12*(1+Dashboard!$P$11) -> 0 | L35: =M35+F35 -> 685.98 | M35: =M12*(1+Dashboard!$P$11) -> 597.4 | N35: =((M35*D35)*12) -> 21506.4 | P35: =B35 -> 2x1.5 | Q35: =C35 -> 50% AMI | R35: =D35 -> 3 | S35: =E35 -> 990 | T35: =F35 -> 88.58 | U35: =((M35*R35)*12) -> 21506.4 | W35: =B35 -> 2x1.5 | X35: =C35 -> 50% AMI | Y35: =D35 -> 3 | Z35: =E35 -> 990 | AA35: =F35 -> 88.58 | AB35: =((H35*Y35)*12) -> 22581.72 | AD35: =B35 -> 2x1.5 | AE35: =C35 -> 50% AMI | AF35: =D35 -> 3 | AG35: =E35 -> 990 | AH35: =F35 -> 88.58 | AI35: =+MAX(U35,AB35) -> 22581.72
B36: =B13 -> 2x1.5 | C36: =C13 -> 60% AMI | D36: =$D13 -> 2 | E36: =E13 -> 980 | F36: =F13*(1+Dashboard!$P$12) -> 88.58 | G36: =G13*(1+Dashboard!$P$11) -> 876.53 | H36: =+G36-F36 -> 787.95 | I36: =I13*(1+Dashboard!$P$11) -> 801.34 | J36: =I36-F36 -> 712.76 | K36: =K13*(1+Dashboard!$P$11) -> 0 | L36: =M36+F36 -> 749.84 | M36: =M13*(1+Dashboard!$P$11) -> 661.26 | N36: =((M36*D36)*12) -> 15870.24 | P36: =B36 -> 2x1.5 | Q36: =C36 -> 60% AMI | R36: =D36 -> 2 | S36: =E36 -> 980 | T36: =F36 -> 88.58 | U36: =((M36*R36)*12) -> 15870.24 | W36: =B36 -> 2x1.5 | X36: =C36 -> 60% AMI | Y36: =D36 -> 2 | Z36: =E36 -> 980 | AA36: =F36 -> 88.58 | AB36: =((H36*Y36)*12) -> 18910.8 | AD36: =B36 -> 2x1.5 | AE36: =C36 -> 60% AMI | AF36: =D36 -> 2 | AG36: =E36 -> 980 | AH36: =F36 -> 88.58 | AI36: =+MAX(U36,AB36) -> 18910.8
B37: =B14 -> 2x2 | C37: =C14 -> 50% AMI | D37: =$D14 -> 1 | E37: =E14 -> 968 | F37: =F14*(1+Dashboard!$P$12) -> 88.58 | G37: =G14*(1+Dashboard!$P$11) -> 715.85 | H37: =+G37-F37 -> 627.27 | I37: =I14*(1+Dashboard!$P$11) -> 801.34 | J37: =I37-F37 -> 712.76 | K37: =K14*(1+Dashboard!$P$11) -> 0 | L37: =M37+F37 -> 716.88 | M37: =M14*(1+Dashboard!$P$11) -> 628.3 | N37: =((M37*D37)*12) -> 7539.6 | P37: =B37 -> 2x2 | Q37: =C37 -> 50% AMI | R37: =D37 -> 1 | S37: =E37 -> 968 | T37: =F37 -> 88.58 | U37: =((M37*R37)*12) -> 7539.6 | W37: =B37 -> 2x2 | X37: =C37 -> 50% AMI | Y37: =D37 -> 1 | Z37: =E37 -> 968 | AA37: =F37 -> 88.58 | AB37: =((H37*Y37)*12) -> 7527.24 | AD37: =B37 -> 2x2 | AE37: =C37 -> 50% AMI | AF37: =D37 -> 1 | AG37: =E37 -> 968 | AH37: =F37 -> 88.58 | AI37: =+MAX(U37,AB37) -> 7539.6
B38: =B15 -> 2x2 | C38: =C15 -> 60% AMI | D38: =$D15 -> 2 | E38: =E15 -> 968 | F38: =F15*(1+Dashboard!$P$12) -> 88.58 | G38: =G15*(1+Dashboard!$P$11) -> 876.53 | H38: =+G38-F38 -> 787.95 | I38: =I15*(1+Dashboard!$P$11) -> 801.34 | J38: =I38-F38 -> 712.76 | K38: =K15*(1+Dashboard!$P$11) -> 0 | L38: =M38+F38 -> 742.63 | M38: =M15*(1+Dashboard!$P$11) -> 654.05 | N38: =((M38*D38)*12) -> 15697.2 | P38: =B38 -> 2x2 | Q38: =C38 -> 60% AMI | R38: =D38 -> 2 | S38: =E38 -> 968 | T38: =F38 -> 88.58 | U38: =((M38*R38)*12) -> 15697.2 | W38: =B38 -> 2x2 | X38: =C38 -> 60% AMI | Y38: =D38 -> 2 | Z38: =E38 -> 968 | AA38: =F38 -> 88.58 | AB38: =((H38*Y38)*12) -> 18910.8 | AD38: =B38 -> 2x2 | AE38: =C38 -> 60% AMI | AF38: =D38 -> 2 | AG38: =E38 -> 968 | AH38: =F38 -> 88.58 | AI38: =+MAX(U38,AB38) -> 18910.8
B39: =B16 -> 2x2 | C39: =C16 -> Market | D39: =$D16 -> 0 | E39: =E16 -> 968 | F39: =F16*(1+Dashboard!$P$12) -> 0 | G39: =G16*(1+Dashboard!$P$11) -> 0 | H39: =+G39-F39 -> 0 | I39: =I16*(1+Dashboard!$P$11) -> 801.34 | J39: =I39-F39 -> 801.34 | K39: =K16*(1+Dashboard!$P$11) -> 0 | L39: =M39+F39 -> 0 | M39: =M16*(1+Dashboard!$P$11) -> 0 | N39: =((M39*D39)*12) -> 0 | P39: =B39 -> 2x2 | Q39: =C39 -> Market | R39: =D39 -> 0 | S39: =E39 -> 968 | T39: =F39 -> 0 | U39: =((M39*R39)*12) -> 0 | W39: =B39 -> 2x2 | X39: =C39 -> Market | Y39: =D39 -> 0 | Z39: =E39 -> 968 | AA39: =F39 -> 0 | AB39: =((H39*Y39)*12) -> 0 | AD39: =B39 -> 2x2 | AE39: =C39 -> Market | AF39: =D39 -> 0 | AG39: =E39 -> 968 | AH39: =F39 -> 0 | AI39: =+MAX(U39,AB39) -> 0
B40: =B17 -> 2x2 (TH) | C40: =C17 -> 40% AMI | D40: =$D17 -> 1 | E40: =E17 -> 1058 | F40: =F17*(1+Dashboard!$P$12) -> 88.58 | G40: =G17*(1+Dashboard!$P$11) -> 555.17 | H40: =+G40-F40 -> 466.59 | I40: =I17*(1+Dashboard!$P$11) -> 801.34 | J40: =I40-F40 -> 712.76 | K40: =K17*(1+Dashboard!$P$11) -> 0 | L40: =M40+F40 -> 552.08 | M40: =M17*(1+Dashboard!$P$11) -> 463.5 | N40: =((M40*D40)*12) -> 5562 | P40: =B40 -> 2x2 (TH) | Q40: =C40 -> 40% AMI | R40: =D40 -> 1 | S40: =E40 -> 1058 | T40: =F40 -> 88.58 | U40: =((M40*R40)*12) -> 5562 | W40: =B40 -> 2x2 (TH) | X40: =C40 -> 40% AMI | Y40: =D40 -> 1 | Z40: =E40 -> 1058 | AA40: =F40 -> 88.58 | AB40: =((H40*Y40)*12) -> 5599.08 | AD40: =B40 -> 2x2 (TH) | AE40: =C40 -> 40% AMI | AF40: =D40 -> 1 | AG40: =E40 -> 1058 | AH40: =F40 -> 88.58 | AI40: =+MAX(U40,AB40) -> 5599.08
B41: =B18 -> 2x2 (TH) | C41: =C18 -> 50% AMI | D41: =$D18 -> 1 | E41: =E18 -> 1058 | F41: =F18*(1+Dashboard!$P$12) -> 88.58 | G41: =G18*(1+Dashboard!$P$11) -> 715.85 | H41: =+G41-F41 -> 627.27 | I41: =I18*(1+Dashboard!$P$11) -> 801.34 | J41: =I41-F41 -> 712.76 | K41: =K18*(1+Dashboard!$P$11) -> 0 | L41: =M41+F41 -> 150.38 | M41: =M18*(1+Dashboard!$P$11) -> 61.8 | N41: =((M41*D41)*12) -> 741.6 | P41: =B41 -> 2x2 (TH) | Q41: =C41 -> 50% AMI | R41: =D41 -> 1 | S41: =E41 -> 1058 | T41: =F41 -> 88.58 | U41: =((M41*R41)*12) -> 741.6 | W41: =B41 -> 2x2 (TH) | X41: =C41 -> 50% AMI | Y41: =D41 -> 1 | Z41: =E41 -> 1058 | AA41: =F41 -> 88.58 | AB41: =((H41*Y41)*12) -> 7527.24 | AD41: =B41 -> 2x2 (TH) | AE41: =C41 -> 50% AMI | AF41: =D41 -> 1 | AG41: =E41 -> 1058 | AH41: =F41 -> 88.58 | AI41: =+MAX(U41,AB41) -> 7527.24
... B48: =B25 -> 3x2 (TH) | C48: =C25 -> S8 Voucher | D48: =$D25 -> 11 | E48: =E25 -> 1296 | F48: =F25*(1+Dashboard!$P$12) -> 110.21 | G48: =G25*(1+Dashboard!$P$11) -> 1005.28 | H48: =+G48-F48 -> 895.07 | I48: =I25*(1+Dashboard!$P$11) -> 1053.69 | J48: =I48-F48 -> 943.48 | K48: =K25*(1+Dashboard!$P$11) -> 0 | L48: =M48+F48 -> 963.05 | M48: =M25*(1+Dashboard!$P$11) -> 852.84 | N48: =((M48*D48)*12) -> 112574.88 | P48: =B48 -> 3x2 (TH) | Q48: =C48 -> S8 Voucher | R48: =D48 -> 11 | S48: =E48 -> 1296 | T48: =F48 -> 110.21 | U48: =((M48*R48)*12) -> 112574.88 | W48: =B48 -> 3x2 (TH) | X48: =C48 -> S8 Voucher | Y48: =D48 -> 11 | Z48: =E48 -> 1296 | AA48: =F48 -> 110.21 | AB48: =((H48*Y48)*12) -> 118149.24 | AD48: =B48 -> 3x2 (TH) | AE48: =C48 -> S8 Voucher | AF48: =D48 -> 11 | AG48: =E48 -> 1296 | AH48: =F48 -> 110.21 | AI48: =+MAX(U48,AB48) -> 118149.24
B49: Total (Pre-Vacancy) | D49: =SUM(D30:D48) -> 72 | E49: =+SUMPRODUCT(E30:E48,$D30:$D48) -> 59002 | F49: =+SUMPRODUCT(F30:F48,$D30:$D48) -> 6525.05 | G49: =+SUMPRODUCT(G30:G48,$D30:$D48) -> 61484.82 | H49: =+SUMPRODUCT(H30:H48,$D30:$D48) -> 54959.77 | I49: =+SUMPRODUCT(I30:I48,$D30:$D48) -> 62156.38 | J49: =+SUMPRODUCT(J30:J48,$D30:$D48) -> 55631.33 | K49: =+SUMPRODUCT(K30:K48,$D30:$D48) -> 0 | L49: =+SUMPRODUCT(L30:L48,$D30:$D48) -> 57482.24 | M49: =+SUMPRODUCT(M30:M48,$D30:$D48) -> 50957.19 | N49: =SUM(N30:N48) -> 611486.28 | P49: Total (Pre-Vacancy) | R49: =SUM(R30:R48) -> 72 | S49: =+SUMPRODUCT(S30:S48,$R30:$R48) -> 59002 | T49: =+SUMPRODUCT(T30:T48,$R30:$R48) -> 6525.05 | U49: =SUM(U30:U48) -> 611486.28 | W49: Total (Pre-Vacancy) | Y49: =SUM(Y30:Y48) -> 72 | Z49: =+SUMPRODUCT(Z30:Z48,$Y30:$Y48) -> 59002 | AA49: =+SUMPRODUCT(AA30:AA48,$Y30:$Y48) -> 6525.05 | AB49: =SUM(AB30:AB48) -> 659517.24 | AD49: Total (Pre-Vacancy) | AF49: =SUM(AF30:AF48) -> 72 | AG49: =+SUMPRODUCT(AG30:AG48,$AF30:$AF48) -> 59002 | AH49: =+SUMPRODUCT(AH30:AH48,$AF30:$AF48) -> 6525.05 | AI49: =SUM(AI30:AI48) -> 676277.4
B51: Year 3 | P51: =+$B51 -> Year 3 | W51: =+$B51 -> Year 3 | AD51: =+$B51 -> Year 3
B52: Unit Type | C52: AMI / S8 | D52: # of Units | E52: Avg. SF | F52: Avg. Utilities | G52: Avg. Max LITHC | H52: Net LIHTC | I52: Avg. Max FMR | J52: Net FMR | K52: =+K29 -> CoStar Rent | L52: Gross Rent | M52: Avg. Current Rent | N52: Yrly. Gross Income (Net Rent) | P52: Unit Type | Q52: AMI / S8 | R52: # of Units | S52: Avg. SF | T52: Avg. Utilities | U52: Max Current Vouchers | W52: Unit Type | X52: AMI / S8 | Y52: # of Units | Z52: Avg. SF | AA52: Avg. Utilities | AB52: Max NET LIHTC | AD52: Unit Type | AE52: AMI / S8 | AF52: # of Units | AG52: Avg. SF | AH52: Avg. Utilities | AI52: Max Current Vouchers + NET LIHTC
B53: =B30 -> 1x1 | C53: =C30 -> 50% AMI | D53: =$D30 -> 2 | E53: =E30 -> 701 | F53: =F30*(1+Dashboard!$P$12) -> 68.9585 | G53: =G30*(1+Dashboard!$P$11) -> 690.6459 | H53: =+G53-F53 -> 621.6874 | I53: =I30*(1+Dashboard!$P$11) -> 724.5947 | J53: =I53-F53 -> 655.6362 | K53: =K30*(1+Dashboard!$P$11) -> 0 | L53: =M53+F53 -> 628.0528 | M53: =M30*(1+Dashboard!$P$11) -> 559.0943 | N53: =((M53*D53)*12) -> 13418.263 | P53: =B53 -> 1x1 | Q53: =C53 -> 50% AMI | R53: =D53 -> 2 | S53: =E53 -> 701 | T53: =F53 -> 68.9585 | U53: =((M53*R53)*12) -> 13418.263 | W53: =B53 -> 1x1 | X53: =C53 -> 50% AMI | Y53: =D53 -> 2 | Z53: =E53 -> 701 | AA53: =F53 -> 68.9585 | AB53: =((H53*Y53)*12) -> 14920.498 | AD53: =B53 -> 1x1 | AE53: =C53 -> 50% AMI | AF53: =D53 -> 2 | AG53: =E53 -> 701 | AH53: =F53 -> 68.9585 | AI53: =+MAX(U53,AB53) -> 14920.498
B54: =B31 -> 1x1 | C54: =C31 -> 60% AMI | D54: =$D31 -> 0 | E54: =E31 -> 701 | F54: =F31*(1+Dashboard!$P$12) -> 68.9585 | G54: =G31*(1+Dashboard!$P$11) -> 828.5629 | H54: =+G54-F54 -> 759.6044 | I54: =I31*(1+Dashboard!$P$11) -> 724.5947 | J54: =I54-F54 -> 655.6362 | K54: =K31*(1+Dashboard!$P$11) -> 0 | L54: =M54+F54 -> 68.9585 | M54: =M31*(1+Dashboard!$P$11) -> 0 | N54: =((M54*D54)*12) -> 0 | P54: =B54 -> 1x1 | Q54: =C54 -> 60% AMI | R54: =D54 -> 0 | S54: =E54 -> 701 | T54: =F54 -> 68.9585 | U54: =((M54*R54)*12) -> 0 | W54: =B54 -> 1x1 | X54: =C54 -> 60% AMI | Y54: =D54 -> 0 | Z54: =E54 -> 701 | AA54: =F54 -> 68.9585 | AB54: =((H54*Y54)*12) -> 0 | AD54: =B54 -> 1x1 | AE54: =C54 -> 60% AMI | AF54: =D54 -> 0 | AG54: =E54 -> 701 | AH54: =F54 -> 68.9585 | AI54: =+MAX(U54,AB54) -> 0
B55: =B32 -> 1x1 | C55: =C32 -> Market | D55: =$D32 -> 1 | E55: =E32 -> 701 | F55: =F32*(1+Dashboard!$P$12) -> 0 | G55: =G32*(1+Dashboard!$P$11) -> 0 | H55: =+G55-F55 -> 0 | I55: =I32*(1+Dashboard!$P$11) -> 724.5947 | J55: =I55-F55 -> 724.5947 | K55: =K32*(1+Dashboard!$P$11) -> 0 | L55: =M55+F55 -> 629.1137 | M55: =M32*(1+Dashboard!$P$11) -> 629.1137 | N55: =((M55*D55)*12) -> 7549.3644 | P55: =B55 -> 1x1 | Q55: =C55 -> Market | R55: =D55 -> 1 | S55: =E55 -> 701 | T55: =F55 -> 0 | U55: =((M55*R55)*12) -> 7549.3644 | W55: =B55 -> 1x1 | X55: =C55 -> Market | Y55: =D55 -> 1 | Z55: =E55 -> 701 | AA55: =F55 -> 0 | AB55: =((H55*Y55)*12) -> 0 | AD55: =B55 -> 1x1 | AE55: =C55 -> Market | AF55: =D55 -> 1 | AG55: =E55 -> 701 | AH55: =F55 -> 0 | AI55: =+MAX(U55,AB55) -> 7549.3644
B56: =B33 -> 1x1 | C56: =C33 -> S8 Voucher | D56: =$D33 -> 3 | E56: =E33 -> 701 | F56: =F33*(1+Dashboard!$P$12) -> 68.9585 | G56: =G33*(1+Dashboard!$P$11) -> 828.5629 | H56: =+G56-F56 -> 759.6044 | I56: =I33*(1+Dashboard!$P$11) -> 724.5947 | J56: =I56-F56 -> 655.6362 | K56: =K33*(1+Dashboard!$P$11) -> 0 | L56: =M56+F56 -> 623.8092 | M56: =M33*(1+Dashboard!$P$11) -> 554.8507 | N56: =((M56*D56)*12) -> 19974.625 | P56: =B56 -> 1x1 | Q56: =C56 -> S8 Voucher | R56: =D56 -> 3 | S56: =E56 -> 701 | T56: =F56 -> 68.9585 | U56: =((M56*R56)*12) -> 19974.625 | W56: =B56 -> 1x1 | X56: =C56 -> S8 Voucher | Y56: =D56 -> 3 | Z56: =E56 -> 701 | AA56: =F56 -> 68.9585 | AB56: =((H56*Y56)*12) -> 27345.758 | AD56: =B56 -> 1x1 | AE56: =C56 -> S8 Voucher | AF56: =D56 -> 3 | AG56: =E56 -> 701 | AH56: =F56 -> 68.9585 | AI56: =+MAX(U56,AB56) -> 27345.758
B57: =B34 -> 2x1.5 | C57: =C34 -> 40% AMI | D57: =$D34 -> 1 | E57: =E34 -> 940 | F57: =F34*(1+Dashboard!$P$12) -> 91.2374 | G57: =G34*(1+Dashboard!$P$11) -> 571.8251 | H57: =+G57-F57 -> 480.5877 | I57: =I34*(1+Dashboard!$P$11) -> 825.3802 | J57: =I57-F57 -> 734.1428 | K57: =K34*(1+Dashboard!$P$11) -> 0 | L57: =M57+F57 -> 584.5559 | M57: =M34*(1+Dashboard!$P$11) -> 493.3185 | N57: =((M57*D57)*12) -> 5919.822 | P57: =B57 -> 2x1.5 | Q57: =C57 -> 40% AMI | R57: =D57 -> 1 | S57: =E57 -> 940 | T57: =F57 -> 91.2374 | U57: =((M57*R57)*12) -> 5919.822 | W57: =B57 -> 2x1.5 | X57: =C57 -> 40% AMI | Y57: =D57 -> 1 | Z57: =E57 -> 940 | AA57: =F57 -> 91.2374 | AB57: =((H57*Y57)*12) -> 5767.0524 | AD57: =B57 -> 2x1.5 | AE57: =C57 -> 40% AMI | AF57: =D57 -> 1 | AG57: =E57 -> 940 | AH57: =F57 -> 91.2374 | AI57: =+MAX(U57,AB57) -> 5919.822
B58: =B35 -> 2x1.5 | C58: =C35 -> 50% AMI | D58: =$D35 -> 3 | E58: =E35 -> 990 | F58: =F35*(1+Dashboard!$P$12) -> 91.2374 | G58: =G35*(1+Dashboard!$P$11) -> 737.3255 | H58: =+G58-F58 -> 646.0881 | I58: =I35*(1+Dashboard!$P$11) -> 825.3802 | J58: =I58-F58 -> 734.1428 | K58: =K35*(1+Dashboard!$P$11) -> 0 | L58: =M58+F58 -> 706.5594 | M58: =M35*(1+Dashboard!$P$11) -> 615.322 | N58: =((M58*D58)*12) -> 22151.592 | P58: =B58 -> 2x1.5 | Q58: =C58 -> 50% AMI | R58: =D58 -> 3 | S58: =E58 -> 990 | T58: =F58 -> 91.2374 | U58: =((M58*R58)*12) -> 22151.592 | W58: =B58 -> 2x1.5 | X58: =C58 -> 50% AMI | Y58: =D58 -> 3 | Z58: =E58 -> 990 | AA58: =F58 -> 91.2374 | AB58: =((H58*Y58)*12) -> 23259.172 | AD58: =B58 -> 2x1.5 | AE58: =C58 -> 50% AMI | AF58: =D58 -> 3 | AG58: =E58 -> 990 | AH58: =F58 -> 91.2374 | AI58: =+MAX(U58,AB58) -> 23259.172
B59: =B36 -> 2x1.5 | C59: =C36 -> 60% AMI | D59: =$D36 -> 2 | E59: =E36 -> 980 | F59: =F36*(1+Dashboard!$P$12) -> 91.2374 | G59: =G36*(1+Dashboard!$P$11) -> 902.8259 | H59: =+G59-F59 -> 811.5885 | I59: =I36*(1+Dashboard!$P$11) -> 825.3802 | J59: =I59-F59 -> 734.1428 | K59: =K36*(1+Dashboard!$P$11) -> 0 | L59: =M59+F59 -> 772.3352 | M59: =M36*(1+Dashboard!$P$11) -> 681.0978 | N59: =((M59*D59)*12) -> 16346.347 | P59: =B59 -> 2x1.5 | Q59: =C59 -> 60% AMI | R59: =D59 -> 2 | S59: =E59 -> 980 | T59: =F59 -> 91.2374 | U59: =((M59*R59)*12) -> 16346.347 | W59: =B59 -> 2x1.5 | X59: =C59 -> 60% AMI | Y59: =D59 -> 2 | Z59: =E59 -> 980 | AA59: =F59 -> 91.2374 | AB59: =((H59*Y59)*12) -> 19478.124 | AD59: =B59 -> 2x1.5 | AE59: =C59 -> 60% AMI | AF59: =D59 -> 2 | AG59: =E59 -> 980 | AH59: =F59 -> 91.2374 | AI59: =+MAX(U59,AB59) -> 19478.124
B60: =B37 -> 2x2 | C60: =C37 -> 50% AMI | D60: =$D37 -> 1 | E60: =E37 -> 968 | F60: =F37*(1+Dashboard!$P$12) -> 91.2374 | G60: =G37*(1+Dashboard!$P$11) -> 737.3255 | H60: =+G60-F60 -> 646.0881 | I60: =I37*(1+Dashboard!$P$11) -> 825.3802 | J60: =I60-F60 -> 734.1428 | K60: =K37*(1+Dashboard!$P$11) -> 0 | L60: =M60+F60 -> 738.3864 | M60: =M37*(1+Dashboard!$P$11) -> 647.149 | N60: =((M60*D60)*12) -> 7765.788 | P60: =B60 -> 2x2 | Q60: =C60 -> 50% AMI | R60: =D60 -> 1 | S60: =E60 -> 968 | T60: =F60 -> 91.2374 | U60: =((M60*R60)*12) -> 7765.788 | W60: =B60 -> 2x2 | X60: =C60 -> 50% AMI | Y60: =D60 -> 1 | Z60: =E60 -> 968 | AA60: =F60 -> 91.2374 | AB60: =((H60*Y60)*12) -> 7753.0572 | AD60: =B60 -> 2x2 | AE60: =C60 -> 50% AMI | AF60: =D60 -> 1 | AG60: =E60 -> 968 | AH60: =F60 -> 91.2374 | AI60: =+MAX(U60,AB60) -> 7765.788
B61: =B38 -> 2x2 | C61: =C38 -> 60% AMI | D61: =$D38 -> 2 | E61: =E38 -> 968 | F61: =F38*(1+Dashboard!$P$12) -> 91.2374 | G61: =G38*(1+Dashboard!$P$11) -> 902.8259 | H61: =+G61-F61 -> 811.5885 | I61: =I38*(1+Dashboard!$P$11) -> 825.3802 | J61: =I61-F61 -> 734.1428 | K61: =K38*(1+Dashboard!$P$11) -> 0 | L61: =M61+F61 -> 764.9089 | M61: =M38*(1+Dashboard!$P$11) -> 673.6715 | N61: =((M61*D61)*12) -> 16168.116 | P61: =B61 -> 2x2 | Q61: =C61 -> 60% AMI | R61: =D61 -> 2 | S61: =E61 -> 968 | T61: =F61 -> 91.2374 | U61: =((M61*R61)*12) -> 16168.116 | W61: =B61 -> 2x2 | X61: =C61 -> 60% AMI | Y61: =D61 -> 2 | Z61: =E61 -> 968 | AA61: =F61 -> 91.2374 | AB61: =((H61*Y61)*12) -> 19478.124 | AD61: =B61 -> 2x2 | AE61: =C61 -> 60% AMI | AF61: =D61 -> 2 | AG61: =E61 -> 968 | AH61: =F61 -> 91.2374 | AI61: =+MAX(U61,AB61) -> 19478.124
B62: =B39 -> 2x2 | C62: =C39 -> Market | D62: =$D39 -> 0 | E62: =E39 -> 968 | F62: =F39*(1+Dashboard!$P$12) -> 0 | G62: =G39*(1+Dashboard!$P$11) -> 0 | H62: =+G62-F62 -> 0 | I62: =I39*(1+Dashboard!$P$11) -> 825.3802 | J62: =I62-F62 -> 825.3802 | K62: =K39*(1+Dashboard!$P$11) -> 0 | L62: =M62+F62 -> 0 | M62: =M39*(1+Dashboard!$P$11) -> 0 | N62: =((M62*D62)*12) -> 0 | P62: =B62 -> 2x2 | Q62: =C62 -> Market | R62: =D62 -> 0 | S62: =E62 -> 968 | T62: =F62 -> 0 | U62: =((M62*R62)*12) -> 0 | W62: =B62 -> 2x2 | X62: =C62 -> Market | Y62: =D62 -> 0 | Z62: =E62 -> 968 | AA62: =F62 -> 0 | AB62: =((H62*Y62)*12) -> 0 | AD62: =B62 -> 2x2 | AE62: =C62 -> Market | AF62: =D62 -> 0 | AG62: =E62 -> 968 | AH62: =F62 -> 0 | AI62: =+MAX(U62,AB62) -> 0
B63: =B40 -> 2x2 (TH) | C63: =C40 -> 40% AMI | D63: =$D40 -> 1 | E63: =E40 -> 1058 | F63: =F40*(1+Dashboard!$P$12) -> 91.2374 | G63: =G40*(1+Dashboard!$P$11) -> 571.8251 | H63: =+G63-F63 -> 480.5877 | I63: =I40*(1+Dashboard!$P$11) -> 825.3802 | J63: =I63-F63 -> 734.1428 | K63: =K40*(1+Dashboard!$P$11) -> 0 | L63: =M63+F63 -> 568.6424 | M63: =M40*(1+Dashboard!$P$11) -> 477.405 | N63: =((M63*D63)*12) -> 5728.86 | P63: =B63 -> 2x2 (TH) | Q63: =C63 -> 40% AMI | R63: =D63 -> 1 | S63: =E63 -> 1058 | T63: =F63 -> 91.2374 | U63: =((M63*R63)*12) -> 5728.86 | W63: =B63 -> 2x2 (TH) | X63: =C63 -> 40% AMI | Y63: =D63 -> 1 | Z63: =E63 -> 1058 | AA63: =F63 -> 91.2374 | AB63: =((H63*Y63)*12) -> 5767.0524 | AD63: =B63 -> 2x2 (TH) | AE63: =C63 -> 40% AMI | AF63: =D63 -> 1 | AG63: =E63 -> 1058 | AH63: =F63 -> 91.2374 | AI63: =+MAX(U63,AB63) -> 5767.0524
B64: =B41 -> 2x2 (TH) | C64: =C41 -> 50% AMI | D64: =$D41 -> 1 | E64: =E41 -> 1058 | F64: =F41*(1+Dashboard!$P$12) -> 91.2374 | G64: =G41*(1+Dashboard!$P$11) -> 737.3255 | H64: =+G64-F64 -> 646.0881 | I64: =I41*(1+Dashboard!$P$11) -> 825.3802 | J64: =I64-F64 -> 734.1428 | K64: =K41*(1+Dashboard!$P$11) -> 0 | L64: =M64+F64 -> 154.8914 | M64: =M41*(1+Dashboard!$P$11) -> 63.654 | N64: =((M64*D64)*12) -> 763.848 | P64: =B64 -> 2x2 (TH) | Q64: =C64 -> 50% AMI | R64: =D64 -> 1 | S64: =E64 -> 1058 | T64: =F64 -> 91.2374 | U64: =((M64*R64)*12) -> 763.848 | W64: =B64 -> 2x2 (TH) | X64: =C64 -> 50% AMI | Y64: =D64 -> 1 | Z64: =E64 -> 1058 | AA64: =F64 -> 91.2374 | AB64: =((H64*Y64)*12) -> 7753.0572 | AD64: =B64 -> 2x2 (TH) | AE64: =C64 -> 50% AMI | AF64: =D64 -> 1 | AG64: =E64 -> 1058 | AH64: =F64 -> 91.2374 | AI64: =+MAX(U64,AB64) -> 7753.0572
... B71: =B48 -> 3x2 (TH) | C71: =C48 -> S8 Voucher | D71: =$D48 -> 11 | E71: =E48 -> 1296 | F71: =F48*(1+Dashboard!$P$12) -> 113.5163 | G71: =G48*(1+Dashboard!$P$11) -> 1035.4384 | H71: =+G71-F71 -> 921.9221 | I71: =I48*(1+Dashboard!$P$11) -> 1085.3007 | J71: =I71-F71 -> 971.7844 | K71: =K48*(1+Dashboard!$P$11) -> 0 | L71: =M71+F71 -> 991.9415 | M71: =M48*(1+Dashboard!$P$11) -> 878.4252 | N71: =((M71*D71)*12) -> 115952.13 | P71: =B71 -> 3x2 (TH) | Q71: =C71 -> S8 Voucher | R71: =D71 -> 11 | S71: =E71 -> 1296 | T71: =F71 -> 113.5163 | U71: =((M71*R71)*12) -> 115952.13 | W71: =B71 -> 3x2 (TH) | X71: =C71 -> S8 Voucher | Y71: =D71 -> 11 | Z71: =E71 -> 1296 | AA71: =F71 -> 113.5163 | AB71: =((H71*Y71)*12) -> 121693.72 | AD71: =B71 -> 3x2 (TH) | AE71: =C71 -> S8 Voucher | AF71: =D71 -> 11 | AG71: =E71 -> 1296 | AH71: =F71 -> 113.5163 | AI71: =+MAX(U71,AB71) -> 121693.72
B72: Total (Pre-Vacancy) | D72: =SUM(D53:D71) -> 72 | E72: =+SUMPRODUCT(E53:E71,$D53:$D71) -> 59002 | F72: =+SUMPRODUCT(F53:F71,$D53:$D71) -> 6720.8015 | G72: =+SUMPRODUCT(G53:G71,$D53:$D71) -> 63329.365 | H72: =+SUMPRODUCT(H53:H71,$D53:$D71) -> 56608.563 | I72: =+SUMPRODUCT(I53:I71,$D53:$D71) -> 64021.071 | J72: =+SUMPRODUCT(J53:J71,$D53:$D71) -> 57300.27 | K72: =+SUMPRODUCT(K53:K71,$D53:$D71) -> 0 | L72: =+SUMPRODUCT(L53:L71,$D53:$D71) -> 59206.707 | M72: =+SUMPRODUCT(M53:M71,$D53:$D71) -> 52485.906 | N72: =SUM(N53:N71) -> 629830.87 | P72: Total (Pre-Vacancy) | R72: =SUM(R53:R71) -> 72 | S72: =+SUMPRODUCT(S53:S71,$R53:$R71) -> 59002 | T72: =+SUMPRODUCT(T53:T71,$R53:$R71) -> 6720.8015 | U72: =SUM(U53:U71) -> 629830.87 | W72: Total (Pre-Vacancy) | Y72: =SUM(Y53:Y71) -> 72 | Z72: =+SUMPRODUCT(Z53:Z71,$Y53:$Y71) -> 59002 | AA72: =+SUMPRODUCT(AA53:AA71,$Y53:$Y71) -> 6720.8015 | AB72: =SUM(AB53:AB71) -> 679302.76 | AD72: Total (Pre-Vacancy) | AF72: =SUM(AF53:AF71) -> 72 | AG72: =+SUMPRODUCT(AG53:AG71,$AF53:$AF71) -> 59002 | AH72: =+SUMPRODUCT(AH53:AH71,$AF53:$AF71) -> 6720.8015 | AI72: =SUM(AI53:AI71) -> 696565.72
B74: Year 4 | P74: =+$B74 -> Year 4 | W74: =+$B74 -> Year 4 | AD74: =+$B74 -> Year 4
B75: Unit Type | C75: AMI / S8 | D75: # of Units | E75: Avg. SF | F75: Avg. Utilities | G75: Avg. Max LITHC | H75: Net LIHTC | I75: Avg. Max FMR | J75: Net FMR | K75: =+K52 -> CoStar Rent | L75: Gross Rent | M75: Avg. Current Rent | N75: Yrly. Gross Income (Net Rent) | P75: Unit Type | Q75: AMI / S8 | R75: # of Units | S75: Avg. SF | T75: Avg. Utilities | U75: Max Current Vouchers | W75: Unit Type | X75: AMI / S8 | Y75: # of Units | Z75: Avg. SF | AA75: Avg. Utilities | AB75: Max NET LIHTC | AD75: Unit Type | AE75: AMI / S8 | AF75: # of Units | AG75: Avg. SF | AH75: Avg. Utilities | AI75: Max Current Vouchers + NET LIHTC
B76: =B53 -> 1x1 | C76: =C53 -> 50% AMI | D76: =$D53 -> 2 | E76: =E53 -> 701 | F76: =F53*(1+Dashboard!$P$12) -> 71.027255 | G76: =G53*(1+Dashboard!$P$11) -> 711.36528 | H76: =+G76-F76 -> 640.33802 | I76: =I53*(1+Dashboard!$P$11) -> 746.33254 | J76: =I76-F76 -> 675.30529 | K76: =K53*(1+Dashboard!$P$11) -> 0 | L76: =M76+F76 -> 646.89438 | M76: =M53*(1+Dashboard!$P$11) -> 575.86713 | N76: =((M76*D76)*12) -> 13820.811 | P76: =B76 -> 1x1 | Q76: =C76 -> 50% AMI | R76: =D76 -> 2 | S76: =E76 -> 701 | T76: =F76 -> 71.027255 | U76: =((M76*R76)*12) -> 13820.811 | W76: =B76 -> 1x1 | X76: =C76 -> 50% AMI | Y76: =D76 -> 2 | Z76: =E76 -> 701 | AA76: =F76 -> 71.027255 | AB76: =((H76*Y76)*12) -> 15368.113 | AD76: =B76 -> 1x1 | AE76: =C76 -> 50% AMI | AF76: =D76 -> 2 | AG76: =E76 -> 701 | AH76: =F76 -> 71.027255 | AI76: =+MAX(U76,AB76) -> 15368.113
B77: =B54 -> 1x1 | C77: =C54 -> 60% AMI | D77: =$D54 -> 0 | E77: =E54 -> 701 | F77: =F54*(1+Dashboard!$P$12) -> 71.027255 | G77: =G54*(1+Dashboard!$P$11) -> 853.41979 | H77: =+G77-F77 -> 782.39253 | I77: =I54*(1+Dashboard!$P$11) -> 746.33254 | J77: =I77-F77 -> 675.30529 | K77: =K54*(1+Dashboard!$P$11) -> 0 | L77: =M77+F77 -> 71.027255 | M77: =M54*(1+Dashboard!$P$11) -> 0 | N77: =((M77*D77)*12) -> 0 | P77: =B77 -> 1x1 | Q77: =C77 -> 60% AMI | R77: =D77 -> 0 | S77: =E77 -> 701 | T77: =F77 -> 71.027255 | U77: =((M77*R77)*12) -> 0 | W77: =B77 -> 1x1 | X77: =C77 -> 60% AMI | Y77: =D77 -> 0 | Z77: =E77 -> 701 | AA77: =F77 -> 71.027255 | AB77: =((H77*Y77)*12) -> 0 | AD77: =B77 -> 1x1 | AE77: =C77 -> 60% AMI | AF77: =D77 -> 0 | AG77: =E77 -> 701 | AH77: =F77 -> 71.027255 | AI77: =+MAX(U77,AB77) -> 0
B78: =B55 -> 1x1 | C78: =C55 -> Market | D78: =$D55 -> 1 | E78: =E55 -> 701 | F78: =F55*(1+Dashboard!$P$12) -> 0 | G78: =G55*(1+Dashboard!$P$11) -> 0 | H78: =+G78-F78 -> 0 | I78: =I55*(1+Dashboard!$P$11) -> 746.33254 | J78: =I78-F78 -> 746.33254 | K78: =K55*(1+Dashboard!$P$11) -> 0 | L78: =M78+F78 -> 647.98711 | M78: =M55*(1+Dashboard!$P$11) -> 647.98711 | N78: =((M78*D78)*12) -> 7775.8453 | P78: =B78 -> 1x1 | Q78: =C78 -> Market | R78: =D78 -> 1 | S78: =E78 -> 701 | T78: =F78 -> 0 | U78: =((M78*R78)*12) -> 7775.8453 | W78: =B78 -> 1x1 | X78: =C78 -> Market | Y78: =D78 -> 1 | Z78: =E78 -> 701 | AA78: =F78 -> 0 | AB78: =((H78*Y78)*12) -> 0 | AD78: =B78 -> 1x1 | AE78: =C78 -> Market | AF78: =D78 -> 1 | AG78: =E78 -> 701 | AH78: =F78 -> 0 | AI78: =+MAX(U78,AB78) -> 7775.8453
B79: =B56 -> 1x1 | C79: =C56 -> S8 Voucher | D79: =$D56 -> 3 | E79: =E56 -> 701 | F79: =F56*(1+Dashboard!$P$12) -> 71.027255 | G79: =G56*(1+Dashboard!$P$11) -> 853.41979 | H79: =+G79-F79 -> 782.39253 | I79: =I56*(1+Dashboard!$P$11) -> 746.33254 | J79: =I79-F79 -> 675.30529 | K79: =K56*(1+Dashboard!$P$11) -> 0 | L79: =M79+F79 -> 642.52348 | M79: =M56*(1+Dashboard!$P$11) -> 571.49622 | N79: =((M79*D79)*12) -> 20573.864 | P79: =B79 -> 1x1 | Q79: =C79 -> S8 Voucher | R79: =D79 -> 3 | S79: =E79 -> 701 | T79: =F79 -> 71.027255 | U79: =((M79*R79)*12) -> 20573.864 | W79: =B79 -> 1x1 | X79: =C79 -> S8 Voucher | Y79: =D79 -> 3 | Z79: =E79 -> 701 | AA79: =F79 -> 71.027255 | AB79: =((H79*Y79)*12) -> 28166.131 | AD79: =B79 -> 1x1 | AE79: =C79 -> S8 Voucher | AF79: =D79 -> 3 | AG79: =E79 -> 701 | AH79: =F79 -> 71.027255 | AI79: =+MAX(U79,AB79) -> 28166.131
B80: =B57 -> 2x1.5 | C80: =C57 -> 40% AMI | D80: =$D57 -> 1 | E80: =E57 -> 940 | F80: =F57*(1+Dashboard!$P$12) -> 93.974522 | G80: =G57*(1+Dashboard!$P$11) -> 588.97985 | H80: =+G80-F80 -> 495.00533 | I80: =I57*(1+Dashboard!$P$11) -> 850.14161 | J80: =I80-F80 -> 756.16708 | K80: =K57*(1+Dashboard!$P$11) -> 0 | L80: =M80+F80 -> 602.09258 | M80: =M57*(1+Dashboard!$P$11) -> 508.11806 | N80: =((M80*D80)*12) -> 6097.4167 | P80: =B80 -> 2x1.5 | Q80: =C80 -> 40% AMI | R80: =D80 -> 1 | S80: =E80 -> 940 | T80: =F80 -> 93.974522 | U80: =((M80*R80)*12) -> 6097.4167 | W80: =B80 -> 2x1.5 | X80: =C80 -> 40% AMI | Y80: =D80 -> 1 | Z80: =E80 -> 940 | AA80: =F80 -> 93.974522 | AB80: =((H80*Y80)*12) -> 5940.064 | AD80: =B80 -> 2x1.5 | AE80: =C80 -> 40% AMI | AF80: =D80 -> 1 | AG80: =E80 -> 940 | AH80: =F80 -> 93.974522 | AI80: =+MAX(U80,AB80) -> 6097.4167
B81: =B58 -> 2x1.5 | C81: =C58 -> 50% AMI | D81: =$D58 -> 3 | E81: =E58 -> 990 | F81: =F58*(1+Dashboard!$P$12) -> 93.974522 | G81: =G58*(1+Dashboard!$P$11) -> 759.44527 | H81: =+G81-F81 -> 665.47074 | I81: =I58*(1+Dashboard!$P$11) -> 850.14161 | J81: =I81-F81 -> 756.16708 | K81: =K58*(1+Dashboard!$P$11) -> 0 | L81: =M81+F81 -> 727.75618 | M81: =M58*(1+Dashboard!$P$11) -> 633.78166 | N81: =((M81*D81)*12) -> 22816.14 | P81: =B81 -> 2x1.5 | Q81: =C81 -> 50% AMI | R81: =D81 -> 3 | S81: =E81 -> 990 | T81: =F81 -> 93.974522 | U81: =((M81*R81)*12) -> 22816.14 | W81: =B81 -> 2x1.5 | X81: =C81 -> 50% AMI | Y81: =D81 -> 3 | Z81: =E81 -> 990 | AA81: =F81 -> 93.974522 | AB81: =((H81*Y81)*12) -> 23956.947 | AD81: =B81 -> 2x1.5 | AE81: =C81 -> 50% AMI | AF81: =D81 -> 3 | AG81: =E81 -> 990 | AH81: =F81 -> 93.974522 | AI81: =+MAX(U81,AB81) -> 23956.947
B82: =B59 -> 2x1.5 | C82: =C59 -> 60% AMI | D82: =$D59 -> 2 | E82: =E59 -> 980 | F82: =F59*(1+Dashboard!$P$12) -> 93.974522 | G82: =G59*(1+Dashboard!$P$11) -> 929.91068 | H82: =+G82-F82 -> 835.93616 | I82: =I59*(1+Dashboard!$P$11) -> 850.14161 | J82: =I82-F82 -> 756.16708 | K82: =K59*(1+Dashboard!$P$11) -> 0 | L82: =M82+F82 -> 795.50526 | M82: =M59*(1+Dashboard!$P$11) -> 701.53073 | N82: =((M82*D82)*12) -> 16836.738 | P82: =B82 -> 2x1.5 | Q82: =C82 -> 60% AMI | R82: =D82 -> 2 | S82: =E82 -> 980 | T82: =F82 -> 93.974522 | U82: =((M82*R82)*12) -> 16836.738 | W82: =B82 -> 2x1.5 | X82: =C82 -> 60% AMI | Y82: =D82 -> 2 | Z82: =E82 -> 980 | AA82: =F82 -> 93.974522 | AB82: =((H82*Y82)*12) -> 20062.468 | AD82: =B82 -> 2x1.5 | AE82: =C82 -> 60% AMI | AF82: =D82 -> 2 | AG82: =E82 -> 980 | AH82: =F82 -> 93.974522 | AI82: =+MAX(U82,AB82) -> 20062.468
B83: =B60 -> 2x2 | C83: =C60 -> 50% AMI | D83: =$D60 -> 1 | E83: =E60 -> 968 | F83: =F60*(1+Dashboard!$P$12) -> 93.974522 | G83: =G60*(1+Dashboard!$P$11) -> 759.44527 | H83: =+G83-F83 -> 665.47074 | I83: =I60*(1+Dashboard!$P$11) -> 850.14161 | J83: =I83-F83 -> 756.16708 | K83: =K60*(1+Dashboard!$P$11) -> 0 | L83: =M83+F83 -> 760.53799 | M83: =M60*(1+Dashboard!$P$11) -> 666.56347 | N83: =((M83*D83)*12) -> 7998.7616 | P83: =B83 -> 2x2 | Q83: =C83 -> 50% AMI | R83: =D83 -> 1 | S83: =E83 -> 968 | T83: =F83 -> 93.974522 | U83: =((M83*R83)*12) -> 7998.7616 | W83: =B83 -> 2x2 | X83: =C83 -> 50% AMI | Y83: =D83 -> 1 | Z83: =E83 -> 968 | AA83: =F83 -> 93.974522 | AB83: =((H83*Y83)*12) -> 7985.6489 | AD83: =B83 -> 2x2 | AE83: =C83 -> 50% AMI | AF83: =D83 -> 1 | AG83: =E83 -> 968 | AH83: =F83 -> 93.974522 | AI83: =+MAX(U83,AB83) -> 7998.7616
B84: =B61 -> 2x2 | C84: =C61 -> 60% AMI | D84: =$D61 -> 2 | E84: =E61 -> 968 | F84: =F61*(1+Dashboard!$P$12) -> 93.974522 | G84: =G61*(1+Dashboard!$P$11) -> 929.91068 | H84: =+G84-F84 -> 835.93616 | I84: =I61*(1+Dashboard!$P$11) -> 850.14161 | J84: =I84-F84 -> 756.16708 | K84: =K61*(1+Dashboard!$P$11) -> 0 | L84: =M84+F84 -> 787.85617 | M84: =M61*(1+Dashboard!$P$11) -> 693.88165 | N84: =((M84*D84)*12) -> 16653.159 | P84: =B84 -> 2x2 | Q84: =C84 -> 60% AMI | R84: =D84 -> 2 | S84: =E84 -> 968 | T84: =F84 -> 93.974522 | U84: =((M84*R84)*12) -> 16653.159 | W84: =B84 -> 2x2 | X84: =C84 -> 60% AMI | Y84: =D84 -> 2 | Z84: =E84 -> 968 | AA84: =F84 -> 93.974522 | AB84: =((H84*Y84)*12) -> 20062.468 | AD84: =B84 -> 2x2 | AE84: =C84 -> 60% AMI | AF84: =D84 -> 2 | AG84: =E84 -> 968 | AH84: =F84 -> 93.974522 | AI84: =+MAX(U84,AB84) -> 20062.468
B85: =B62 -> 2x2 | C85: =C62 -> Market | D85: =$D62 -> 0 | E85: =E62 -> 968 | F85: =F62*(1+Dashboard!$P$12) -> 0 | G85: =G62*(1+Dashboard!$P$11) -> 0 | H85: =+G85-F85 -> 0 | I85: =I62*(1+Dashboard!$P$11) -> 850.14161 | J85: =I85-F85 -> 850.14161 | K85: =K62*(1+Dashboard!$P$11) -> 0 | L85: =M85+F85 -> 0 | M85: =M62*(1+Dashboard!$P$11) -> 0 | N85: =((M85*D85)*12) -> 0 | P85: =B85 -> 2x2 | Q85: =C85 -> Market | R85: =D85 -> 0 | S85: =E85 -> 968 | T85: =F85 -> 0 | U85: =((M85*R85)*12) -> 0 | W85: =B85 -> 2x2 | X85: =C85 -> Market | Y85: =D85 -> 0 | Z85: =E85 -> 968 | AA85: =F85 -> 0 | AB85: =((H85*Y85)*12) -> 0 | AD85: =B85 -> 2x2 | AE85: =C85 -> Market | AF85: =D85 -> 0 | AG85: =E85 -> 968 | AH85: =F85 -> 0 | AI85: =+MAX(U85,AB85) -> 0
B86: =B63 -> 2x2 (TH) | C86: =C63 -> 40% AMI | D86: =$D63 -> 1 | E86: =E63 -> 1058 | F86: =F63*(1+Dashboard!$P$12) -> 93.974522 | G86: =G63*(1+Dashboard!$P$11) -> 588.97985 | H86: =+G86-F86 -> 495.00533 | I86: =I63*(1+Dashboard!$P$11) -> 850.14161 | J86: =I86-F86 -> 756.16708 | K86: =K63*(1+Dashboard!$P$11) -> 0 | L86: =M86+F86 -> 585.70167 | M86: =M63*(1+Dashboard!$P$11) -> 491.72715 | N86: =((M86*D86)*12) -> 5900.7258 | P86: =B86 -> 2x2 (TH) | Q86: =C86 -> 40% AMI | R86: =D86 -> 1 | S86: =E86 -> 1058 | T86: =F86 -> 93.974522 | U86: =((M86*R86)*12) -> 5900.7258 | W86: =B86 -> 2x2 (TH) | X86: =C86 -> 40% AMI | Y86: =D86 -> 1 | Z86: =E86 -> 1058 | AA86: =F86 -> 93.974522 | AB86: =((H86*Y86)*12) -> 5940.064 | AD86: =B86 -> 2x2 (TH) | AE86: =C86 -> 40% AMI | AF86: =D86 -> 1 | AG86: =E86 -> 1058 | AH86: =F86 -> 93.974522 | AI86: =+MAX(U86,AB86) -> 5940.064
B87: =B64 -> 2x2 (TH) | C87: =C64 -> 50% AMI | D87: =$D64 -> 1 | E87: =E64 -> 1058 | F87: =F64*(1+Dashboard!$P$12) -> 93.974522 | G87: =G64*(1+Dashboard!$P$11) -> 759.44527 | H87: =+G87-F87 -> 665.47074 | I87: =I64*(1+Dashboard!$P$11) -> 850.14161 | J87: =I87-F87 -> 756.16708 | K87: =K64*(1+Dashboard!$P$11) -> 0 | L87: =M87+F87 -> 159.53814 | M87: =M64*(1+Dashboard!$P$11) -> 65.56362 | N87: =((M87*D87)*12) -> 786.76344 | P87: =B87 -> 2x2 (TH) | Q87: =C87 -> 50% AMI | R87: =D87 -> 1 | S87: =E87 -> 1058 | T87: =F87 -> 93.974522 | U87: =((M87*R87)*12) -> 786.76344 | W87: =B87 -> 2x2 (TH) | X87: =C87 -> 50% AMI | Y87: =D87 -> 1 | Z87: =E87 -> 1058 | AA87: =F87 -> 93.974522 | AB87: =((H87*Y87)*12) -> 7985.6489 | AD87: =B87 -> 2x2 (TH) | AE87: =C87 -> 50% AMI | AF87: =D87 -> 1 | AG87: =E87 -> 1058 | AH87: =F87 -> 93.974522 | AI87: =+MAX(U87,AB87) -> 7985.6489
... B94: =B71 -> 3x2 (TH) | C94: =C71 -> S8 Voucher | D94: =$D71 -> 11 | E94: =E71 -> 1296 | F94: =F71*(1+Dashboard!$P$12) -> 116.92179 | G94: =G71*(1+Dashboard!$P$11) -> 1066.5016 | H94: =+G94-F94 -> 949.57976 | I94: =I71*(1+Dashboard!$P$11) -> 1117.8597 | J94: =I94-F94 -> 1000.9379 | K94: =K71*(1+Dashboard!$P$11) -> 0 | L94: =M94+F94 -> 1021.6997 | M94: =M71*(1+Dashboard!$P$11) -> 904.77796 | N94: =((M94*D94)*12) -> 119430.69 | P94: =B94 -> 3x2 (TH) | Q94: =C94 -> S8 Voucher | R94: =D94 -> 11 | S94: =E94 -> 1296 | T94: =F94 -> 116.92179 | U94: =((M94*R94)*12) -> 119430.69 | W94: =B94 -> 3x2 (TH) | X94: =C94 -> S8 Voucher | Y94: =D94 -> 11 | Z94: =E94 -> 1296 | AA94: =F94 -> 116.92179 | AB94: =((H94*Y94)*12) -> 125344.53 | AD94: =B94 -> 3x2 (TH) | AE94: =C94 -> S8 Voucher | AF94: =D94 -> 11 | AG94: =E94 -> 1296 | AH94: =F94 -> 116.92179 | AI94: =+MAX(U94,AB94) -> 125344.53
B95: Total (Pre-Vacancy) | D95: =SUM(D76:D94) -> 72 | E95: =+SUMPRODUCT(E76:E94,$D76:$D94) -> 59002 | F95: =+SUMPRODUCT(F76:F94,$D76:$D94) -> 6922.4255 | G95: =+SUMPRODUCT(G76:G94,$D76:$D94) -> 65229.246 | H95: =+SUMPRODUCT(H76:H94,$D76:$D94) -> 58306.82 | I95: =+SUMPRODUCT(I76:I94,$D76:$D94) -> 65941.704 | J95: =+SUMPRODUCT(J76:J94,$D76:$D94) -> 59019.278 | K95: =+SUMPRODUCT(K76:K94,$D76:$D94) -> 0 | L95: =+SUMPRODUCT(L76:L94,$D76:$D94) -> 60982.908 | M95: =+SUMPRODUCT(M76:M94,$D76:$D94) -> 54060.483 | N95: =SUM(N76:N94) -> 648725.79 | P95: Total (Pre-Vacancy) | R95: =SUM(R76:R94) -> 72 | S95: =+SUMPRODUCT(S76:S94,$R76:$R94) -> 59002 | T95: =+SUMPRODUCT(T76:T94,$R76:$R94) -> 6922.4255 | U95: =SUM(U76:U94) -> 648725.79 | W95: Total (Pre-Vacancy) | Y95: =SUM(Y76:Y94) -> 72 | Z95: =+SUMPRODUCT(Z76:Z94,$Y76:$Y94) -> 59002 | AA95: =+SUMPRODUCT(AA76:AA94,$Y76:$Y94) -> 6922.4255 | AB95: =SUM(AB76:AB94) -> 699681.84 | AD95: Total (Pre-Vacancy) | AF95: =SUM(AF76:AF94) -> 72 | AG95: =+SUMPRODUCT(AG76:AG94,$AF76:$AF94) -> 59002 | AH95: =+SUMPRODUCT(AH76:AH94,$AF76:$AF94) -> 6922.4255 | AI95: =SUM(AI76:AI94) -> 717462.69
B97: Year 5 | P97: =+$B97 -> Year 5 | W97: =+$B97 -> Year 5 | AD97: =+$B97 -> Year 5
B98: Unit Type | C98: AMI / S8 | D98: # of Units | E98: Avg. SF | F98: Avg. Utilities | G98: Avg. Max LITHC | H98: Net LIHTC | I98: Avg. Max FMR | J98: Net FMR | K98: =+K75 -> CoStar Rent | L98: Gross Rent | M98: Avg. Current Rent | N98: Yrly. Gross Income (Net Rent) | P98: Unit Type | Q98: AMI / S8 | R98: # of Units | S98: Avg. SF | T98: Avg. Utilities | U98: Max Current Vouchers | W98: Unit Type | X98: AMI / S8 | Y98: # of Units | Z98: Avg. SF | AA98: Avg. Utilities | AB98: Max NET LIHTC | AD98: Unit Type | AE98: AMI / S8 | AF98: # of Units | AG98: Avg. SF | AH98: Avg. Utilities | AI98: Max Current Vouchers + NET LIHTC
B99: =B76 -> 1x1 | C99: =C76 -> 50% AMI | D99: =$D76 -> 2 | E99: =E76 -> 701 | F99: =F76*(1+Dashboard!$P$12) -> 73.158073 | G99: =G76*(1+Dashboard!$P$11) -> 732.70624 | H99: =+G99-F99 -> 659.54816 | I99: =I76*(1+Dashboard!$P$11) -> 768.72252 | J99: =I99-F99 -> 695.56444 | K99: =K76*(1+Dashboard!$P$11) -> 0 | L99: =M99+F99 -> 666.30122 | M99: =M76*(1+Dashboard!$P$11) -> 593.14314 | N99: =((M99*D99)*12) -> 14235.435 | P99: =B99 -> 1x1 | Q99: =C99 -> 50% AMI | R99: =D99 -> 2 | S99: =E99 -> 701 | T99: =F99 -> 73.158073 | U99: =((M99*R99)*12) -> 14235.435 | W99: =B99 -> 1x1 | X99: =C99 -> 50% AMI | Y99: =D99 -> 2 | Z99: =E99 -> 701 | AA99: =F99 -> 73.158073 | AB99: =((H99*Y99)*12) -> 15829.156 | AD99: =B99 -> 1x1 | AE99: =C99 -> 50% AMI | AF99: =D99 -> 2 | AG99: =E99 -> 701 | AH99: =F99 -> 73.158073 | AI99: =+MAX(U99,AB99) -> 15829.156
B100: =B77 -> 1x1 | C100: =C77 -> 60% AMI | D100: =$D77 -> 0 | E100: =E77 -> 701 | F100: =F77*(1+Dashboard!$P$12) -> 73.158073 | G100: =G77*(1+Dashboard!$P$11) -> 879.02238 | H100: =+G100-F100 -> 805.86431 | I100: =I77*(1+Dashboard!$P$11) -> 768.72252 | J100: =I100-F100 -> 695.56444 | K100: =K77*(1+Dashboard!$P$11) -> 0 | L100: =M100+F100 -> 73.158073 | M100: =M77*(1+Dashboard!$P$11) -> 0 | N100: =((M100*D100)*12) -> 0 | P100: =B100 -> 1x1 | Q100: =C100 -> 60% AMI | R100: =D100 -> 0 | S100: =E100 -> 701 | T100: =F100 -> 73.158073 | U100: =((M100*R100)*12) -> 0 | W100: =B100 -> 1x1 | X100: =C100 -> 60% AMI | Y100: =D100 -> 0 | Z100: =E100 -> 701 | AA100: =F100 -> 73.158073 | AB100: =((H100*Y100)*12) -> 0 | AD100: =B100 -> 1x1 | AE100: =C100 -> 60% AMI | AF100: =D100 -> 0 | AG100: =E100 -> 701 | AH100: =F100 -> 73.158073 | AI100: =+MAX(U100,AB100) -> 0
B101: =B78 -> 1x1 | C101: =C78 -> Market | D101: =$D78 -> 1 | E101: =E78 -> 701 | F101: =F78*(1+Dashboard!$P$12) -> 0 | G101: =G78*(1+Dashboard!$P$11) -> 0 | H101: =+G101-F101 -> 0 | I101: =I78*(1+Dashboard!$P$11) -> 768.72252 | J101: =I101-F101 -> 768.72252 | K101: =K78*(1+Dashboard!$P$11) -> 0 | L101: =M101+F101 -> 667.42672 | M101: =M78*(1+Dashboard!$P$11) -> 667.42672 | N101: =((M101*D101)*12) -> 8009.1207 | P101: =B101 -> 1x1 | Q101: =C101 -> Market | R101: =D101 -> 1 | S101: =E101 -> 701 | T101: =F101 -> 0 | U101: =((M101*R101)*12) -> 8009.1207 | W101: =B101 -> 1x1 | X101: =C101 -> Market | Y101: =D101 -> 1 | Z101: =E101 -> 701 | AA101: =F101 -> 0 | AB101: =((H101*Y101)*12) -> 0 | AD101: =B101 -> 1x1 | AE101: =C101 -> Market | AF101: =D101 -> 1 | AG101: =E101 -> 701 | AH101: =F101 -> 0 | AI101: =+MAX(U101,AB101) -> 8009.1207
B102: =B79 -> 1x1 | C102: =C79 -> S8 Voucher | D102: =$D79 -> 3 | E102: =E79 -> 701 | F102: =F79*(1+Dashboard!$P$12) -> 73.158073 | G102: =G79*(1+Dashboard!$P$11) -> 879.02238 | H102: =+G102-F102 -> 805.86431 | I102: =I79*(1+Dashboard!$P$11) -> 768.72252 | J102: =I102-F102 -> 695.56444 | K102: =K79*(1+Dashboard!$P$11) -> 0 | L102: =M102+F102 -> 661.79918 | M102: =M79*(1+Dashboard!$P$11) -> 588.64111 | N102: =((M102*D102)*12) -> 21191.08 | P102: =B102 -> 1x1 | Q102: =C102 -> S8 Voucher | R102: =D102 -> 3 | S102: =E102 -> 701 | T102: =F102 -> 73.158073 | U102: =((M102*R102)*12) -> 21191.08 | W102: =B102 -> 1x1 | X102: =C102 -> S8 Voucher | Y102: =D102 -> 3 | Z102: =E102 -> 701 | AA102: =F102 -> 73.158073 | AB102: =((H102*Y102)*12) -> 29011.115 | AD102: =B102 -> 1x1 | AE102: =C102 -> S8 Voucher | AF102: =D102 -> 3 | AG102: =E102 -> 701 | AH102: =F102 -> 73.158073 | AI102: =+MAX(U102,AB102) -> 29011.115
B103: =B80 -> 2x1.5 | C103: =C80 -> 40% AMI | D103: =$D80 -> 1 | E103: =E80 -> 940 | F103: =F80*(1+Dashboard!$P$12) -> 96.793758 | G103: =G80*(1+Dashboard!$P$11) -> 606.64925 | H103: =+G103-F103 -> 509.85549 | I103: =I80*(1+Dashboard!$P$11) -> 875.64585 | J103: =I103-F103 -> 778.8521 | K103: =K80*(1+Dashboard!$P$11) -> 0 | L103: =M103+F103 -> 620.15535 | M103: =M80*(1+Dashboard!$P$11) -> 523.3616 | N103: =((M103*D103)*12) -> 6280.3392 | P103: =B103 -> 2x1.5 | Q103: =C103 -> 40% AMI | R103: =D103 -> 1 | S103: =E103 -> 940 | T103: =F103 -> 96.793758 | U103: =((M103*R103)*12) -> 6280.3392 | W103: =B103 -> 2x1.5 | X103: =C103 -> 40% AMI | Y103: =D103 -> 1 | Z103: =E103 -> 940 | AA103: =F103 -> 96.793758 | AB103: =((H103*Y103)*12) -> 6118.2659 | AD103: =B103 -> 2x1.5 | AE103: =C103 -> 40% AMI | AF103: =D103 -> 1 | AG103: =E103 -> 940 | AH103: =F103 -> 96.793758 | AI103: =+MAX(U103,AB103) -> 6280.3392
B104: =B81 -> 2x1.5 | C104: =C81 -> 50% AMI | D104: =$D81 -> 3 | E104: =E81 -> 990 | F104: =F81*(1+Dashboard!$P$12) -> 96.793758 | G104: =G81*(1+Dashboard!$P$11) -> 782.22862 | H104: =+G104-F104 -> 685.43487 | I104: =I81*(1+Dashboard!$P$11) -> 875.64585 | J104: =I104-F104 -> 778.8521 | K104: =K81*(1+Dashboard!$P$11) -> 0 | L104: =M104+F104 -> 749.58887 | M104: =M81*(1+Dashboard!$P$11) -> 652.79511 | N104: =((M104*D104)*12) -> 23500.624 | P104: =B104 -> 2x1.5 | Q104: =C104 -> 50% AMI | R104: =D104 -> 3 | S104: =E104 -> 990 | T104: =F104 -> 96.793758 | U104: =((M104*R104)*12) -> 23500.624 | W104: =B104 -> 2x1.5 | X104: =C104 -> 50% AMI | Y104: =D104 -> 3 | Z104: =E104 -> 990 | AA104: =F104 -> 96.793758 | AB104: =((H104*Y104)*12) -> 24675.655 | AD104: =B104 -> 2x1.5 | AE104: =C104 -> 50% AMI | AF104: =D104 -> 3 | AG104: =E104 -> 990 | AH104: =F104 -> 96.793758 | AI104: =+MAX(U104,AB104) -> 24675.655
B105: =B82 -> 2x1.5 | C105: =C82 -> 60% AMI | D105: =$D82 -> 2 | E105: =E82 -> 980 | F105: =F82*(1+Dashboard!$P$12) -> 96.793758 | G105: =G82*(1+Dashboard!$P$11) -> 957.808 | H105: =+G105-F105 -> 861.01424 | I105: =I82*(1+Dashboard!$P$11) -> 875.64585 | J105: =I105-F105 -> 778.8521 | K105: =K82*(1+Dashboard!$P$11) -> 0 | L105: =M105+F105 -> 819.37041 | M105: =M82*(1+Dashboard!$P$11) -> 722.57666 | N105: =((M105*D105)*12) -> 17341.84 | P105: =B105 -> 2x1.5 | Q105: =C105 -> 60% AMI | R105: =D105 -> 2 | S105: =E105 -> 980 | T105: =F105 -> 96.793758 | U105: =((M105*R105)*12) -> 17341.84 | W105: =B105 -> 2x1.5 | X105: =C105 -> 60% AMI | Y105: =D105 -> 2 | Z105: =E105 -> 980 | AA105: =F105 -> 96.793758 | AB105: =((H105*Y105)*12) -> 20664.342 | AD105: =B105 -> 2x1.5 | AE105: =C105 -> 60% AMI | AF105: =D105 -> 2 | AG105: =E105 -> 980 | AH105: =F105 -> 96.793758 | AI105: =+MAX(U105,AB105) -> 20664.342
B106: =B83 -> 2x2 | C106: =C83 -> 50% AMI | D106: =$D83 -> 1 | E106: =E83 -> 968 | F106: =F83*(1+Dashboard!$P$12) -> 96.793758 | G106: =G83*(1+Dashboard!$P$11) -> 782.22862 | H106: =+G106-F106 -> 685.43487 | I106: =I83*(1+Dashboard!$P$11) -> 875.64585 | J106: =I106-F106 -> 778.8521 | K106: =K83*(1+Dashboard!$P$11) -> 0 | L106: =M106+F106 -> 783.35413 | M106: =M83*(1+Dashboard!$P$11) -> 686.56037 | N106: =((M106*D106)*12) -> 8238.7245 | P106: =B106 -> 2x2 | Q106: =C106 -> 50% AMI | R106: =D106 -> 1 | S106: =E106 -> 968 | T106: =F106 -> 96.793758 | U106: =((M106*R106)*12) -> 8238.7245 | W106: =B106 -> 2x2 | X106: =C106 -> 50% AMI | Y106: =D106 -> 1 | Z106: =E106 -> 968 | AA106: =F106 -> 96.793758 | AB106: =((H106*Y106)*12) -> 8225.2184 | AD106: =B106 -> 2x2 | AE106: =C106 -> 50% AMI | AF106: =D106 -> 1 | AG106: =E106 -> 968 | AH106: =F106 -> 96.793758 | AI106: =+MAX(U106,AB106) -> 8238.7245
B107: =B84 -> 2x2 | C107: =C84 -> 60% AMI | D107: =$D84 -> 2 | E107: =E84 -> 968 | F107: =F84*(1+Dashboard!$P$12) -> 96.793758 | G107: =G84*(1+Dashboard!$P$11) -> 957.808 | H107: =+G107-F107 -> 861.01424 | I107: =I84*(1+Dashboard!$P$11) -> 875.64585 | J107: =I107-F107 -> 778.8521 | K107: =K84*(1+Dashboard!$P$11) -> 0 | L107: =M107+F107 -> 811.49185 | M107: =M84*(1+Dashboard!$P$11) -> 714.69809 | N107: =((M107*D107)*12) -> 17152.754 | P107: =B107 -> 2x2 | Q107: =C107 -> 60% AMI | R107: =D107 -> 2 | S107: =E107 -> 968 | T107: =F107 -> 96.793758 | U107: =((M107*R107)*12) -> 17152.754 | W107: =B107 -> 2x2 | X107: =C107 -> 60% AMI | Y107: =D107 -> 2 | Z107: =E107 -> 968 | AA107: =F107 -> 96.793758 | AB107: =((H107*Y107)*12) -> 20664.342 | AD107: =B107 -> 2x2 | AE107: =C107 -> 60% AMI | AF107: =D107 -> 2 | AG107: =E107 -> 968 | AH107: =F107 -> 96.793758 | AI107: =+MAX(U107,AB107) -> 20664.342
B108: =B85 -> 2x2 | C108: =C85 -> Market | D108: =$D85 -> 0 | E108: =E85 -> 968 | F108: =F85*(1+Dashboard!$P$12) -> 0 | G108: =G85*(1+Dashboard!$P$11) -> 0 | H108: =+G108-F108 -> 0 | I108: =I85*(1+Dashboard!$P$11) -> 875.64585 | J108: =I108-F108 -> 875.64585 | K108: =K85*(1+Dashboard!$P$11) -> 0 | L108: =M108+F108 -> 0 | M108: =M85*(1+Dashboard!$P$11) -> 0 | N108: =((M108*D108)*12) -> 0 | P108: =B108 -> 2x2 | Q108: =C108 -> Market | R108: =D108 -> 0 | S108: =E108 -> 968 | T108: =F108 -> 0 | U108: =((M108*R108)*12) -> 0 | W108: =B108 -> 2x2 | X108: =C108 -> Market | Y108: =D108 -> 0 | Z108: =E108 -> 968 | AA108: =F108 -> 0 | AB108: =((H108*Y108)*12) -> 0 | AD108: =B108 -> 2x2 | AE108: =C108 -> Market | AF108: =D108 -> 0 | AG108: =E108 -> 968 | AH108: =F108 -> 0 | AI108: =+MAX(U108,AB108) -> 0
B109: =B86 -> 2x2 (TH) | C109: =C86 -> 40% AMI | D109: =$D86 -> 1 | E109: =E86 -> 1058 | F109: =F86*(1+Dashboard!$P$12) -> 96.793758 | G109: =G86*(1+Dashboard!$P$11) -> 606.64925 | H109: =+G109-F109 -> 509.85549 | I109: =I86*(1+Dashboard!$P$11) -> 875.64585 | J109: =I109-F109 -> 778.8521 | K109: =K86*(1+Dashboard!$P$11) -> 0 | L109: =M109+F109 -> 603.27272 | M109: =M86*(1+Dashboard!$P$11) -> 506.47896 | N109: =((M109*D109)*12) -> 6077.7476 | P109: =B109 -> 2x2 (TH) | Q109: =C109 -> 40% AMI | R109: =D109 -> 1 | S109: =E109 -> 1058 | T109: =F109 -> 96.793758 | U109: =((M109*R109)*12) -> 6077.7476 | W109: =B109 -> 2x2 (TH) | X109: =C109 -> 40% AMI | Y109: =D109 -> 1 | Z109: =E109 -> 1058 | AA109: =F109 -> 96.793758 | AB109: =((H109*Y109)*12) -> 6118.2659 | AD109: =B109 -> 2x2 (TH) | AE109: =C109 -> 40% AMI | AF109: =D109 -> 1 | AG109: =E109 -> 1058 | AH109: =F109 -> 96.793758 | AI109: =+MAX(U109,AB109) -> 6118.2659
B110: =B87 -> 2x2 (TH) | C110: =C87 -> 50% AMI | D110: =$D87 -> 1 | E110: =E87 -> 1058 | F110: =F87*(1+Dashboard!$P$12) -> 96.793758 | G110: =G87*(1+Dashboard!$P$11) -> 782.22862 | H110: =+G110-F110 -> 685.43487 | I110: =I87*(1+Dashboard!$P$11) -> 875.64585 | J110: =I110-F110 -> 778.8521 | K110: =K87*(1+Dashboard!$P$11) -> 0 | L110: =M110+F110 -> 164.32429 | M110: =M87*(1+Dashboard!$P$11) -> 67.530529 | N110: =((M110*D110)*12) -> 810.36634 | P110: =B110 -> 2x2 (TH) | Q110: =C110 -> 50% AMI | R110: =D110 -> 1 | S110: =E110 -> 1058 | T110: =F110 -> 96.793758 | U110: =((M110*R110)*12) -> 810.36634 | W110: =B110 -> 2x2 (TH) | X110: =C110 -> 50% AMI | Y110: =D110 -> 1 | Z110: =E110 -> 1058 | AA110: =F110 -> 96.793758 | AB110: =((H110*Y110)*12) -> 8225.2184 | AD110: =B110 -> 2x2 (TH) | AE110: =C110 -> 50% AMI | AF110: =D110 -> 1 | AG110: =E110 -> 1058 | AH110: =F110 -> 96.793758 | AI110: =+MAX(U110,AB110) -> 8225.2184
... B117: =B94 -> 3x2 (TH) | C117: =C94 -> S8 Voucher | D117: =$D94 -> 11 | E117: =E94 -> 1296 | F117: =F94*(1+Dashboard!$P$12) -> 120.42944 | G117: =G94*(1+Dashboard!$P$11) -> 1098.4966 | H117: =+G117-F117 -> 978.06716 | I117: =I94*(1+Dashboard!$P$11) -> 1151.3955 | J117: =I117-F117 -> 1030.9661 | K117: =K94*(1+Dashboard!$P$11) -> 0 | L117: =M117+F117 -> 1052.3507 | M117: =M94*(1+Dashboard!$P$11) -> 931.92129 | N117: =((M117*D117)*12) -> 123013.61 | P117: =B117 -> 3x2 (TH) | Q117: =C117 -> S8 Voucher | R117: =D117 -> 11 | S117: =E117 -> 1296 | T117: =F117 -> 120.42944 | U117: =((M117*R117)*12) -> 123013.61 | W117: =B117 -> 3x2 (TH) | X117: =C117 -> S8 Voucher | Y117: =D117 -> 11 | Z117: =E117 -> 1296 | AA117: =F117 -> 120.42944 | AB117: =((H117*Y117)*12) -> 129104.86 | AD117: =B117 -> 3x2 (TH) | AE117: =C117 -> S8 Voucher | AF117: =D117 -> 11 | AG117: =E117 -> 1296 | AH117: =F117 -> 120.42944 | AI117: =+MAX(U117,AB117) -> 129104.86
B118: Total (Pre-Vacancy) | D118: =SUM(D99:D117) -> 72 | E118: =+SUMPRODUCT(E99:E117,$D99:$D117) -> 59002 | F118: =+SUMPRODUCT(F99:F117,$D99:$D117) -> 7130.0983 | G118: =+SUMPRODUCT(G99:G117,$D99:$D117) -> 67186.123 | H118: =+SUMPRODUCT(H99:H117,$D99:$D117) -> 60056.025 | I118: =+SUMPRODUCT(I99:I117,$D99:$D117) -> 67919.955 | J118: =+SUMPRODUCT(J99:J117,$D99:$D117) -> 60789.856 | K118: =+SUMPRODUCT(K99:K117,$D99:$D117) -> 0 | L118: =+SUMPRODUCT(L99:L117,$D99:$D117) -> 62812.396 | M118: =+SUMPRODUCT(M99:M117,$D99:$D117) -> 55682.297 | N118: =SUM(N99:N117) -> 668187.57 | P118: Total (Pre-Vacancy) | R118: =SUM(R99:R117) -> 72 | S118: =+SUMPRODUCT(S99:S117,$R99:$R117) -> 59002 | T118: =+SUMPRODUCT(T99:T117,$R99:$R117) -> 7130.0983 | U118: =SUM(U99:U117) -> 668187.57 | W118: Total (Pre-Vacancy) | Y118: =SUM(Y99:Y117) -> 72 | Z118: =+SUMPRODUCT(Z99:Z117,$Y99:$Y117) -> 59002 | AA118: =+SUMPRODUCT(AA99:AA117,$Y99:$Y117) -> 7130.0983 | AB118: =SUM(AB99:AB117) -> 720672.3 | AD118: Total (Pre-Vacancy) | AF118: =SUM(AF99:AF117) -> 72 | AG118: =+SUMPRODUCT(AG99:AG117,$AF99:$AF117) -> 59002 | AH118: =+SUMPRODUCT(AH99:AH117,$AF99:$AF117) -> 7130.0983 | AI118: =SUM(AI99:AI117) -> 738986.57
B120: Year 6 | P120: =+$B120 -> Year 6 | W120: =+$B120 -> Year 6 | AD120: =+$B120 -> Year 6
B121: Unit Type | C121: AMI / S8 | D121: # of Units | E121: Avg. SF | F121: Avg. Utilities | G121: Avg. Max LITHC | H121: Net LIHTC | I121: Avg. Max FMR | J121: Net FMR | K121: =+K98 -> CoStar Rent | L121: Gross Rent | M121: Avg. Current Rent | N121: Yrly. Gross Income (Net Rent) | P121: Unit Type | Q121: AMI / S8 | R121: # of Units | S121: Avg. SF | T121: Avg. Utilities | U121: Max Current Vouchers | W121: Unit Type | X121: AMI / S8 | Y121: # of Units | Z121: Avg. SF | AA121: Avg. Utilities | AB121: Max NET LIHTC | AD121: Unit Type | AE121: AMI / S8 | AF121: # of Units | AG121: Avg. SF | AH121: Avg. Utilities | AI121: Max Current Vouchers + NET LIHTC
B122: =B99 -> 1x1 | C122: =C99 -> 50% AMI | D122: =$D99 -> 2 | E122: =E99 -> 701 | F122: =F99*(1+Dashboard!$P$12) -> 75.352815 | G122: =G99*(1+Dashboard!$P$11) -> 754.68742 | H122: =+G122-F122 -> 679.33461 | I122: =I99*(1+Dashboard!$P$11) -> 791.78419 | J122: =I122-F122 -> 716.43138 | K122: =K99*(1+Dashboard!$P$11) -> 0 | L122: =M122+F122 -> 686.29025 | M122: =M99*(1+Dashboard!$P$11) -> 610.93744 | N122: =((M122*D122)*12) -> 14662.498 | P122: =B122 -> 1x1 | Q122: =C122 -> 50% AMI | R122: =D122 -> 2 | S122: =E122 -> 701 | T122: =F122 -> 75.352815 | U122: =((M122*R122)*12) -> 14662.498 | W122: =B122 -> 1x1 | X122: =C122 -> 50% AMI | Y122: =D122 -> 2 | Z122: =E122 -> 701 | AA122: =F122 -> 75.352815 | AB122: =((H122*Y122)*12) -> 16304.031 | AD122: =B122 -> 1x1 | AE122: =C122 -> 50% AMI | AF122: =D122 -> 2 | AG122: =E122 -> 701 | AH122: =F122 -> 75.352815 | AI122: =+MAX(U122,AB122) -> 16304.031
B123: =B100 -> 1x1 | C123: =C100 -> 60% AMI | D123: =$D100 -> 0 | E123: =E100 -> 701 | F123: =F100*(1+Dashboard!$P$12) -> 75.352815 | G123: =G100*(1+Dashboard!$P$11) -> 905.39305 | H123: =+G123-F123 -> 830.04024 | I123: =I100*(1+Dashboard!$P$11) -> 791.78419 | J123: =I123-F123 -> 716.43138 | K123: =K100*(1+Dashboard!$P$11) -> 0 | L123: =M123+F123 -> 75.352815 | M123: =M100*(1+Dashboard!$P$11) -> 0 | N123: =((M123*D123)*12) -> 0 | P123: =B123 -> 1x1 | Q123: =C123 -> 60% AMI | R123: =D123 -> 0 | S123: =E123 -> 701 | T123: =F123 -> 75.352815 | U123: =((M123*R123)*12) -> 0 | W123: =B123 -> 1x1 | X123: =C123 -> 60% AMI | Y123: =D123 -> 0 | Z123: =E123 -> 701 | AA123: =F123 -> 75.352815 | AB123: =((H123*Y123)*12) -> 0 | AD123: =B123 -> 1x1 | AE123: =C123 -> 60% AMI | AF123: =D123 -> 0 | AG123: =E123 -> 701 | AH123: =F123 -> 75.352815 | AI123: =+MAX(U123,AB123) -> 0
B124: =B101 -> 1x1 | C124: =C101 -> Market | D124: =$D101 -> 1 | E124: =E101 -> 701 | F124: =F101*(1+Dashboard!$P$12) -> 0 | G124: =G101*(1+Dashboard!$P$11) -> 0 | H124: =+G124-F124 -> 0 | I124: =I101*(1+Dashboard!$P$11) -> 791.78419 | J124: =I124-F124 -> 791.78419 | K124: =K101*(1+Dashboard!$P$11) -> 0 | L124: =M124+F124 -> 687.44953 | M124: =M101*(1+Dashboard!$P$11) -> 687.44953 | N124: =((M124*D124)*12) -> 8249.3943 | P124: =B124 -> 1x1 | Q124: =C124 -> Market | R124: =D124 -> 1 | S124: =E124 -> 701 | T124: =F124 -> 0 | U124: =((M124*R124)*12) -> 8249.3943 | W124: =B124 -> 1x1 | X124: =C124 -> Market | Y124: =D124 -> 1 | Z124: =E124 -> 701 | AA124: =F124 -> 0 | AB124: =((H124*Y124)*12) -> 0 | AD124: =B124 -> 1x1 | AE124: =C124 -> Market | AF124: =D124 -> 1 | AG124: =E124 -> 701 | AH124: =F124 -> 0 | AI124: =+MAX(U124,AB124) -> 8249.3943
B125: =B102 -> 1x1 | C125: =C102 -> S8 Voucher | D125: =$D102 -> 3 | E125: =E102 -> 701 | F125: =F102*(1+Dashboard!$P$12) -> 75.352815 | G125: =G102*(1+Dashboard!$P$11) -> 905.39305 | H125: =+G125-F125 -> 830.04024 | I125: =I102*(1+Dashboard!$P$11) -> 791.78419 | J125: =I125-F125 -> 716.43138 | K125: =K102*(1+Dashboard!$P$11) -> 0 | L125: =M125+F125 -> 681.65316 | M125: =M102*(1+Dashboard!$P$11) -> 606.30034 | N125: =((M125*D125)*12) -> 21826.812 | P125: =B125 -> 1x1 | Q125: =C125 -> S8 Voucher | R125: =D125 -> 3 | S125: =E125 -> 701 | T125: =F125 -> 75.352815 | U125: =((M125*R125)*12) -> 21826.812 | W125: =B125 -> 1x1 | X125: =C125 -> S8 Voucher | Y125: =D125 -> 3 | Z125: =E125 -> 701 | AA125: =F125 -> 75.352815 | AB125: =((H125*Y125)*12) -> 29881.449 | AD125: =B125 -> 1x1 | AE125: =C125 -> S8 Voucher | AF125: =D125 -> 3 | AG125: =E125 -> 701 | AH125: =F125 -> 75.352815 | AI125: =+MAX(U125,AB125) -> 29881.449
B126: =B103 -> 2x1.5 | C126: =C103 -> 40% AMI | D126: =$D103 -> 1 | E126: =E103 -> 940 | F126: =F103*(1+Dashboard!$P$12) -> 99.69757 | G126: =G103*(1+Dashboard!$P$11) -> 624.84873 | H126: =+G126-F126 -> 525.15116 | I126: =I103*(1+Dashboard!$P$11) -> 901.91523 | J126: =I126-F126 -> 802.21766 | K126: =K103*(1+Dashboard!$P$11) -> 0 | L126: =M126+F126 -> 638.76001 | M126: =M103*(1+Dashboard!$P$11) -> 539.06244 | N126: =((M126*D126)*12) -> 6468.7493 | P126: =B126 -> 2x1.5 | Q126: =C126 -> 40% AMI | R126: =D126 -> 1 | S126: =E126 -> 940 | T126: =F126 -> 99.69757 | U126: =((M126*R126)*12) -> 6468.7493 | W126: =B126 -> 2x1.5 | X126: =C126 -> 40% AMI | Y126: =D126 -> 1 | Z126: =E126 -> 940 | AA126: =F126 -> 99.69757 | AB126: =((H126*Y126)*12) -> 6301.8139 | AD126: =B126 -> 2x1.5 | AE126: =C126 -> 40% AMI | AF126: =D126 -> 1 | AG126: =E126 -> 940 | AH126: =F126 -> 99.69757 | AI126: =+MAX(U126,AB126) -> 6468.7493
B127: =B104 -> 2x1.5 | C127: =C104 -> 50% AMI | D127: =$D104 -> 3 | E127: =E104 -> 990 | F127: =F104*(1+Dashboard!$P$12) -> 99.69757 | G127: =G104*(1+Dashboard!$P$11) -> 805.69548 | H127: =+G127-F127 -> 705.99791 | I127: =I104*(1+Dashboard!$P$11) -> 901.91523 | J127: =I127-F127 -> 802.21766 | K127: =K104*(1+Dashboard!$P$11) -> 0 | L127: =M127+F127 -> 772.07653 | M127: =M104*(1+Dashboard!$P$11) -> 672.37896 | N127: =((M127*D127)*12) -> 24205.643 | P127: =B127 -> 2x1.5 | Q127: =C127 -> 50% AMI | R127: =D127 -> 3 | S127: =E127 -> 990 | T127: =F127 -> 99.69757 | U127: =((M127*R127)*12) -> 24205.643 | W127: =B127 -> 2x1.5 | X127: =C127 -> 50% AMI | Y127: =D127 -> 3 | Z127: =E127 -> 990 | AA127: =F127 -> 99.69757 | AB127: =((H127*Y127)*12) -> 25415.925 | AD127: =B127 -> 2x1.5 | AE127: =C127 -> 50% AMI | AF127: =D127 -> 3 | AG127: =E127 -> 990 | AH127: =F127 -> 99.69757 | AI127: =+MAX(U127,AB127) -> 25415.925
B128: =B105 -> 2x1.5 | C128: =C105 -> 60% AMI | D128: =$D105 -> 2 | E128: =E105 -> 980 | F128: =F105*(1+Dashboard!$P$12) -> 99.69757 | G128: =G105*(1+Dashboard!$P$11) -> 986.54224 | H128: =+G128-F128 -> 886.84467 | I128: =I105*(1+Dashboard!$P$11) -> 901.91523 | J128: =I128-F128 -> 802.21766 | K128: =K105*(1+Dashboard!$P$11) -> 0 | L128: =M128+F128 -> 843.95153 | M128: =M105*(1+Dashboard!$P$11) -> 744.25396 | N128: =((M128*D128)*12) -> 17862.095 | P128: =B128 -> 2x1.5 | Q128: =C128 -> 60% AMI | R128: =D128 -> 2 | S128: =E128 -> 980 | T128: =F128 -> 99.69757 | U128: =((M128*R128)*12) -> 17862.095 | W128: =B128 -> 2x1.5 | X128: =C128 -> 60% AMI | Y128: =D128 -> 2 | Z128: =E128 -> 980 | AA128: =F128 -> 99.69757 | AB128: =((H128*Y128)*12) -> 21284.272 | AD128: =B128 -> 2x1.5 | AE128: =C128 -> 60% AMI | AF128: =D128 -> 2 | AG128: =E128 -> 980 | AH128: =F128 -> 99.69757 | AI128: =+MAX(U128,AB128) -> 21284.272
B129: =B106 -> 2x2 | C129: =C106 -> 50% AMI | D129: =$D106 -> 1 | E129: =E106 -> 968 | F129: =F106*(1+Dashboard!$P$12) -> 99.69757 | G129: =G106*(1+Dashboard!$P$11) -> 805.69548 | H129: =+G129-F129 -> 705.99791 | I129: =I106*(1+Dashboard!$P$11) -> 901.91523 | J129: =I129-F129 -> 802.21766 | K129: =K106*(1+Dashboard!$P$11) -> 0 | L129: =M129+F129 -> 806.85476 | M129: =M106*(1+Dashboard!$P$11) -> 707.15719 | N129: =((M129*D129)*12) -> 8485.8862 | P129: =B129 -> 2x2 | Q129: =C129 -> 50% AMI | R129: =D129 -> 1 | S129: =E129 -> 968 | T129: =F129 -> 99.69757 | U129: =((M129*R129)*12) -> 8485.8862 | W129: =B129 -> 2x2 | X129: =C129 -> 50% AMI | Y129: =D129 -> 1 | Z129: =E129 -> 968 | AA129: =F129 -> 99.69757 | AB129: =((H129*Y129)*12) -> 8471.9749 | AD129: =B129 -> 2x2 | AE129: =C129 -> 50% AMI | AF129: =D129 -> 1 | AG129: =E129 -> 968 | AH129: =F129 -> 99.69757 | AI129: =+MAX(U129,AB129) -> 8485.8862
B130: =B107 -> 2x2 | C130: =C107 -> 60% AMI | D130: =$D107 -> 2 | E130: =E107 -> 968 | F130: =F107*(1+Dashboard!$P$12) -> 99.69757 | G130: =G107*(1+Dashboard!$P$11) -> 986.54224 | H130: =+G130-F130 -> 886.84467 | I130: =I107*(1+Dashboard!$P$11) -> 901.91523 | J130: =I130-F130 -> 802.21766 | K130: =K107*(1+Dashboard!$P$11) -> 0 | L130: =M130+F130 -> 835.83661 | M130: =M107*(1+Dashboard!$P$11) -> 736.13904 | N130: =((M130*D130)*12) -> 17667.337 | P130: =B130 -> 2x2 | Q130: =C130 -> 60% AMI | R130: =D130 -> 2 | S130: =E130 -> 968 | T130: =F130 -> 99.69757 | U130: =((M130*R130)*12) -> 17667.337 | W130: =B130 -> 2x2 | X130: =C130 -> 60% AMI | Y130: =D130 -> 2 | Z130: =E130 -> 968 | AA130: =F130 -> 99.69757 | AB130: =((H130*Y130)*12) -> 21284.272 | AD130: =B130 -> 2x2 | AE130: =C130 -> 60% AMI | AF130: =D130 -> 2 | AG130: =E130 -> 968 | AH130: =F130 -> 99.69757 | AI130: =+MAX(U130,AB130) -> 21284.272
B131: =B108 -> 2x2 | C131: =C108 -> Market | D131: =$D108 -> 0 | E131: =E108 -> 968 | F131: =F108*(1+Dashboard!$P$12) -> 0 | G131: =G108*(1+Dashboard!$P$11) -> 0 | H131: =+G131-F131 -> 0 | I131: =I108*(1+Dashboard!$P$11) -> 901.91523 | J131: =I131-F131 -> 901.91523 | K131: =K108*(1+Dashboard!$P$11) -> 0 | L131: =M131+F131 -> 0 | M131: =M108*(1+Dashboard!$P$11) -> 0 | N131: =((M131*D131)*12) -> 0 | P131: =B131 -> 2x2 | Q131: =C131 -> Market | R131: =D131 -> 0 | S131: =E131 -> 968 | T131: =F131 -> 0 | U131: =((M131*R131)*12) -> 0 | W131: =B131 -> 2x2 | X131: =C131 -> Market | Y131: =D131 -> 0 | Z131: =E131 -> 968 | AA131: =F131 -> 0 | AB131: =((H131*Y131)*12) -> 0 | AD131: =B131 -> 2x2 | AE131: =C131 -> Market | AF131: =D131 -> 0 | AG131: =E131 -> 968 | AH131: =F131 -> 0 | AI131: =+MAX(U131,AB131) -> 0
B132: =B109 -> 2x2 (TH) | C132: =C109 -> 40% AMI | D132: =$D109 -> 1 | E132: =E109 -> 1058 | F132: =F109*(1+Dashboard!$P$12) -> 99.69757 | G132: =G109*(1+Dashboard!$P$11) -> 624.84873 | H132: =+G132-F132 -> 525.15116 | I132: =I109*(1+Dashboard!$P$11) -> 901.91523 | J132: =I132-F132 -> 802.21766 | K132: =K109*(1+Dashboard!$P$11) -> 0 | L132: =M132+F132 -> 621.3709 | M132: =M109*(1+Dashboard!$P$11) -> 521.67333 | N132: =((M132*D132)*12) -> 6260.08 | P132: =B132 -> 2x2 (TH) | Q132: =C132 -> 40% AMI | R132: =D132 -> 1 | S132: =E132 -> 1058 | T132: =F132 -> 99.69757 | U132: =((M132*R132)*12) -> 6260.08 | W132: =B132 -> 2x2 (TH) | X132: =C132 -> 40% AMI | Y132: =D132 -> 1 | Z132: =E132 -> 1058 | AA132: =F132 -> 99.69757 | AB132: =((H132*Y132)*12) -> 6301.8139 | AD132: =B132 -> 2x2 (TH) | AE132: =C132 -> 40% AMI | AF132: =D132 -> 1 | AG132: =E132 -> 1058 | AH132: =F132 -> 99.69757 | AI132: =+MAX(U132,AB132) -> 6301.8139
B133: =B110 -> 2x2 (TH) | C133: =C110 -> 50% AMI | D133: =$D110 -> 1 | E133: =E110 -> 1058 | F133: =F110*(1+Dashboard!$P$12) -> 99.69757 | G133: =G110*(1+Dashboard!$P$11) -> 805.69548 | H133: =+G133-F133 -> 705.99791 | I133: =I110*(1+Dashboard!$P$11) -> 901.91523 | J133: =I133-F133 -> 802.21766 | K133: =K110*(1+Dashboard!$P$11) -> 0 | L133: =M133+F133 -> 169.25401 | M133: =M110*(1+Dashboard!$P$11) -> 69.556444 | N133: =((M133*D133)*12) -> 834.67733 | P133: =B133 -> 2x2 (TH) | Q133: =C133 -> 50% AMI | R133: =D133 -> 1 | S133: =E133 -> 1058 | T133: =F133 -> 99.69757 | U133: =((M133*R133)*12) -> 834.67733 | W133: =B133 -> 2x2 (TH) | X133: =C133 -> 50% AMI | Y133: =D133 -> 1 | Z133: =E133 -> 1058 | AA133: =F133 -> 99.69757 | AB133: =((H133*Y133)*12) -> 8471.9749 | AD133: =B133 -> 2x2 (TH) | AE133: =C133 -> 50% AMI | AF133: =D133 -> 1 | AG133: =E133 -> 1058 | AH133: =F133 -> 99.69757 | AI133: =+MAX(U133,AB133) -> 8471.9749
... B140: =B117 -> 3x2 (TH) | C140: =C117 -> S8 Voucher | D140: =$D117 -> 11 | E140: =E117 -> 1296 | F140: =F117*(1+Dashboard!$P$12) -> 124.04233 | G140: =G117*(1+Dashboard!$P$11) -> 1131.4515 | H140: =+G140-F140 -> 1007.4092 | I140: =I117*(1+Dashboard!$P$11) -> 1185.9374 | J140: =I140-F140 -> 1061.8951 | K140: =K117*(1+Dashboard!$P$11) -> 0 | L140: =M140+F140 -> 1083.9213 | M140: =M117*(1+Dashboard!$P$11) -> 959.87893 | N140: =((M140*D140)*12) -> 126704.02 | P140: =B140 -> 3x2 (TH) | Q140: =C140 -> S8 Voucher | R140: =D140 -> 11 | S140: =E140 -> 1296 | T140: =F140 -> 124.04233 | U140: =((M140*R140)*12) -> 126704.02 | W140: =B140 -> 3x2 (TH) | X140: =C140 -> S8 Voucher | Y140: =D140 -> 11 | Z140: =E140 -> 1296 | AA140: =F140 -> 124.04233 | AB140: =((H140*Y140)*12) -> 132978.01 | AD140: =B140 -> 3x2 (TH) | AE140: =C140 -> S8 Voucher | AF140: =D140 -> 11 | AG140: =E140 -> 1296 | AH140: =F140 -> 124.04233 | AI140: =+MAX(U140,AB140) -> 132978.01
B141: Total (Pre-Vacancy) | D141: =SUM(D122:D140) -> 72 | E141: =+SUMPRODUCT(E122:E140,$D122:$D140) -> 59002 | F141: =+SUMPRODUCT(F122:F140,$D122:$D140) -> 7344.0013 | G141: =+SUMPRODUCT(G122:G140,$D122:$D140) -> 69201.707 | H141: =+SUMPRODUCT(H122:H140,$D122:$D140) -> 61857.705 | I141: =+SUMPRODUCT(I122:I140,$D122:$D140) -> 69957.553 | J141: =+SUMPRODUCT(J122:J140,$D122:$D140) -> 62613.552 | K141: =+SUMPRODUCT(K122:K140,$D122:$D140) -> 0 | L141: =+SUMPRODUCT(L122:L140,$D122:$D140) -> 64696.768 | M141: =+SUMPRODUCT(M122:M140,$D122:$D140) -> 57352.766 | N141: =SUM(N122:N140) -> 688233.2 | P141: Total (Pre-Vacancy) | R141: =SUM(R122:R140) -> 72 | S141: =+SUMPRODUCT(S122:S140,$R122:$R140) -> 59002 | T141: =+SUMPRODUCT(T122:T140,$R122:$R140) -> 7344.0013 | U141: =SUM(U122:U140) -> 688233.2 | W141: Total (Pre-Vacancy) | Y141: =SUM(Y122:Y140) -> 72 | Z141: =+SUMPRODUCT(Z122:Z140,$Y122:$Y140) -> 59002 | AA141: =+SUMPRODUCT(AA122:AA140,$Y122:$Y140) -> 7344.0013 | AB141: =SUM(AB122:AB140) -> 742292.46 | AD141: Total (Pre-Vacancy) | AF141: =SUM(AF122:AF140) -> 72 | AG141: =+SUMPRODUCT(AG122:AG140,$AF122:$AF140) -> 59002 | AH141: =+SUMPRODUCT(AH122:AH140,$AF122:$AF140) -> 7344.0013 | AI141: =SUM(AI122:AI140) -> 761156.17
B143: Year 7 | P143: =+$B143 -> Year 7 | W143: =+$B143 -> Year 7 | AD143: =+$B143 -> Year 7
B144: Unit Type | C144: AMI / S8 | D144: # of Units | E144: Avg. SF | F144: Avg. Utilities | G144: Avg. Max LITHC | H144: Net LIHTC | I144: Avg. Max FMR | J144: Net FMR | K144: =+K121 -> CoStar Rent | L144: Gross Rent | M144: Avg. Current Rent | N144: Yrly. Gross Income (Net Rent) | P144: Unit Type | Q144: AMI / S8 | R144: # of Units | S144: Avg. SF | T144: Avg. Utilities | U144: Max Current Vouchers | W144: Unit Type | X144: AMI / S8 | Y144: # of Units | Z144: Avg. SF | AA144: Avg. Utilities | AB144: Max NET LIHTC | AD144: Unit Type | AE144: AMI / S8 | AF144: # of Units | AG144: Avg. SF | AH144: Avg. Utilities | AI144: Max Current Vouchers + NET LIHTC
B145: =B122 -> 1x1 | C145: =C122 -> 50% AMI | D145: =$D122 -> 2 | E145: =E122 -> 701 | F145: =F122*(1+Dashboard!$P$12) -> 77.613399 | G145: =G122*(1+Dashboard!$P$11) -> 777.32805 | H145: =+G145-F145 -> 699.71465 | I145: =I122*(1+Dashboard!$P$11) -> 815.53772 | J145: =I145-F145 -> 737.92432 | K145: =K122*(1+Dashboard!$P$11) -> 0 | L145: =M145+F145 -> 706.87896 | M145: =M122*(1+Dashboard!$P$11) -> 629.26556 | N145: =((M145*D145)*12) -> 15102.373 | P145: =B145 -> 1x1 | Q145: =C145 -> 50% AMI | R145: =D145 -> 2 | S145: =E145 -> 701 | T145: =F145 -> 77.613399 | U145: =((M145*R145)*12) -> 15102.373 | W145: =B145 -> 1x1 | X145: =C145 -> 50% AMI | Y145: =D145 -> 2 | Z145: =E145 -> 701 | AA145: =F145 -> 77.613399 | AB145: =((H145*Y145)*12) -> 16793.151 | AD145: =B145 -> 1x1 | AE145: =C145 -> 50% AMI | AF145: =D145 -> 2 | AG145: =E145 -> 701 | AH145: =F145 -> 77.613399 | AI145: =+MAX(U145,AB145) -> 16793.151
...

Sheet Rent Roll
B3: Unit Statistics | F3: Unit Types | J3: AMI / S8 Breakdown | N3: Total SF | O3: Avg Gross Rent | P3: Avg Net Rent
B4: Occupied | C4: =C6-C5 -> 68 | D4: =+C4/C6 -> 0.94444444 | F4: =+C13 -> 1x1 | G4: =SUMIF(C$13:E$32,F4,E$13:E$32) -> 6 | H4: =G4/G$10 -> 0.083333333 | J4: =+D17 -> 40% AMI | K4: =SUMIF(D$13:E$32,J4,E$13:E$32) -> 2 | L4: =K4/K$10 -> 0.027777778 | N4: =+SUMPRODUCT(E13:E31,F13:F31) -> 59002 | O4: =L33/C$6 -> 775.11111 | P4: =J33/C6 -> 687.125
B5: Vacant | C5: =+ROUND(D5*$C$6,0) -> 4 | D5: =+Dashboard!P10 -> 0.05 | F5: =+C17 -> 2x1.5 | G5: =SUMIF(C$13:E$32,F5,E$13:E$32) -> 6 | H5: =G5/G$10 -> 0.083333333 | J5: =+D13 -> 50% AMI | K5: =SUMIF(D$13:E$32,J5,E$13:E$32) -> 9 | L5: =K5/K$10 -> 0.125
B6: Total Units | C6: =+SUM(E13:E31) -> 72 | D6: =SUM(D4:D5) -> 0.99444444 | F6: =+C20 -> 2x2 | G6: =SUMIF(C$13:E$32,F6,E$13:E$32) -> 3 | H6: =G6/G$10 -> 0.041666667 | J6: =+D14 -> 60% AMI | K6: =SUMIF(D$13:E$32,J6,E$13:E$32) -> 27 | L6: =K6/K$10 -> 0.375
F7: =+C23 -> 2x2 (TH) | G7: =SUMIF(C$13:E$32,F7,E$13:E$32) -> 19 | H7: =G7/G$10 -> 0.26388889 | J7: =+D22 -> Market | K7: =SUMIF(D$13:E$32,J7,E$13:E$32) -> 2 | L7: =K7/K$10 -> 0.027777778
F8: =+C27 -> 2x1.5-2x2 | G8: =SUMIF(C$13:E$32,F8,E$13:E$32) -> 18 | H8: =G8/G$10 -> 0.25 | J8: =+D27 -> S8 Voucher | K8: =SUMIF(D$13:E$32,J8,E$13:E$32) -> 32 | L8: =K8/K$10 -> 0.44444444
F9: =+C28 -> 3x2 (TH) | G9: =SUMIF(C$13:E$32,F9,E$13:E$32) -> 20 | H9: =G9/G$10 -> 0.27777778
F10: Total | G10: =SUM(G4:G9) -> 72 | H10: =SUM(H4:H9) -> 1 | J10: Total | K10: =SUM(K4:K9) -> 72 | L10: =SUM(L4:L8) -> 1
B12: Unit Set # | C12: Unit Types | D12: AMI / S8 | E12: # of Units | F12: Avg. SF | G12: Avg. Market Rent | H12: Avg. Resident Rent | I12: Avg. Subsidy | J12: Avg. Current Rent | K12: Avg. Utilities | L12: Gross Rent | M12: Avg. Max LIHTC | N12: Net LIHTC | O12: Avg. Max FMR | P12: Net FMR
B13: 1 | C13: 1x1 | D13: 50% AMI | E13: 2 | F13: 701 | H13: 527 | J13: =+(I13+H13) -> 527 | K13: 65 | L13: =J13+K13 -> 592 | M13: 651 | N13: =M13-$K13 -> 586 | O13: 683 | P13: =O13-$K13 -> 618
B14: =+B13+1 -> 2 | C14: 1x1 | D14: 60% AMI | E14: 0 | F14: 701 | H14: 0 | J14: =+(I14+H14) -> 0 | K14: 65 | L14: =J14+K14 -> 65 | M14: 781 | N14: =M14-$K14 -> 716 | O14: 683 | P14: =O14-$K14 -> 618
B15: =+B14+1 -> 3 | C15: 1x1 | D15: Market | E15: 1 | F15: 701 | H15: 593 | J15: =+(I15+H15) -> 593 | K15: 0 | L15: =J15+K15 -> 593 | M15: 0 | N15: =M15-$K15 -> 0 | O15: 683 | P15: =O15-$K15 -> 683
B16: =+B15+1 -> 4 | C16: 1x1 | D16: S8 Voucher | E16: 3 | F16: 701 | H16: 523 | J16: =+(I16+H16) -> 523 | K16: 65 | L16: =J16+K16 -> 588 | M16: 781 | N16: =M16-$K16 -> 716 | O16: 683 | P16: =O16-$K16 -> 618
B17: =+B16+1 -> 5 | C17: 2x1.5 | D17: 40% AMI | E17: 1 | F17: 940 | H17: 465 | J17: =+(I17+H17) -> 465 | K17: 86 | L17: =J17+K17 -> 551 | M17: 539 | N17: =M17-$K17 -> 453 | O17: 778 | P17: =O17-$K17 -> 692
B18: =+B17+1 -> 6 | C18: 2x1.5 | D18: =+D13 -> 50% AMI | E18: 3 | F18: 990 | H18: 580 | J18: =+(I18+H18) -> 580 | K18: 86 | L18: =J18+K18 -> 666 | M18: 695 | N18: =M18-$K18 -> 609 | O18: 778 | P18: =O18-$K18 -> 692
B19: =+B18+1 -> 7 | C19: 2x1.5 | D19: =+D14 -> 60% AMI | E19: 2 | F19: 980 | H19: 642 | J19: =+(I19+H19) -> 642 | K19: 86 | L19: =J19+K19 -> 728 | M19: 851 | N19: =M19-$K19 -> 765 | O19: 778 | P19: =O19-$K19 -> 692
B20: =+B19+1 -> 8 | C20: 2x2 | D20: =+D18 -> 50% AMI | E20: 1 | F20: 968 | H20: 610 | J20: =+(I20+H20) -> 610 | K20: 86 | L20: =J20+K20 -> 696 | M20: 695 | N20: =M20-$K20 -> 609 | O20: 778 | P20: =O20-$K20 -> 692
B21: =+B20+1 -> 9 | C21: 2x2 | D21: =+D19 -> 60% AMI | E21: 2 | F21: 968 | H21: 635 | J21: =+(I21+H21) -> 635 | K21: 86 | L21: =J21+K21 -> 721 | M21: 851 | N21: =M21-$K21 -> 765 | O21: 778 | P21: =O21-$K21 -> 692
B22: =+B21+1 -> 10 | C22: 2x2 | D22: =+D15 -> Market | E22: 0 | F22: 968 | H22: 0 | J22: =+(I22+H22) -> 0 | K22: 0 | L22: =J22+K22 -> 0 | M22: 0 | N22: =M22-$K22 -> 0 | O22: 778 | P22: =O22-$K22 -> 778
B23: =+B22+1 -> 11 | C23: 2x2 (TH) | D23: =+D17 -> 40% AMI | E23: 1 | F23: 1058 | H23: 450 | J23: =+(I23+H23) -> 450 | K23: 86 | L23: =J23+K23 -> 536 | M23: 539 | N23: =M23-$K23 -> 453 | O23: 778 | P23: =O23-$K23 -> 692
B24: =+B23+1 -> 12 | C24: 2x2 (TH) | D24: =+D18 -> 50% AMI | E24: 1 | F24: 1058 | H24: 60 | J24: =+(I24+H24) -> 60 | K24: 86 | L24: =J24+K24 -> 146 | M24: 695 | N24: =M24-$K24 -> 609 | O24: 778 | P24: =O24-$K24 -> 692
B25: =+B24+1 -> 13 | C25: 2x2 (TH) | D25: =+D19 -> 60% AMI | E25: 16 | F25: 1058 | H25: 690 | J25: =+(I25+H25) -> 690 | K25: 86 | L25: =J25+K25 -> 776 | M25: 851 | N25: =M25-$K25 -> 765 | O25: 778 | P25: =O25-$K25 -> 692
B26: =+B25+1 -> 14 | C26: 2x2 (TH) | D26: =+D15 -> Market | E26: 1 | F26: 1058 | H26: 750 | J26: =+(I26+H26) -> 750 | K26: 0 | L26: =J26+K26 -> 750 | M26: 0 | N26: =M26-$K26 -> 0 | O26: 778 | P26: =O26-$K26 -> 778
B27: =+B26+1 -> 15 | C27: 2x1.5-2x2 | D27: =+D16 -> S8 Voucher | E27: 18 | H27: 736 | J27: =+(I27+H27) -> 736 | K27: 86 | L27: =J27+K27 -> 822 | M27: 851 | N27: =M27-$K27 -> 765 | O27: 778 | P27: =O27-$K27 -> 692
B28: =+B27+1 -> 16 | C28: 3x2 (TH) | D28: =+D24 -> 50% AMI | E28: 2 | F28: 1296 | H28: 680 | J28: =+(I28+H28) -> 680 | K28: 107 | L28: =J28+K28 -> 787 | M28: 795 | N28: =M28-$K28 -> 688 | O28: 1023 | P28: =O28-$K28 -> 916
B29: =+B28+1 -> 17 | C29: 3x2 (TH) | D29: =+D25 -> 60% AMI | E29: 7 | F29: 1296 | H29: 696 | J29: =+(I29+H29) -> 696 | K29: 107 | L29: =J29+K29 -> 803 | M29: 976 | N29: =M29-$K29 -> 869 | O29: 1023 | P29: =O29-$K29 -> 916
B30: =+B29+1 -> 18 | C30: 3x2 (TH) | D30: =+D26 -> Market | E30: 0 | F30: 1296 | H30: 0 | J30: =+(I30+H30) -> 0 | K30: 0 | L30: =J30+K30 -> 0 | M30: 0 | N30: =M30-$K30 -> 0 | O30: 1023 | P30: =O30-$K30 -> 1023
B31: =+B30+1 -> 19 | C31: 3x2 (TH) | D31: =+D27 -> S8 Voucher | E31: 11 | F31: 1296 | H31: 828 | J31: =+(I31+H31) -> 828 | K31: 107 | L31: =J31+K31 -> 935 | M31: 976 | N31: =M31-$K31 -> 869 | O31: 1023 | P31: =O31-$K31 -> 916
B32: Add Rows by Inserting Row Above This Row
B33: Monthly Total | F33: --- | G33: =+SUMPRODUCT($E$13:$E$32,G13:G32) -> 0 | H33: =+SUMPRODUCT($E$13:$E$32,H13:H32) -> 49473 | I33: =+SUMPRODUCT($E$13:$E$32,I13:I32) -> 0 | J33: =+SUMPRODUCT($E$13:$E$32,J13:J32) -> 49473 | K33: =+SUMPRODUCT($E$13:$E$32,K13:K32) -> 6335 | L33: =+SUMPRODUCT($E$13:$E$32,L13:L32) -> 55808 | M33: =+SUMPRODUCT($E$13:$E$32,M13:M32) -> 59694 | N33: =+SUMPRODUCT($E$13:$E$32,N13:N32) -> 53359 | ... P33: =+SUMPRODUCT($E$13:$E$32,P13:P32) -> 54011
B34: Yearly Total | F34: --- | G34: =G33*12 -> 0 | H34: =H33*12 -> 593676 | I34: =I33*12 -> 0 | J34: =J33*12 -> 593676 | K34: =K33*12 -> 76020 | L34: =L33*12 -> 669696 | M34: =M33*12 -> 716328 | N34: =N33*12 -> 640308 | ... P34: =P33*12 -> 648132
B36: Weighted Average | F36: =+SUMPRODUCT(F13:F32,$E$13:$E$32)/$C$6 -> 819.47222 | G36: =+SUMPRODUCT(G13:G32,$E$13:$E$32)/$C$6 -> 0 | H36: =+SUMPRODUCT(H13:H32,$E$13:$E$32)/$C$6 -> 687.125 | J36: =+SUMPRODUCT(J13:J32,$E$13:$E$32)/$C$6 -> 687.125 | K36: =+SUMPRODUCT(K13:K32,$E$13:$E$32)/$C$6 -> 87.986111 | L36: =+SUMPRODUCT(L13:L32,$E$13:$E$32)/$C$6 -> 775.11111 | M36: =+SUMPRODUCT(M13:M32,$E$13:$E$32)/$C$6 -> 829.08333 | N36: =+SUMPRODUCT(N13:N32,$E$13:$E$32)/$C$6 -> 741.09722 | O36: =+SUMPRODUCT(O13:O32,$E$13:$E$32)/$C$6 -> 838.13889 | P36: =+SUMPRODUCT(P13:P32,$E$13:$E$32)/$C$6 -> 750.15278

Sheet Summary Outputs -->

Sheet Op Ex per Unit
B3: Total Operating Expenses | O3: Operating Expenses Cost Per Unit
B5: Income Statement | C5: T12 | D5: 1 | E5: =+D5+1 -> 2 | F5: =+E5+1 -> 3 | G5: =+F5+1 -> 4 | H5: =+G5+1 -> 5 | I5: =+H5+1 -> 6 | J5: =+I5+1 -> 7 | K5: =+J5+1 -> 8 | L5: =+K5+1 -> 9 | M5: =+L5+1 -> 10 | O5: Income Statement | P5: T12 | Q5: 1 | R5: =+Q5+1 -> 2 | S5: =+R5+1 -> 3 | T5: =+S5+1 -> 4 | U5: =+T5+1 -> 5 | V5: =+U5+1 -> 6 | W5: =+V5+1 -> 7 | X5: =+W5+1 -> 8 | Y5: =+X5+1 -> 9 | Z5: =+Y5+1 -> 10
B7: Bad Debt | C7: =+'Scenario 0'!E17 -> 0 | D7: =+'Scenario 0'!F17 -> 0 | E7: =+'Scenario 0'!G17 -> 0 | F7: =+'Scenario 0'!H17 -> 0 | G7: =+'Scenario 0'!I17 -> 0 | H7: =+'Scenario 0'!J17 -> 0 | I7: =+'Scenario 0'!K17 -> 0 | J7: =+'Scenario 0'!L17 -> 0 | ... M7: =+'Scenario 0'!O17 -> 0 | O7: Bad Debt | P7: =+'Scenario 0'!E17/Dashboard!$E$16 -> 0 | Q7: =+'Scenario 0'!F17/Dashboard!$E$16 -> 0 | R7: =+'Scenario 0'!G17/Dashboard!$E$16 -> 0 | S7: =+'Scenario 0'!H17/Dashboard!$E$16 -> 0 | T7: =+'Scenario 0'!I17/Dashboard!$E$16 -> 0 | U7: =+'Scenario 0'!J17/Dashboard!$E$16 -> 0 | V7: =+'Scenario 0'!K17/Dashboard!$E$16 -> 0 | W7: =+'Scenario 0'!L17/Dashboard!$E$16 -> 0 | ... Z7: =+'Scenario 0'!O17/Dashboard!$E$16 -> 0
B8: Total Bad Debt | C8: =+'Scenario 0'!E18 -> 0 | D8: =+'Scenario 0'!F18 -> 0 | E8: =+'Scenario 0'!G18 -> 0 | F8: =+'Scenario 0'!H18 -> 0 | G8: =+'Scenario 0'!I18 -> 0 | H8: =+'Scenario 0'!J18 -> 0 | I8: =+'Scenario 0'!K18 -> 0 | J8: =+'Scenario 0'!L18 -> 0 | ... M8: =+'Scenario 0'!O18 -> 0 | O8: Total Bad Debt | P8: =+'Scenario 0'!E18/Dashboard!$E$16 -> 0 | Q8: =+'Scenario 0'!F18/Dashboard!$E$16 -> 0 | R8: =+'Scenario 0'!G18/Dashboard!$E$16 -> 0 | S8: =+'Scenario 0'!H18/Dashboard!$E$16 -> 0 | T8: =+'Scenario 0'!I18/Dashboard!$E$16 -> 0 | U8: =+'Scenario 0'!J18/Dashboard!$E$16 -> 0 | V8: =+'Scenario 0'!K18/Dashboard!$E$16 -> 0 | W8: =+'Scenario 0'!L18/Dashboard!$E$16 -> 0 | ... Z8: =+'Scenario 0'!O18/Dashboard!$E$16 -> 0
B10: Replacement Reserves | C10: =+'Scenario 0'!E20 -> 21600 | D10: =+'Scenario 0'!F20 -> 21600 | E10: =+'Scenario 0'!G20 -> 21600 | F10: =+'Scenario 0'!H20 -> 21600 | G10: =+'Scenario 0'!I20 -> 21600 | H10: =+'Scenario 0'!J20 -> 21600 | I10: =+'Scenario 0'!K20 -> 21600 | J10: =+'Scenario 0'!L20 -> 21600 | ... M10: =+'Scenario 0'!O20 -> 21600 | O10: Replacement Reserves | P10: =+'Scenario 0'!E20/Dashboard!$E$16 -> 300 | Q10: =+'Scenario 0'!F20/Dashboard!$E$16 -> 300 | R10: =+'Scenario 0'!G20/Dashboard!$E$16 -> 300 | S10: =+'Scenario 0'!H20/Dashboard!$E$16 -> 300 | T10: =+'Scenario 0'!I20/Dashboard!$E$16 -> 300 | U10: =+'Scenario 0'!J20/Dashboard!$E$16 -> 300 | V10: =+'Scenario 0'!K20/Dashboard!$E$16 -> 300 | W10: =+'Scenario 0'!L20/Dashboard!$E$16 -> 300 | ... Z10: =+'Scenario 0'!O20/Dashboard!$E$16 -> 300
B11: Compliance Fee | C11: =+'Scenario 0'!E21 -> 0 | D11: =+'Scenario 0'!F21 -> 0 | E11: =+'Scenario 0'!G21 -> 0 | F11: =+'Scenario 0'!H21 -> 0 | G11: =+'Scenario 0'!I21 -> 0 | H11: =+'Scenario 0'!J21 -> 0 | I11: =+'Scenario 0'!K21 -> 0 | J11: =+'Scenario 0'!L21 -> 0 | ... M11: =+'Scenario 0'!O21 -> 0 | O11: Compliance Fee | P11: =+'Scenario 0'!E21/Dashboard!$E$16 -> 0 | Q11: =+'Scenario 0'!F21/Dashboard!$E$16 -> 0 | R11: =+'Scenario 0'!G21/Dashboard!$E$16 -> 0 | S11: =+'Scenario 0'!H21/Dashboard!$E$16 -> 0 | T11: =+'Scenario 0'!I21/Dashboard!$E$16 -> 0 | U11: =+'Scenario 0'!J21/Dashboard!$E$16 -> 0 | V11: =+'Scenario 0'!K21/Dashboard!$E$16 -> 0 | W11: =+'Scenario 0'!L21/Dashboard!$E$16 -> 0 | ... Z11: =+'Scenario 0'!O21/Dashboard!$E$16 -> 0
B12: Total Replacement Reserves | C12: =+'Scenario 0'!E22 -> 21600 | D12: =+'Scenario 0'!F22 -> 21600 | E12: =+'Scenario 0'!G22 -> 21600 | F12: =+'Scenario 0'!H22 -> 21600 | G12: =+'Scenario 0'!I22 -> 21600 | H12: =+'Scenario 0'!J22 -> 21600 | I12: =+'Scenario 0'!K22 -> 21600 | J12: =+'Scenario 0'!L22 -> 21600 | ... M12: =+'Scenario 0'!O22 -> 21600 | O12: Total Replacement Reserves | P12: =+'Scenario 0'!E22/Dashboard!$E$16 -> 300 | Q12: =+'Scenario 0'!F22/Dashboard!$E$16 -> 300 | R12: =+'Scenario 0'!G22/Dashboard!$E$16 -> 300 | S12: =+'Scenario 0'!H22/Dashboard!$E$16 -> 300 | T12: =+'Scenario 0'!I22/Dashboard!$E$16 -> 300 | U12: =+'Scenario 0'!J22/Dashboard!$E$16 -> 300 | V12: =+'Scenario 0'!K22/Dashboard!$E$16 -> 300 | W12: =+'Scenario 0'!L22/Dashboard!$E$16 -> 300 | ... Z12: =+'Scenario 0'!O22/Dashboard!$E$16 -> 300
B14: Property Manager Salary | C14: =+'Scenario 0'!E25 -> 0 | D14: =+'Scenario 0'!F25 -> 56160 | E14: =+'Scenario 0'!G25 -> 57844.8 | F14: =+'Scenario 0'!H25 -> 59580.144 | G14: =+'Scenario 0'!I25 -> 61367.548 | H14: =+'Scenario 0'!J25 -> 63208.575 | I14: =+'Scenario 0'!K25 -> 65104.832 | J14: =+'Scenario 0'!L25 -> 67057.977 | ... M14: =+'Scenario 0'!O25 -> 73276.062 | O14: Property Manager Salary | P14: =+'Scenario 0'!E25/Dashboard!$E$16 -> 0 | Q14: =+'Scenario 0'!F25/Dashboard!$E$16 -> 780 | R14: =+'Scenario 0'!G25/Dashboard!$E$16 -> 803.4 | S14: =+'Scenario 0'!H25/Dashboard!$E$16 -> 827.502 | T14: =+'Scenario 0'!I25/Dashboard!$E$16 -> 852.32706 | U14: =+'Scenario 0'!J25/Dashboard!$E$16 -> 877.89687 | V14: =+'Scenario 0'!K25/Dashboard!$E$16 -> 904.23378 | W14: =+'Scenario 0'!L25/Dashboard!$E$16 -> 931.36079 | ... Z14: =+'Scenario 0'!O25/Dashboard!$E$16 -> 1017.7231
B15: Assistant Manager (over 160 units) | C15: =+'Scenario 0'!E26 -> 0 | D15: =+'Scenario 0'!F26 -> 0 | E15: =+'Scenario 0'!G26 -> 0 | F15: =+'Scenario 0'!H26 -> 0 | G15: =+'Scenario 0'!I26 -> 0 | H15: =+'Scenario 0'!J26 -> 0 | I15: =+'Scenario 0'!K26 -> 0 | J15: =+'Scenario 0'!L26 -> 0 | ... M15: =+'Scenario 0'!O26 -> 0 | O15: Assistant Manager (over 160 units) | P15: =+'Scenario 0'!E26/Dashboard!$E$16 -> 0 | Q15: =+'Scenario 0'!F26/Dashboard!$E$16 -> 0 | R15: =+'Scenario 0'!G26/Dashboard!$E$16 -> 0 | S15: =+'Scenario 0'!H26/Dashboard!$E$16 -> 0 | T15: =+'Scenario 0'!I26/Dashboard!$E$16 -> 0 | U15: =+'Scenario 0'!J26/Dashboard!$E$16 -> 0 | V15: =+'Scenario 0'!K26/Dashboard!$E$16 -> 0 | W15: =+'Scenario 0'!L26/Dashboard!$E$16 -> 0 | ... Z15: =+'Scenario 0'!O26/Dashboard!$E$16 -> 0
B16: Commissions/Bonuses | C16: =+'Scenario 0'!E27 -> 0 | D16: =+'Scenario 0'!F27 -> 0 | E16: =+'Scenario 0'!G27 -> 0 | F16: =+'Scenario 0'!H27 -> 0 | G16: =+'Scenario 0'!I27 -> 0 | H16: =+'Scenario 0'!J27 -> 0 | I16: =+'Scenario 0'!K27 -> 0 | J16: =+'Scenario 0'!L27 -> 0 | ... M16: =+'Scenario 0'!O27 -> 0 | O16: Commissions/Bonuses | P16: =+'Scenario 0'!E27/Dashboard!$E$16 -> 0 | Q16: =+'Scenario 0'!F27/Dashboard!$E$16 -> 0 | R16: =+'Scenario 0'!G27/Dashboard!$E$16 -> 0 | S16: =+'Scenario 0'!H27/Dashboard!$E$16 -> 0 | T16: =+'Scenario 0'!I27/Dashboard!$E$16 -> 0 | U16: =+'Scenario 0'!J27/Dashboard!$E$16 -> 0 | V16: =+'Scenario 0'!K27/Dashboard!$E$16 -> 0 | W16: =+'Scenario 0'!L27/Dashboard!$E$16 -> 0 | ... Z16: =+'Scenario 0'!O27/Dashboard!$E$16 -> 0
B17: Maintenance Salary | C17: =+'Scenario 0'!E28 -> 0 | D17: =+'Scenario 0'!F28 -> 56160 | E17: =+'Scenario 0'!G28 -> 57844.8 | F17: =+'Scenario 0'!H28 -> 59580.144 | G17: =+'Scenario 0'!I28 -> 61367.548 | H17: =+'Scenario 0'!J28 -> 63208.575 | I17: =+'Scenario 0'!K28 -> 65104.832 | J17: =+'Scenario 0'!L28 -> 67057.977 | ... M17: =+'Scenario 0'!O28 -> 73276.062 | O17: Maintenance Salary | P17: =+'Scenario 0'!E28/Dashboard!$E$16 -> 0 | Q17: =+'Scenario 0'!F28/Dashboard!$E$16 -> 780 | R17: =+'Scenario 0'!G28/Dashboard!$E$16 -> 803.4 | S17: =+'Scenario 0'!H28/Dashboard!$E$16 -> 827.502 | T17: =+'Scenario 0'!I28/Dashboard!$E$16 -> 852.32706 | U17: =+'Scenario 0'!J28/Dashboard!$E$16 -> 877.89687 | V17: =+'Scenario 0'!K28/Dashboard!$E$16 -> 904.23378 | W17: =+'Scenario 0'!L28/Dashboard!$E$16 -> 931.36079 | ... Z17: =+'Scenario 0'!O28/Dashboard!$E$16 -> 1017.7231
B18: Total Payroll | C18: =+'Scenario 0'!E29 -> 0 | D18: =+'Scenario 0'!F29 -> 126720 | E18: =+'Scenario 0'!G29 -> 130521.6 | F18: =+'Scenario 0'!H29 -> 134437.25 | G18: =+'Scenario 0'!I29 -> 138470.37 | H18: =+'Scenario 0'!J29 -> 142624.48 | I18: =+'Scenario 0'!K29 -> 146903.21 | J18: =+'Scenario 0'!L29 -> 151310.31 | ... M18: =+'Scenario 0'!O29 -> 165340.86 | O18: Total Payroll | P18: =+'Scenario 0'!E29/Dashboard!$E$16 -> 0 | Q18: =+'Scenario 0'!F29/Dashboard!$E$16 -> 1760 | R18: =+'Scenario 0'!G29/Dashboard!$E$16 -> 1812.8 | S18: =+'Scenario 0'!H29/Dashboard!$E$16 -> 1867.184 | T18: =+'Scenario 0'!I29/Dashboard!$E$16 -> 1923.1995 | U18: =+'Scenario 0'!J29/Dashboard!$E$16 -> 1980.8955 | V18: =+'Scenario 0'!K29/Dashboard!$E$16 -> 2040.3224 | W18: =+'Scenario 0'!L29/Dashboard!$E$16 -> 2101.532 | ... Z18: =+'Scenario 0'!O29/Dashboard!$E$16 -> 2296.4008
B20: Management Fee | C20: =+'Scenario 0'!E31 -> 0 | D20: =+'Scenario 0'!F31 -> 28199.61 | E20: =+'Scenario 0'!G31 -> 29045.598 | F20: =+'Scenario 0'!H31 -> 29916.966 | G20: =+'Scenario 0'!I31 -> 30814.475 | H20: =+'Scenario 0'!J31 -> 31738.909 | I20: =+'Scenario 0'!K31 -> 32691.077 | J20: =+'Scenario 0'!L31 -> 33671.809 | ... M20: =+'Scenario 0'!O31 -> 36794.095 | O20: Management Fee | P20: =+'Scenario 0'!E31/Dashboard!$E$16 -> 0 | Q20: =+'Scenario 0'!F31/Dashboard!$E$16 -> 391.66125 | R20: =+'Scenario 0'!G31/Dashboard!$E$16 -> 403.41109 | S20: =+'Scenario 0'!H31/Dashboard!$E$16 -> 415.51342 | T20: =+'Scenario 0'!I31/Dashboard!$E$16 -> 427.97882 | U20: =+'Scenario 0'!J31/Dashboard!$E$16 -> 440.81819 | V20: =+'Scenario 0'!K31/Dashboard!$E$16 -> 454.04273 | W20: =+'Scenario 0'!L31/Dashboard!$E$16 -> 467.66402 | ... Z20: =+'Scenario 0'!O31/Dashboard!$E$16 -> 511.0291
B21: Legal Expense | C21: =+'Scenario 0'!E32 -> 0 | D21: =+'Scenario 0'!F32 -> 6000 | E21: =+'Scenario 0'!G32 -> 6180 | F21: =+'Scenario 0'!H32 -> 6365.4 | G21: =+'Scenario 0'!I32 -> 6556.362 | H21: =+'Scenario 0'!J32 -> 6753.0529 | I21: =+'Scenario 0'!K32 -> 6955.6444 | J21: =+'Scenario 0'!L32 -> 7164.3138 | ... M21: =+'Scenario 0'!O32 -> 7828.6391 | O21: Legal Expense | P21: =+'Scenario 0'!E32/Dashboard!$E$16 -> 0 | Q21: =+'Scenario 0'!F32/Dashboard!$E$16 -> 83.333333 | R21: =+'Scenario 0'!G32/Dashboard!$E$16 -> 85.833333 | S21: =+'Scenario 0'!H32/Dashboard!$E$16 -> 88.408333 | T21: =+'Scenario 0'!I32/Dashboard!$E$16 -> 91.060583 | U21: =+'Scenario 0'!J32/Dashboard!$E$16 -> 93.792401 | V21: =+'Scenario 0'!K32/Dashboard!$E$16 -> 96.606173 | W21: =+'Scenario 0'!L32/Dashboard!$E$16 -> 99.504358 | ... Z21: =+'Scenario 0'!O32/Dashboard!$E$16 -> 108.7311
B22: Office Expense | C22: =+'Scenario 0'!E33 -> 0 | D22: =+'Scenario 0'!F33 -> 10800 | E22: =+'Scenario 0'!G33 -> 11124 | F22: =+'Scenario 0'!H33 -> 11457.72 | G22: =+'Scenario 0'!I33 -> 11801.452 | H22: =+'Scenario 0'!J33 -> 12155.495 | I22: =+'Scenario 0'!K33 -> 12520.16 | J22: =+'Scenario 0'!L33 -> 12895.765 | ... M22: =+'Scenario 0'!O33 -> 14091.55 | O22: Office Expense | P22: =+'Scenario 0'!E33/Dashboard!$E$16 -> 0 | Q22: =+'Scenario 0'!F33/Dashboard!$E$16 -> 150 | R22: =+'Scenario 0'!G33/Dashboard!$E$16 -> 154.5 | S22: =+'Scenario 0'!H33/Dashboard!$E$16 -> 159.135 | T22: =+'Scenario 0'!I33/Dashboard!$E$16 -> 163.90905 | U22: =+'Scenario 0'!J33/Dashboard!$E$16 -> 168.82632 | V22: =+'Scenario 0'!K33/Dashboard!$E$16 -> 173.89111 | W22: =+'Scenario 0'!L33/Dashboard!$E$16 -> 179.10784 | ... Z22: =+'Scenario 0'!O33/Dashboard!$E$16 -> 195.71598
B23: Travel Cost | C23: =+'Scenario 0'!E34 -> 0 | D23: =+'Scenario 0'!F34 -> 6000 | E23: =+'Scenario 0'!G34 -> 6180 | F23: =+'Scenario 0'!H34 -> 6365.4 | G23: =+'Scenario 0'!I34 -> 6556.362 | H23: =+'Scenario 0'!J34 -> 6753.0529 | I23: =+'Scenario 0'!K34 -> 6955.6444 | J23: =+'Scenario 0'!L34 -> 7164.3138 | ... M23: =+'Scenario 0'!O34 -> 7828.6391 | O23: Travel Cost | P23: =+'Scenario 0'!E34/Dashboard!$E$16 -> 0 | Q23: =+'Scenario 0'!F34/Dashboard!$E$16 -> 83.333333 | R23: =+'Scenario 0'!G34/Dashboard!$E$16 -> 85.833333 | S23: =+'Scenario 0'!H34/Dashboard!$E$16 -> 88.408333 | T23: =+'Scenario 0'!I34/Dashboard!$E$16 -> 91.060583 | U23: =+'Scenario 0'!J34/Dashboard!$E$16 -> 93.792401 | V23: =+'Scenario 0'!K34/Dashboard!$E$16 -> 96.606173 | W23: =+'Scenario 0'!L34/Dashboard!$E$16 -> 99.504358 | ... Z23: =+'Scenario 0'!O34/Dashboard!$E$16 -> 108.7311
B24: Audit Expense | C24: =+'Scenario 0'!E35 -> 0 | D24: =+'Scenario 0'!F35 -> 6500 | E24: =+'Scenario 0'!G35 -> 6695 | F24: =+'Scenario 0'!H35 -> 6895.85 | G24: =+'Scenario 0'!I35 -> 7102.7255 | H24: =+'Scenario 0'!J35 -> 7315.8073 | I24: =+'Scenario 0'!K35 -> 7535.2815 | J24: =+'Scenario 0'!L35 -> 7761.3399 | ... M24: =+'Scenario 0'!O35 -> 8481.0257 | O24: Audit Expense | P24: =+'Scenario 0'!E35/Dashboard!$E$16 -> 0 | Q24: =+'Scenario 0'!F35/Dashboard!$E$16 -> 90.277778 | R24: =+'Scenario 0'!G35/Dashboard!$E$16 -> 92.986111 | S24: =+'Scenario 0'!H35/Dashboard!$E$16 -> 95.775694 | T24: =+'Scenario 0'!I35/Dashboard!$E$16 -> 98.648965 | U24: =+'Scenario 0'!J35/Dashboard!$E$16 -> 101.60843 | V24: =+'Scenario 0'!K35/Dashboard!$E$16 -> 104.65669 | W24: =+'Scenario 0'!L35/Dashboard!$E$16 -> 107.79639 | ... Z24: =+'Scenario 0'!O35/Dashboard!$E$16 -> 117.79202
B25: Advertising | C25: =+'Scenario 0'!E36 -> 0 | D25: =+'Scenario 0'!F36 -> 0 | E25: =+'Scenario 0'!G36 -> 0 | F25: =+'Scenario 0'!H36 -> 0 | G25: =+'Scenario 0'!I36 -> 0 | H25: =+'Scenario 0'!J36 -> 0 | I25: =+'Scenario 0'!K36 -> 0 | J25: =+'Scenario 0'!L36 -> 0 | ... M25: =+'Scenario 0'!O36 -> 0 | O25: Advertising | P25: =+'Scenario 0'!E36/Dashboard!$E$16 -> 0 | Q25: =+'Scenario 0'!F36/Dashboard!$E$16 -> 0 | R25: =+'Scenario 0'!G36/Dashboard!$E$16 -> 0 | S25: =+'Scenario 0'!H36/Dashboard!$E$16 -> 0 | T25: =+'Scenario 0'!I36/Dashboard!$E$16 -> 0 | U25: =+'Scenario 0'!J36/Dashboard!$E$16 -> 0 | V25: =+'Scenario 0'!K36/Dashboard!$E$16 -> 0 | W25: =+'Scenario 0'!L36/Dashboard!$E$16 -> 0 | ... Z25: =+'Scenario 0'!O36/Dashboard!$E$16 -> 0
B26: Training Charge | C26: =+'Scenario 0'!E37 -> 0 | D26: =+'Scenario 0'!F37 -> 0 | E26: =+'Scenario 0'!G37 -> 0 | F26: =+'Scenario 0'!H37 -> 0 | G26: =+'Scenario 0'!I37 -> 0 | H26: =+'Scenario 0'!J37 -> 0 | I26: =+'Scenario 0'!K37 -> 0 | J26: =+'Scenario 0'!L37 -> 0 | ... M26: =+'Scenario 0'!O37 -> 0 | O26: Training Charge | P26: =+'Scenario 0'!E37/Dashboard!$E$16 -> 0 | Q26: =+'Scenario 0'!F37/Dashboard!$E$16 -> 0 | R26: =+'Scenario 0'!G37/Dashboard!$E$16 -> 0 | S26: =+'Scenario 0'!H37/Dashboard!$E$16 -> 0 | T26: =+'Scenario 0'!I37/Dashboard!$E$16 -> 0 | U26: =+'Scenario 0'!J37/Dashboard!$E$16 -> 0 | V26: =+'Scenario 0'!K37/Dashboard!$E$16 -> 0 | W26: =+'Scenario 0'!L37/Dashboard!$E$16 -> 0 | ... Z26: =+'Scenario 0'!O37/Dashboard!$E$16 -> 0
... B48: Total Operating and Maint. | C48: =+'Scenario 0'!E59 -> 0 | D48: =+'Scenario 0'!F59 -> 15060 | E48: =+'Scenario 0'!G59 -> 15511.8 | F48: =+'Scenario 0'!H59 -> 15977.154 | G48: =+'Scenario 0'!I59 -> 16456.469 | H48: =+'Scenario 0'!J59 -> 16950.163 | I48: =+'Scenario 0'!K59 -> 17458.668 | J48: =+'Scenario 0'!L59 -> 17982.428 | ... M48: =+'Scenario 0'!O59 -> 19649.884 | O48: Total Operating and Maint. | P48: =+'Scenario 0'!E59/Dashboard!$E$16 -> 0 | Q48: =+'Scenario 0'!F59/Dashboard!$E$16 -> 209.16667 | R48: =+'Scenario 0'!G59/Dashboard!$E$16 -> 215.44167 | S48: =+'Scenario 0'!H59/Dashboard!$E$16 -> 221.90492 | T48: =+'Scenario 0'!I59/Dashboard!$E$16 -> 228.56206 | U48: =+'Scenario 0'!J59/Dashboard!$E$16 -> 235.41893 | V48: =+'Scenario 0'!K59/Dashboard!$E$16 -> 242.48149 | W48: =+'Scenario 0'!L59/Dashboard!$E$16 -> 249.75594 | ... Z48: =+'Scenario 0'!O59/Dashboard!$E$16 -> 272.91506
C49: =+'Scenario 0'!R60/Dashboard!$E$16 -> 0 | D49: =+'Scenario 0'!S60/Dashboard!$E$16 -> 0 | E49: =+'Scenario 0'!T60/Dashboard!$E$16 -> 0 | F49: =+'Scenario 0'!U60/Dashboard!$E$16 -> 0 | G49: =+'Scenario 0'!V60/Dashboard!$E$16 -> 0 | H49: =+'Scenario 0'!W60/Dashboard!$E$16 -> 0 | I49: =+'Scenario 0'!X60/Dashboard!$E$16 -> 0 | J49: =+'Scenario 0'!Y60/Dashboard!$E$16 -> 0 | ... M49: =+'Scenario 0'!AB60/Dashboard!$E$16 -> 0 | P49: =+'Scenario 0'!E60/Dashboard!$E$16 -> 0 | Q49: =+'Scenario 0'!F60/Dashboard!$E$16 -> 0 | R49: =+'Scenario 0'!G60/Dashboard!$E$16 -> 0 | S49: =+'Scenario 0'!H60/Dashboard!$E$16 -> 0 | T49: =+'Scenario 0'!I60/Dashboard!$E$16 -> 0 | U49: =+'Scenario 0'!J60/Dashboard!$E$16 -> 0 | V49: =+'Scenario 0'!K60/Dashboard!$E$16 -> 0 | W49: =+'Scenario 0'!L60/Dashboard!$E$16 -> 0 | ... Z49: =+'Scenario 0'!O60/Dashboard!$E$16 -> 0
B50: Landscaping/Grounds Contract | C50: =+'Scenario 0'!E61 -> 0 | D50: =+'Scenario 0'!F61 -> 0 | E50: =+'Scenario 0'!G61 -> 0 | F50: =+'Scenario 0'!H61 -> 0 | G50: =+'Scenario 0'!I61 -> 0 | H50: =+'Scenario 0'!J61 -> 0 | I50: =+'Scenario 0'!K61 -> 0 | J50: =+'Scenario 0'!L61 -> 0 | ... M50: =+'Scenario 0'!O61 -> 0 | O50: Landscaping/Grounds Contract | P50: =+'Scenario 0'!E61/Dashboard!$E$16 -> 0 | Q50: =+'Scenario 0'!F61/Dashboard!$E$16 -> 0 | R50: =+'Scenario 0'!G61/Dashboard!$E$16 -> 0 | S50: =+'Scenario 0'!H61/Dashboard!$E$16 -> 0 | T50: =+'Scenario 0'!I61/Dashboard!$E$16 -> 0 | U50: =+'Scenario 0'!J61/Dashboard!$E$16 -> 0 | V50: =+'Scenario 0'!K61/Dashboard!$E$16 -> 0 | W50: =+'Scenario 0'!L61/Dashboard!$E$16 -> 0 | ... Z50: =+'Scenario 0'!O61/Dashboard!$E$16 -> 0
B51: Fire & Safety System | C51: =+'Scenario 0'!E62 -> 0 | D51: =+'Scenario 0'!F62 -> 0 | E51: =+'Scenario 0'!G62 -> 0 | F51: =+'Scenario 0'!H62 -> 0 | G51: =+'Scenario 0'!I62 -> 0 | H51: =+'Scenario 0'!J62 -> 0 | I51: =+'Scenario 0'!K62 -> 0 | J51: =+'Scenario 0'!L62 -> 0 | ... M51: =+'Scenario 0'!O62 -> 0 | O51: Fire & Safety System | P51: =+'Scenario 0'!E62/Dashboard!$E$16 -> 0 | Q51: =+'Scenario 0'!F62/Dashboard!$E$16 -> 0 | R51: =+'Scenario 0'!G62/Dashboard!$E$16 -> 0 | S51: =+'Scenario 0'!H62/Dashboard!$E$16 -> 0 | T51: =+'Scenario 0'!I62/Dashboard!$E$16 -> 0 | U51: =+'Scenario 0'!J62/Dashboard!$E$16 -> 0 | V51: =+'Scenario 0'!K62/Dashboard!$E$16 -> 0 | W51: =+'Scenario 0'!L62/Dashboard!$E$16 -> 0 | ... Z51: =+'Scenario 0'!O62/Dashboard!$E$16 -> 0
B52: Security | C52: =+'Scenario 0'!E63 -> 0 | D52: =+'Scenario 0'!F63 -> 0 | E52: =+'Scenario 0'!G63 -> 0 | F52: =+'Scenario 0'!H63 -> 0 | G52: =+'Scenario 0'!I63 -> 0 | H52: =+'Scenario 0'!J63 -> 0 | I52: =+'Scenario 0'!K63 -> 0 | J52: =+'Scenario 0'!L63 -> 0 | ... M52: =+'Scenario 0'!O63 -> 0 | O52: Security | P52: =+'Scenario 0'!E63/Dashboard!$E$16 -> 0 | Q52: =+'Scenario 0'!F63/Dashboard!$E$16 -> 0 | R52: =+'Scenario 0'!G63/Dashboard!$E$16 -> 0 | S52: =+'Scenario 0'!H63/Dashboard!$E$16 -> 0 | T52: =+'Scenario 0'!I63/Dashboard!$E$16 -> 0 | U52: =+'Scenario 0'!J63/Dashboard!$E$16 -> 0 | V52: =+'Scenario 0'!K63/Dashboard!$E$16 -> 0 | W52: =+'Scenario 0'!L63/Dashboard!$E$16 -> 0 | ... Z52: =+'Scenario 0'!O63/Dashboard!$E$16 -> 0
B53: Pest Control | C53: =+'Scenario 0'!E64 -> 0 | D53: =+'Scenario 0'!F64 -> 0 | E53: =+'Scenario 0'!G64 -> 0 | F53: =+'Scenario 0'!H64 -> 0 | G53: =+'Scenario 0'!I64 -> 0 | H53: =+'Scenario 0'!J64 -> 0 | I53: =+'Scenario 0'!K64 -> 0 | J53: =+'Scenario 0'!L64 -> 0 | ... M53: =+'Scenario 0'!O64 -> 0 | O53: Pest Control | P53: =+'Scenario 0'!E64/Dashboard!$E$16 -> 0 | Q53: =+'Scenario 0'!F64/Dashboard!$E$16 -> 0 | R53: =+'Scenario 0'!G64/Dashboard!$E$16 -> 0 | S53: =+'Scenario 0'!H64/Dashboard!$E$16 -> 0 | T53: =+'Scenario 0'!I64/Dashboard!$E$16 -> 0 | U53: =+'Scenario 0'!J64/Dashboard!$E$16 -> 0 | V53: =+'Scenario 0'!K64/Dashboard!$E$16 -> 0 | W53: =+'Scenario 0'!L64/Dashboard!$E$16 -> 0 | ... Z53: =+'Scenario 0'!O64/Dashboard!$E$16 -> 0
B54: Misc. Contracts | C54: =+'Scenario 0'!E65 -> 0 | D54: =+'Scenario 0'!F65 -> 0 | E54: =+'Scenario 0'!G65 -> 0 | F54: =+'Scenario 0'!H65 -> 0 | G54: =+'Scenario 0'!I65 -> 0 | H54: =+'Scenario 0'!J65 -> 0 | I54: =+'Scenario 0'!K65 -> 0 | J54: =+'Scenario 0'!L65 -> 0 | ... M54: =+'Scenario 0'!O65 -> 0 | O54: Misc. Contracts | P54: =+'Scenario 0'!E65/Dashboard!$E$16 -> 0 | Q54: =+'Scenario 0'!F65/Dashboard!$E$16 -> 0 | R54: =+'Scenario 0'!G65/Dashboard!$E$16 -> 0 | S54: =+'Scenario 0'!H65/Dashboard!$E$16 -> 0 | T54: =+'Scenario 0'!I65/Dashboard!$E$16 -> 0 | U54: =+'Scenario 0'!J65/Dashboard!$E$16 -> 0 | V54: =+'Scenario 0'!K65/Dashboard!$E$16 -> 0 | W54: =+'Scenario 0'!L65/Dashboard!$E$16 -> 0 | ... Z54: =+'Scenario 0'!O65/Dashboard!$E$16 -> 0
B55: Elevator Costs | C55: =+'Scenario 0'!E66 -> 0 | D55: =+'Scenario 0'!F66 -> 0 | E55: =+'Scenario 0'!G66 -> 0 | F55: =+'Scenario 0'!H66 -> 0 | G55: =+'Scenario 0'!I66 -> 0 | H55: =+'Scenario 0'!J66 -> 0 | I55: =+'Scenario 0'!K66 -> 0 | J55: =+'Scenario 0'!L66 -> 0 | ... M55: =+'Scenario 0'!O66 -> 0 | O55: Elevator Costs | P55: =+'Scenario 0'!E66/Dashboard!$E$16 -> 0 | Q55: =+'Scenario 0'!F66/Dashboard!$E$16 -> 0 | R55: =+'Scenario 0'!G66/Dashboard!$E$16 -> 0 | S55: =+'Scenario 0'!H66/Dashboard!$E$16 -> 0 | T55: =+'Scenario 0'!I66/Dashboard!$E$16 -> 0 | U55: =+'Scenario 0'!J66/Dashboard!$E$16 -> 0 | V55: =+'Scenario 0'!K66/Dashboard!$E$16 -> 0 | W55: =+'Scenario 0'!L66/Dashboard!$E$16 -> 0 | ... Z55: =+'Scenario 0'!O66/Dashboard!$E$16 -> 0
B56: Snow | C56: =+'Scenario 0'!E67 -> 0 | D56: =+'Scenario 0'!F67 -> 0 | E56: =+'Scenario 0'!G67 -> 0 | F56: =+'Scenario 0'!H67 -> 0 | G56: =+'Scenario 0'!I67 -> 0 | H56: =+'Scenario 0'!J67 -> 0 | I56: =+'Scenario 0'!K67 -> 0 | J56: =+'Scenario 0'!L67 -> 0 | ... M56: =+'Scenario 0'!O67 -> 0 | O56: Snow | P56: =+'Scenario 0'!E67/Dashboard!$E$16 -> 0 | Q56: =+'Scenario 0'!F67/Dashboard!$E$16 -> 0 | R56: =+'Scenario 0'!G67/Dashboard!$E$16 -> 0 | S56: =+'Scenario 0'!H67/Dashboard!$E$16 -> 0 | T56: =+'Scenario 0'!I67/Dashboard!$E$16 -> 0 | U56: =+'Scenario 0'!J67/Dashboard!$E$16 -> 0 | V56: =+'Scenario 0'!K67/Dashboard!$E$16 -> 0 | W56: =+'Scenario 0'!L67/Dashboard!$E$16 -> 0 | ... Z56: =+'Scenario 0'!O67/Dashboard!$E$16 -> 0
B57: Misc. Operating & Maint. | C57: =+'Scenario 0'!E68 -> 0 | D57: =+'Scenario 0'!F68 -> 0 | E57: =+'Scenario 0'!G68 -> 0 | F57: =+'Scenario 0'!H68 -> 0 | G57: =+'Scenario 0'!I68 -> 0 | H57: =+'Scenario 0'!J68 -> 0 | I57: =+'Scenario 0'!K68 -> 0 | J57: =+'Scenario 0'!L68 -> 0 | ... M57: =+'Scenario 0'!O68 -> 0 | O57: Misc. Operating & Maint. | P57: =+'Scenario 0'!E68/Dashboard!$E$16 -> 0 | Q57: =+'Scenario 0'!F68/Dashboard!$E$16 -> 0 | R57: =+'Scenario 0'!G68/Dashboard!$E$16 -> 0 | S57: =+'Scenario 0'!H68/Dashboard!$E$16 -> 0 | T57: =+'Scenario 0'!I68/Dashboard!$E$16 -> 0 | U57: =+'Scenario 0'!J68/Dashboard!$E$16 -> 0 | V57: =+'Scenario 0'!K68/Dashboard!$E$16 -> 0 | W57: =+'Scenario 0'!L68/Dashboard!$E$16 -> 0 | ... Z57: =+'Scenario 0'!O68/Dashboard!$E$16 -> 0
